Workbook

Sheet Start Here
A1: Backend + AI Engineer Marathon v4: Daily Planner
A2: Wed 04 Nov 2026 to Sun 30 May 2027 | 30 weeks | ~25 h/week | companion: Marathon_Roadmap_v4.docx
A5: How to use (60 seconds)
A6: 1. Open 'Today' | B6: It shows today's card, the steps, the DONE WHEN goal, the LARP topic and the WIN rule. That is all you need for the day.
A7: 2. Work the card | B7: 22:00-23:45: project card (Read 10 / Build 70 / Verify 15 / Commit + log 10). 23:45-01:00: LARP slot with the tutor prompt (sheet 'Tutor Prompts') + the questions in 'LARP Bank'.
A8: 3. Tick it | B8: 'Daily Plan' column A (☐ -> ☑) when the WIN rule is met. Column R for your DSA problem in office. Rows turn green; today's row is highlighted.
A9: 4. Sunday review | B9: Weekly Plan shows % done per week. Missed more than 2 cards? Move dates, don't cram (rules in the roadmap).
A10: 5. Yellow cells are yours | B10: Notes, Job Tracker, Interview Log, Story Bank, Design Choices answers, scores. Rows marked EXAMPLE show the format.
A12: Your week
A13: Mon-Thu | B13: 22:00-23:45 PROJECT | 23:45-01:00 LARP (teach 25, quiz 20, interview + scenarios 25, flashcards 5)
A14: Fri | B14: 22:00-23:45 BUFFER (carry-over, else polish + applications) | 23:45-01:00 WEEKLY MOCK interview
A15: Sat (5 h + 1 optional) | B15: 10:30-13:30 PROJECT | 14:30-15:30 BACKEND LAB | 16:00-17:00 JOB HUNT | 17:00-18:00 optional buffer
A16: Sun (5 h) | B16: 10:30-13:00 PROJECT | 14:00-15:00 MOCK & STORY | 15:00-16:00 READ / CERT (AI-102) | 16:00-16:30 WEEKLY REVIEW
A17: DSA | B17: Not scheduled here: you do it in office. Tick column R.
A19: Gates
A20: Gate 0 | B20: Sun 22 Nov 2026: Resume v1, LinkedIn, GitHub ready (DocuLens with hybrid search and first eval table). First 3 applications; 8/week next week. Interviews are practice and market information.
A21: Gate 1 | B21: Sun 06 Dec 2026: DocuLens v1 deployed on Azure with eval report and demo. Resume v2. 10-15 applications/week + 5 referral asks.
A22: DocuLens v1.5 | B22: Sun 13 Dec 2026: Workflow automation released: claim intake, review queue, webhooks, text-to-SQL, workflow eval. Resume bullets updated.
A23: Gate 2 | B23: Sun 17 Jan 2027: AI SRE Copilot v1 finished. Resume v3 with two projects. Aim at AI-agent / LLM-engineer roles.
A24: PDF Translator v1.0 | B24: Sun 14 Feb 2027: Your PRD built (phases 1-8) + shared AI gateway. Resume v4 with three projects.
A25: AI-102 exam | B25: Sat 20 Feb 2027: Azure AI Engineer Associate (company-paid). Check the current exam code on Microsoft Learn before booking.
A26: Offer rule | B26: Take the first offer that clears your pay bar AND has real engineering substance. Then drop to maintenance mode (roadmap section 9).
A28: Rules that keep it alive
A29: Minimum viable day | B29: Exhausted? 25 minutes of the card's first step + 15 minutes of LARP questions aloud. Tick nothing, but keep the streak in Notes.
A30: One card, one session | B30: Never pull tomorrow's card forward. If unfinished: clean commit + one carry-over line; Friday absorbs it.
A31: Stop at 01:00 | B31: You wake at 8:30. Sleep is part of the plan.
A32: Explain every line | B32: Use Claude Code/Copilot freely, but end each session with 'quiz me on today's code'.
A33: Never edit eval labels | B33: Fix prompts and tools, never the golden answers. That is what makes your numbers quotable.
A35: Progress
A36: Days ticked | B36: =COUNTIF('Daily Plan'!$A$2:$A$209,"☑")&" of "&COUNTA('Daily Plan'!$B$2:$B$209)
A37: Project cards done | B37: =COUNTIFS('Daily Plan'!$A$2:$A$209,"☑",'Daily Plan'!$H$2:$H$209,"<>BUF",'Daily Plan'!$H$2:$H$209,"<>")
A38: DSA days (office) | B38: =COUNTIF('Daily Plan'!$R$2:$R$209,"☑")
A39: Applications logged | B39: =COUNTA('Job Tracker'!$A$7:$A$400)
A40: Interview questions logged | B40: =COUNTA('Interview Log'!$D$7:$D$400)

Sheet Today
A1: Today
A2: Opens on today's date. Type any date in B3 (yellow) to preview that day; clear it to go back to today.
A3: Preview date (optional)
A4: Showing | B4: =IF(ISNUMBER(B3),B3,MIN(MAX(TODAY(),'Daily Plan'!$B$2),'Daily Plan'!$B$209))
A5: Plan row | B5: =IFERROR(MATCH(B4,'Daily Plan'!$B$2:$B$209,0),"")
A6: Week | B6: =IF($B$5="","",INDEX('Daily Plan'!$D$2:$D$209,$B$5)&"")
A7: Stage | B7: =IF($B$5="","",INDEX('Daily Plan'!$E$2:$E$209,$B$5)&"")
A8: Slot 1 | B8: =IF($B$5="","",INDEX('Daily Plan'!$G$2:$G$209,$B$5)&"")
A9: Card | B9: =IF($B$5="","",INDEX('Daily Plan'!$H$2:$H$209,$B$5)&"")
A10: Task | B10: =IF($B$5="","",INDEX('Daily Plan'!$I$2:$I$209,$B$5)&"")
A11: How (steps) | B11: =IF($B$5="","",INDEX('Daily Plan'!$J$2:$J$209,$B$5)&"")
A12: DONE WHEN (end goal) | B12: =IF($B$5="","",INDEX('Daily Plan'!$K$2:$K$209,$B$5)&"")
A13: Learn first | B13: =IF($B$5="","",INDEX('Daily Plan'!$L$2:$L$209,$B$5)&"")
A14: Slot 2 | B14: =IF($B$5="","",INDEX('Daily Plan'!$M$2:$M$209,$B$5)&"")
A15: LARP / mock | B15: =IF($B$5="","",INDEX('Daily Plan'!$N$2:$N$209,$B$5)&"")
A16: Extra blocks | B16: =IF($B$5="","",INDEX('Daily Plan'!$O$2:$O$209,$B$5)&"")
A17: Day is a WIN when | B17: =IF($B$5="","",INDEX('Daily Plan'!$P$2:$P$209,$B$5)&"")
A18: Milestone | B18: =IF($B$5="","",INDEX('Daily Plan'!$S$2:$S$209,$B$5)&"")
A20: Tomorrow | B20: =IF($B$5="","",IFERROR(INDEX('Daily Plan'!$H$2:$H$209,$B$5+1)&" "&INDEX('Daily Plan'!$I$2:$I$209,$B$5+1),""))
A21: Progress | B21: =COUNTIF('Daily Plan'!$A$2:$A$209,"☑")&" of "&COUNTA('Daily Plan'!$B$2:$B$209)&" days ticked; "&COUNTIF('Daily Plan'!$R$2:$R$209,"☑")&" DSA days"

Sheet Daily Plan
A1: Done | B1: Date | C1: Day | D1: Wk | E1: Stage | F1: Hrs | G1: Slot 1 | H1: Card | I1: Task | J1: How (steps) | K1: Done when = end goal of the day | L1: Learn first | M1: Slot 2 | N1: LARP / mock | O1: Weekend + Friday extra blocks | P1: Day is a WIN when | Q1: Apply quota (week) | R1: DSA @ office | S1: Milestone / gate | T1: Notes / carry-over
A2: ☐ | B2: 46330 | C2: Wed | D2: 1 | E2: 1: DocuLens | F2: 3 | G2: 22:00-23:45 PROJECT (105 min) | H2: D01 | I2: Dev setup + repo + hello FastAPI | J2: 1. Install WSL2 (Ubuntu), Docker Desktop with WSL integration, VS Code + WSL extension, git, uv. Work inside WSL from now on (Celery, Tesseract and k8s tooling behave better there). 2. uv init doculens; add fastapi, uvicorn[standard], pydantic-settings; dev deps: pytest, pytest-asyncio, httpx, ruff, mypy, pre-commit. 3. Layout: app/main.py (app factory), app/api/routes/health.py, app/core/config.py, tests/, docs/decisions/, docs/LOG.md. 4. GET /health returns {"status":"ok","version":...}. Write one test with httpx.AsyncClient + ASGITransport. 5. Makefile (run from WSL): make dev, make test, make lint. Add pre-commit with ruff + ruff-format. 6. Create GitHub repo, push, write a 5-line README (what it will be). Stretch: Add a GitHub Actions workflow that runs `make lint test` (you will formalise CI in D25). | K2: `make test` is green, `make lint` is clean, repo is on GitHub, and `docker run hello-world` works inside WSL. | L2: uv docs (docs.astral.sh/uv) 'Projects' page; FastAPI tutorial 'First Steps' and 'Testing' (fastapi.tiangolo.com); WSL2 + Docker Desktop install guide (learn.microsoft.com/windows/wsl). | M2: 23:45-01:00 LARP (75 min) | N2: L01 Python async/await and the event loop | P2: WIN = project 'Done when' met and pushed (or one clean carry-over line in docs/LOG.md) + LARP quiz scored, misses written as flashcards + DSA ticked (office). | R2: ☐ | S2: Marathon starts tonight at 22:00 with D01.
A3: ☐ | B3: 46331 | C3: Thu | D3: 1 | E3: 1: DocuLens | F3: 3 | G3: 22:00-23:45 PROJECT (105 min) | H3: D02 | I3: Docker Compose: Postgres + pgvector + Redis, settings, readiness | J3: 1. docker-compose.yml: pgvector/pgvector:pg16 (volume, healthcheck pg_isready) and redis:7 (healthcheck redis-cli ping). 2. app/core/config.py: Settings(BaseSettings) with DATABASE_URL, REDIS_URL, ENV; .env.example committed, .env ignored. 3. app/db/session.py: async engine (asyncpg) + async_sessionmaker; FastAPI dependency get_session(). 4. GET /health/ready: runs SELECT 1 and Redis PING concurrently with asyncio.gather and a 1 s timeout each; returns per-dependency status and 503 if any fails. 5. Test: ready endpoint returns 200 with compose up; unit test with a failing fake returns 503. Stretch: Write docs/decisions/0001-one-database.md: why Postgres+pgvector instead of a separate vector DB for v1. | K3: `docker compose up -d` then `curl /health/ready` returns {"db":"ok","redis":"ok"}; stopping Redis makes it return 503. | L3: pgvector README (github.com/pgvector/pgvector) 'Docker' + 'Getting started'; SQLAlchemy 2.0 'Asynchronous I/O' page; pydantic-settings docs. | M3: 23:45-01:00 LARP (75 min) | N3: L02 FastAPI internals: dependency injection, Pydantic v2, sync vs async | P3: WIN = project 'Done when' met and pushed (or one clean carry-over line in docs/LOG.md) + LARP quiz scored, misses written as flashcards + DSA ticked (office). | R3: ☐
A4: ☐ | B4: 46332 | C4: Fri | D4: 1 | E4: 1: DocuLens | F4: 3 | G4: 22:00-23:45 PROJECT (105 min) | H4: D03 | I4: Alembic + data model v1 | J4: 1. alembic init -t async migrations; point env.py at your Base metadata and settings. 2. Models: documents(id uuid pk, workspace_id uuid null, filename, sha256 unique-per-workspace, status, page_count, metadata jsonb, created_at). 3. chunks(id uuid, document_id fk, page int, bbox jsonb, section text, text text, token_count int, content_hash text, embedding vector(384), metadata jsonb). 4. First migration runs CREATE EXTENSION IF NOT EXISTS vector; autogenerate the rest and READ the generated file before applying. 5. Test: upgrade head on an empty DB, insert one document + chunk, downgrade base. | K4: `alembic upgrade head` and `alembic downgrade base` both succeed on a clean database and the round-trip test passes. | L4: Alembic tutorial (alembic.sqlalchemy.org) 'Auto Generating Migrations'; pgvector 'Storing' section. | M4: 23:45-01:00 WEEKLY MOCK | N4: Weekly mock interview (Friday prompt). Topics: L01 Python async/await and the event loop, L02 FastAPI internals: dependency injection, Pydantic v2, sync vs async | P4: WIN = carry-over cleared (or the polish task done) + weekly mock scored with your 5 'rewrite' answers listed. | R4: ☐
A5: ☐ | B5: 46333 | C5: Sat | D5: 1 | E5: 1: DocuLens | F5: 5 | G5: 10:30-13:30 PROJECT (3 h) | H5: D04 | I5: Upload + PyMuPDF extraction with coordinates | J5: 1. POST /documents (multipart): check magic bytes %PDF-, size cap (e.g. 25 MB), page cap; compute sha256 while reading. 2. If the same sha256 already exists in the workspace, return the existing document (200) instead of creating a duplicate (idempotent upload). Document the 200 vs 409 choice. 3. Save the file under ./storage/{document_id}.pdf behind a Storage interface (LocalStorage now, Blob later). 4. extract_blocks(path) -> list[Block(page, bbox, text, font_size, is_bold)] using page.get_text('dict'); skip empty/whitespace spans. 5. Pick a corpus: 5-8 public insurance policy wordings (recommended: in week 6 your claim workflow checks claims against these same policies) or pharma drug labels, + 1 scanned PDF. Put 2 small ones in tests/fixtures/. 6. Tests: block count > 0 for the fixture; every bbox has 4 floats inside the page rect; second upload returns the same id. Stretch: Print the 10 largest-font blocks of a document: those are your heading candidates for D05. | K5: Uploading the same PDF twice returns the same document_id, and the extraction test proves every block has a page number and a valid bbox. | L5: PyMuPDF docs 'Text extraction' + 'Appendix 1: Details on Text Extraction' (page.get_text('dict')); FastAPI 'Request Files'. | O5: 14:30-15:30 BACKEND LAB: LAB00 HTTP from raw sockets. Done when: Python socket server that parses a GET request and returns a valid HTTP/1.1 response; curl works against it. 16:00-17:00 JOB HUNT: LinkedIn: headline 'AI Engineer | LLM agents, RAG | Python, FastAPI | Copilot Studio', About (5 lines), skills; open-to-work for recruiters only. 17:00-18:00 OPTIONAL: carry-over, tests, docs (never tomorrow's card) | P5: WIN = project 'Done when' met + lab 'Done when' met + job-hunt task done. | Q5: 0 | R5: ☐
A6: ☐ | B6: 46334 | C6: Sun | D6: 1 | E6: 1: DocuLens | F6: 5 | G6: 10:30-13:00 PROJECT (2.5 h) | H6: D05 | I6: Chunking strategies v1 (layout-aware) | J6: 1. Chunker A, fixed: 400 tokens, 60 overlap (tiktoken cl100k as the counter). 2. Chunker B, recursive: split on paragraph -> sentence -> word to stay under 400 tokens. 3. Chunker C, layout-aware: walk blocks in reading order; a block whose font size is above the page median (or bold + short) starts a new section; never merge across sections; keep the heading path ('3 Exclusions > 3.2 Pre-existing') in chunk.section. 4. Every chunk keeps page, union bbox of its blocks, token_count and content_hash (sha256 of normalised text). 5. scripts/chunk_stats.py prints count / mean / p95 tokens per strategy for the corpus. | K6: Unit tests pass for all three chunkers, chunk_stats prints a table for your corpus, and docs/decisions/0002-chunking.md states your provisional pick (to be confirmed by eval in D16). | L6: Pinecone 'Chunking Strategies for LLM Applications' article; LangChain RecursiveCharacterTextSplitter docs (concept only); tiktoken README. | O6: 14:00-15:00 MOCK & STORY: Write and record 'Tell me about yourself' v1 (90 s). Write 5 bullets describing your Copilot Studio work in engineering terms (integrations, APIs, data, auth, deployment/ALM). 15:00-16:00 READ / CERT: Read Anthropic's 'Building effective agents' essay; write 10 bullets in your own words. 16:00-16:30 WEEKLY REVIEW: tick the week, scorecard (project cards x/6, LARP x/4, mock score, applications x/0), 3 lines in LOG.md, read next week's first card. | P6: WIN = project 'Done when' met + story/mock recorded + weekly review written (scorecard, 3 lines, next week's first card read). | R6: ☐
A7: ☐ | B7: 46335 | C7: Mon | D7: 2 | E7: 1: DocuLens | F7: 3 | G7: 22:00-23:45 PROJECT (105 min) | H7: D06 | I7: Embeddings + dense search on pgvector (HNSW) | J7: 1. EmbeddingProvider protocol: embed_documents(list[str]) / embed_query(str). Implement FastEmbedProvider (BAAI/bge-small-en-v1.5, 384-d, runs on CPU, free) and FakeEmbedder for tests. 2. Pipeline step: embed chunks in batches of 64; store vectors. 3. Migration: HNSW index USING hnsw (embedding vector_cosine_ops). 4. POST /search {query, k, mode:'dense'} -> chunks with score, page, section, document filename. 5. Run EXPLAIN on the search query and confirm the index is used (set enable_seqscan=off only to test). Stretch: Try ef_search 40 vs 200 on 10 queries and note latency vs result changes. | K7: A natural question ('what is not covered?') returns sensible top-5 chunks with page numbers, and EXPLAIN shows the HNSW index scan. | L7: pgvector README sections 'Querying', 'HNSW', 'Filtering'; fastembed README (qdrant/fastembed); MTEB leaderboard (concept: how models are compared). | M7: 23:45-01:00 LARP (75 min) | N7: L03 Embeddings and vector search (ANN, HNSW vs IVFFlat) | P7: WIN = project 'Done when' met and pushed (or one clean carry-over line in docs/LOG.md) + LARP quiz scored, misses written as flashcards + DSA ticked (office). | R7: ☐
A8: ☐ | B8: 46336 | C8: Tue | D8: 2 | E8: 1: DocuLens | F8: 3 | G8: 22:00-23:45 PROJECT (105 min) | H8: D07 | I8: Lexical leg: Postgres full-text search | J8: 1. Migration: generated column tsv tsvector GENERATED ALWAYS AS (to_tsvector('english', coalesce(section,'') || ' ' || text)) STORED + GIN index. 2. mode='lexical': websearch_to_tsquery + ts_rank_cd ordering, same response shape as dense. 3. Find 3 queries where lexical beats dense (exact clause id, rare term, acronym) and 3 where dense beats lexical (paraphrase). Write them in docs/notes/retrieval-examples.md - these are interview examples. 4. Note honestly: ts_rank_cd is not true BM25 (no IDF saturation tuning); record that as a known limit. Stretch: Add bm25s (pip) over the same chunks and compare top-5 for your 6 example queries. | K8: docs/notes/retrieval-examples.md lists at least 3 queries where lexical finds the right chunk and dense does not, and 3 the other way round. | L8: PostgreSQL docs chapter 12 'Full Text Search' (12.1-12.3, websearch_to_tsquery, ts_rank_cd); 'BM25' explanation (Elastic blog 'Practical BM25'). | M8: 23:45-01:00 LARP (75 min) | N8: L04 BM25 and full-text search | P8: WIN = project 'Done when' met and pushed (or one clean carry-over line in docs/LOG.md) + LARP quiz scored, misses written as flashcards + DSA ticked (office). | R8: ☐
A9: ☐ | B9: 46337 | C9: Wed | D9: 2 | E9: 1: DocuLens | F9: 3 | G9: 22:00-23:45 PROJECT (105 min) | H9: D08 | I9: Hybrid retrieval with Reciprocal Rank Fusion + metadata filters | J9: 1. Run dense and lexical legs concurrently (asyncio.gather), each returning top 30. 2. rrf(lists, k=60): score = sum(1/(k + rank)). Pure function + unit test with hand-made rankings. 3. Metadata filters applied INSIDE both legs (document_ids, doc_type, page range) - pre-filtering, not post-filtering. 4. mode='hybrid' is the default; debug=true returns each chunk's dense rank, lexical rank and fused score. Stretch: Add a weight per leg (weighted RRF) behind a setting; you'll tune it with eval data in W3. | K9: RRF unit test passes, and /search?debug=true shows per-leg ranks and the fused order for any query. | L9: Paper/summary: 'Reciprocal Rank Fusion outperforms Condorcet...' (Cormack et al. 2009) - read the abstract and formula only; pgvector 'Hybrid search' section. | M9: 23:45-01:00 LARP (75 min) | N9: L05 Hybrid search, Reciprocal Rank Fusion and metadata filtering | P9: WIN = project 'Done when' met and pushed (or one clean carry-over line in docs/LOG.md) + LARP quiz scored, misses written as flashcards + DSA ticked (office). | R9: ☐
A10: ☐ | B10: 46338 | C10: Thu | D10: 2 | E10: 1: DocuLens | F10: 3 | G10: 22:00-23:45 PROJECT (105 min) | H10: D09 | I10: Reranking with a cross-encoder | J10: 1. Reranker protocol + CrossEncoderReranker (sentence-transformers, BAAI/bge-reranker-base) + NoopReranker. 2. Rerank the fused top-30 down to top-5. Model call is CPU-bound: run it with run_in_threadpool / anyio.to_thread so the event loop is not blocked. 3. Load the model once at startup (lifespan), not per request. 4. Log rerank latency; scripts/bench_rerank.py prints p50/p95 for 20 queries. 5. Setting RERANK_ENABLED to switch it off (you will compare in eval). Stretch: Try top-20 vs top-50 candidates and note the latency change. | K10: debug output shows the order before and after reranking, and bench_rerank prints p50/p95 latency for 20 queries. | L10: sbert.net 'Cross-Encoders' + 'Retrieve & Re-Rank' pages; BAAI/bge-reranker-base model card. | M10: 23:45-01:00 LARP (75 min) | N10: L06 Rerankers: bi-encoders vs cross-encoders | P10: WIN = project 'Done when' met and pushed (or one clean carry-over line in docs/LOG.md) + LARP quiz scored, misses written as flashcards + DSA ticked (office). | R10: ☐
A11: ☐ | B11: 46339 | C11: Fri | D11: 2 | E11: 1: DocuLens | F11: 3 | G11: 22:00-23:45 BUFFER + POLISH | H11: BUF | I11: Carry-over first | J11: If no carry-over: README section 'How retrieval works' + raise test coverage of app/retrieval. | K11: No open carry-over from this week (or exactly one carried line in docs/LOG.md). | M11: 23:45-01:00 WEEKLY MOCK | N11: Weekly mock interview (Friday prompt). Topics: L03 Embeddings and vector search (ANN, HNSW vs IVFFlat), L04 BM25 and full-text search, L05 Hybrid search, Reciprocal Rank Fusion and metadata filtering, L06 Rerankers: bi-encoders vs cross-encoders | P11: WIN = carry-over cleared (or the polish task done) + weekly mock scored with your 5 'rewrite' answers listed. | R11: ☐
A12: ☐ | B12: 46340 | C12: Sat | D12: 2 | E12: 1: DocuLens | F12: 5 | G12: 10:30-13:30 PROJECT (3 h) | H12: D10 | I12: LLM layer: providers, structured output, grounded answers with citations | J12: 1. LLMProvider protocol: complete(messages, model, max_tokens, temperature, response_schema=None) -> LLMResult(text|parsed, usage, latency_ms, model, provider). 2. Adapters: OpenAICompatibleProvider (works for OpenAI and Gemini via base_url) and AnthropicProvider. FakeProvider for tests. Use the cheapest current model of each. 3. generate_structured(schema): ask for JSON matching the Pydantic schema; on ValidationError re-ask once with the error message; then fail with a typed error. 4. Answer schema: {answer: str, citations: list[chunk_id], confidence: float 0-1, unanswerable: bool}. 5. POST /ask: hybrid retrieve -> rerank -> prompt with numbered chunks -> structured answer -> reject citations that are not in the retrieved set. 6. Prompt says: answer only from the context, cite chunk ids, set unanswerable=true if the context does not contain the answer. Stretch: Return the bbox of each cited chunk so a UI could highlight it on the page. | K12: /ask answers a corpus question with valid citation ids (each maps to a page), an out-of-corpus question returns unanswerable=true, and a test proves invented citation ids are rejected. | L12: OpenAI docs 'Structured Outputs'; Anthropic docs 'Tool use' (for JSON via tools) and 'Increase output consistency'; Gemini 'OpenAI compatibility' page. | O12: 14:30-15:30 BACKEND LAB: LAB01 Cache-aside + stampede. Done when: Redis cache-aside over a slow DB call; 100 concurrent misses on expiry hit the DB 100 times, then a SET NX single-flight lock + jittered TTL brings it to 1. 16:00-17:00 JOB HUNT: Resume v1 draft (1 page): Copilot Studio work in engineering terms + DocuLens 'in progress' section. Build a JD keyword list from the JD Skill Matrix sheet. 17:00-18:00 OPTIONAL: carry-over, tests, docs (never tomorrow's card) | P12: WIN = project 'Done when' met + lab 'Done when' met + job-hunt task done. | Q12: 0 | R12: ☐
A13: ☐ | B13: 46341 | C13: Sun | D13: 2 | E13: 1: DocuLens | F13: 5 | G13: 10:30-13:00 PROJECT (2.5 h) | H13: D11 | I13: Streaming answers over SSE + conversation memory | J13: 1. POST /ask/stream returns text/event-stream: event 'token' for answer tokens, then one final event 'citations' with JSON, then 'done'. 2. Implement stream() on both providers (async generator). 3. Conversation: conversations + messages tables; /ask accepts conversation_id; last 6 turns are condensed into a standalone question before retrieval (LLM 'condense' step). 4. Handle client disconnect (request.is_disconnected) so you stop paying for tokens nobody reads. 5. Test the stream with httpx streaming client; manual test with curl -N. | K13: curl -N shows tokens arriving incrementally and a final citations event; a follow-up question ('and what about dental?') is rewritten into a standalone query that retrieves the right chunks. | L13: MDN 'Using server-sent events'; FastAPI 'StreamingResponse' (or sse-starlette README); OpenAI/Anthropic streaming docs. | O13: 14:00-15:00 MOCK & STORY: Record a 3-minute DocuLens architecture walkthrough of what exists; listen back; cut filler words; re-record. 15:00-16:00 READ / CERT: Chip Huyen, 'AI Engineering' - RAG and agents chapter (first half). Notes in your own words. 16:00-16:30 WEEKLY REVIEW: tick the week, scorecard (project cards x/6, LARP x/4, mock score, applications x/0), 3 lines in LOG.md, read next week's first card. | P13: WIN = project 'Done when' met + story/mock recorded + weekly review written (scorecard, 3 lines, next week's first card read). | R13: ☐
A14: ☐ | B14: 46342 | C14: Mon | D14: 3 | E14: 1: DocuLens | F14: 3 | G14: 22:00-23:45 PROJECT (105 min) | H14: D12 | I14: Async ingestion with Celery + Redis (202 + job status) | J14: 1. celery_app.py with Redis broker/result backend; worker service in docker-compose using the same image. 2. jobs table: id, document_id, stage (queued|extracting|chunking|embedding|ready|failed), progress, error, attempts, timestamps. 3. POST /documents now stores the file, creates job, enqueues ingest_document(document_id) and returns 202 {job_id}. 4. Celery chain: extract -> chunk -> embed, each updating the job stage. 5. GET /jobs/{id} returns stage/progress/error. 6. docs/decisions/0003-celery.md: Celery vs FastAPI BackgroundTasks vs arq (why a real broker). | K14: Uploading a 50-page PDF returns 202 in under 300 ms and GET /jobs/{id} moves queued -> extracting -> chunking -> embedding -> ready. | L14: Celery 'First steps with Celery' + 'Tasks' (acks_late, retries); FastAPI 'Background Tasks' page (to explain why you did NOT use it). | M14: 23:45-01:00 LARP (75 min) | N14: L07 Task queues: Celery, Redis, delivery guarantees | P14: WIN = project 'Done when' met and pushed (or one clean carry-over line in docs/LOG.md) + LARP quiz scored, misses written as flashcards + DSA ticked (office). | R14: ☐
A15: ☐ | B15: 46343 | C15: Tue | D15: 3 | E15: 1: DocuLens | F15: 3 | G15: 22:00-23:45 PROJECT (105 min) | H15: D13 | I15: Retries, idempotent tasks and chunk-level de-duplication | J15: 1. Retries: autoretry_for transient errors (timeouts, 429, connection) with retry_backoff + jitter, max 5; permanent errors (corrupt PDF) fail fast with a clear job error. 2. Idempotency: each stage checks whether its output already exists; UNIQUE(document_id, content_hash, page) prevents duplicate chunks. 3. Exact dedup: normalised text hash. Near-dup: MinHash (datasketch) with Jaccard >= 0.9 marks repeated headers/footers/boilerplate as is_boilerplate=true and excludes them from search. 4. Kill the worker mid-embedding (docker kill), restart, verify the job completes without duplicates. | K15: Re-running ingest for the same document does not change the chunk count, the kill-worker test completes the job with no duplicates, and the job report shows how many boilerplate chunks were removed. | L15: Celery 'Retrying' + 'acks_late' notes; datasketch MinHash/LSH README; article on SimHash (optional). | M15: 23:45-01:00 LARP (75 min) | N15: L08 Idempotency and de-duplication | P15: WIN = project 'Done when' met and pushed (or one clean carry-over line in docs/LOG.md) + LARP quiz scored, misses written as flashcards + DSA ticked (office). | R15: ☐
A16: ☐ | B16: 46344 | C16: Wed | D16: 3 | E16: 1: DocuLens | F16: 3 | G16: 22:00-23:45 PROJECT (105 min) | H16: D14 | I16: Metadata extraction with structured outputs + filtered search | J16: 1. DocMetadata schema: title, doc_type (Literal of 4-5 values), issuer, product_names list, effective_date (date|None), language. 2. Celery stage 'extract_metadata': first 3 pages -> cheap model -> DocMetadata; regex fallback for dates if the model fails. 3. Store in documents.metadata and copy doc_type/issuer into chunk metadata for filtering. 4. /search and /ask accept filters {doc_type, issuer}. 5. Add a 'route by metadata' rule: if the question names an issuer/product, filter automatically (simple keyword match against known products). | K16: Every corpus document has extracted metadata you have checked by eye, and a filtered query only returns chunks from matching documents. | L16: Instructor library README (concept of retries on validation) - you already built the equivalent; Pydantic 'Field' + 'Literal' docs. | M16: 23:45-01:00 LARP (75 min) | N16: L09 Structured outputs and prompt engineering | P16: WIN = project 'Done when' met and pushed (or one clean carry-over line in docs/LOG.md) + LARP quiz scored, misses written as flashcards + DSA ticked (office). | R16: ☐
A17: ☐ | B17: 46345 | C17: Thu | D17: 3 | E17: 1: DocuLens | F17: 3 | G17: 22:00-23:45 PROJECT (105 min) | H17: D15 | I17: Golden evaluation dataset (frozen) | J17: 1. Write 30 questions over your corpus: 10 single-fact lookups, 6 exact-term/clause questions, 8 multi-hop or compare-two-documents, 6 unanswerable (not in corpus). 2. For each: reference answer (1-2 lines), expected document + page(s), type tag. 3. Store as eval/golden_v1.jsonl and a loader with Pydantic validation. 4. Freeze it: git tag eval-v1. Rule from your old plan stays: never edit labels to make a run pass. 5. Optional: generate 20 extra synthetic questions with an LLM, but keep them in a separate file and label them synthetic. | K17: eval/golden_v1.jsonl has 30 validated rows with expected pages and types, and the tag eval-v1 exists. | L17: RAGAS docs 'Testset' concepts; Hamel Husain's blog posts on evals ('Your AI product needs evals'). | M17: 23:45-01:00 LARP (75 min) | N17: L10 Evaluating RAG systems | P17: WIN = project 'Done when' met and pushed (or one clean carry-over line in docs/LOG.md) + LARP quiz scored, misses written as flashcards + DSA ticked (office). | R17: ☐
A18: ☐ | B18: 46346 | C18: Fri | D18: 3 | E18: 1: DocuLens | F18: 3 | G18: 22:00-23:45 BUFFER + POLISH | H18: BUF | I18: Carry-over first | J18: If no carry-over: polish resume v1, tidy docs/decisions. | K18: No open carry-over from this week (or exactly one carried line in docs/LOG.md). | M18: 23:45-01:00 WEEKLY MOCK | N18: Weekly mock interview (Friday prompt). Topics: L07 Task queues: Celery, Redis, delivery guarantees, L08 Idempotency and de-duplication, L09 Structured outputs and prompt engineering, L10 Evaluating RAG systems | P18: WIN = carry-over cleared (or the polish task done) + weekly mock scored with your 5 'rewrite' answers listed. | R18: ☐
A19: ☐ | B19: 46347 | C19: Sat | D19: 3 | E19: 1: DocuLens | F19: 5 | G19: 10:30-13:30 PROJECT (3 h) | H19: D16 | I19: Retrieval evaluation harness: numbers for your design choices | J19: 1. eval/retrieval.py: for each golden question run a retrieval config, mark a hit when an expected page/chunk is in top-k. 2. Metrics: recall@5, recall@10, MRR, and context precision (fraction of retrieved chunks that are relevant, using page match). 3. Configs: dense / lexical / hybrid / hybrid+rerank x chunkers A/B/C (at least 6 runs). 4. Write docs/eval/retrieval_v1.md: table + 3-sentence conclusion + chosen default. Update decision 0002-chunking.md with the evidence. 5. Exclude unanswerable questions from recall, but report them separately. | K19: docs/eval/retrieval_v1.md has a table of at least 6 configs x 3 metrics and you can state, from memory, which config won and by how much. | L19: Recall@k, MRR, nDCG definitions (any IR textbook or Pinecone 'Evaluation Measures in IR'). | O19: 14:30-15:30 BACKEND LAB: LAB02 Rate limiters. Done when: Fixed window vs token bucket (Lua) in Redis; a burst test shows the fixed-window edge problem and the bucket's smooth behaviour. 16:00-17:00 JOB HUNT: Target list: 40 companies (product/SaaS, AI startups, GCCs) + 10 recruiters in the Job Tracker; job alerts on LinkedIn, Naukri, Instahyre, Wellfound. Resume v1 final. GATE 0 on Sunday: send the first 3 applications. 17:00-18:00 OPTIONAL: carry-over, tests, docs (never tomorrow's card) | P19: WIN = project 'Done when' met + lab 'Done when' met + job-hunt task done. | Q19: 3 | R19: ☐
A20: ☐ | B20: 46348 | C20: Sun | D20: 3 | E20: 1: DocuLens | F20: 5 | G20: 10:30-13:00 PROJECT (2.5 h) | H20: D17 | I20: Generation eval (RAGAS or DeepEval) + Langfuse tracing | J20: 1. Instrument /ask with Langfuse: one trace per request, spans for condense, retrieve, rerank, generate; record model, tokens, cost, prompt version. 2. eval/generation.py: run the golden set through /ask, score faithfulness, answer relevancy, context precision/recall with RAGAS (or DeepEval); also exact checks: unanswerable questions must return unanswerable=true. 3. Push scores to Langfuse as scores on each trace. 4. docs/eval/generation_v1.md: table + 3 worst answers with a one-line diagnosis each (retrieval miss vs generation error). Stretch: Use a different (cheaper) judge model than the answer model and note why. | K20: One full eval run is visible in Langfuse with per-trace scores, and generation_v1.md lists metrics plus the 3 worst failures with a diagnosis. | L20: Langfuse docs 'Get started' (self-host with docker compose or free cloud) + Python decorator @observe; RAGAS metrics page (faithfulness, answer_relevancy, context_precision, context_recall) or DeepEval 'Getting started'. | O20: 14:00-15:00 MOCK & STORY: STAR stories 1-2 from your real job (a hard integration; a production issue you fixed). Write in the Story Bank, then say them aloud. 15:00-16:00 READ / CERT: Chip Huyen, 'AI Engineering' - evaluation chapters (skim). Note 5 ideas you will use. 16:00-16:30 WEEKLY REVIEW: tick the week, scorecard (project cards x/6, LARP x/4, mock score, applications x/3), 3 lines in LOG.md, read next week's first card. | P20: WIN = project 'Done when' met + story/mock recorded + weekly review written (scorecard, 3 lines, next week's first card read). | R20: ☐ | S20: Gate 0: Resume v1, LinkedIn, GitHub ready (DocuLens with hybrid search and first eval table). First 3 applications; 8/week next week. Interviews are practice and market information.
A21: ☐ | B21: 46349 | C21: Mon | D21: 4 | E21: 1: DocuLens | F21: 3 | G21: 22:00-23:45 PROJECT (105 min) | H21: D18 | I21: Model router: capability routing, fallback, usage ledger | J21: 1. models.yaml: capabilities (extract_metadata, condense, answer, judge) -> ordered list of provider/model with max_tokens and timeout. 2. Router.complete(capability, ...): try primary; on timeout/429/5xx retry once with jittered backoff, then fall back to the next provider. Never fall back on a schema-validation failure that survived the re-ask (that is a prompt bug, not an outage). 3. usage_ledger table: request_id, capability, provider, model, input/output tokens, cost estimate, latency, status (ok|retried|fallback|failed). 4. GET /usage?from&to aggregates cost and calls per capability/model. 5. Test: FakeProvider that returns 429 forces a fallback; ledger shows both attempts. Stretch: Add a simple circuit breaker per provider (open after 5 failures in 60 s). | K21: The forced-429 test shows primary -> fallback in the ledger, and GET /usage returns cost per capability for your eval run. | L21: Your own LLM layer from D10; AWS Builders Library 'Timeouts, retries and backoff with jitter' (read it - it is also a backend interview classic). | M21: 23:45-01:00 LARP (75 min) | N21: L11 LLM routing, fallback, retries, timeouts, circuit breakers | P21: WIN = project 'Done when' met and pushed (or one clean carry-over line in docs/LOG.md) + LARP quiz scored, misses written as flashcards + DSA ticked (office). | R21: ☐
A22: ☐ | B22: 46350 | C22: Tue | D22: 4 | E22: 1: DocuLens | F22: 3 | G22: 22:00-23:45 PROJECT (105 min) | H22: D19 | I22: Query transformation: rewrite, multi-query, HyDE | J22: 1. Multi-query: LLM writes 3 paraphrases; retrieve for each; fuse with RRF. 2. HyDE: LLM writes a hypothetical answer; embed it for the dense leg only. 3. Decomposition for compare questions: split 'A vs B' into two sub-queries. 4. Feature flags per technique; run the retrieval eval on golden_v1 for each. 5. Add rows to retrieval_v1.md and record keep/drop decisions with the cost (extra LLM calls, latency). | K22: The retrieval table has rows for multi-query and HyDE with recall@5 and added latency, and each has a written keep/drop decision. | L22: LangChain 'MultiQueryRetriever' concept page; HyDE paper abstract (Gao et al. 2022); 'step-back prompting' summary. | M22: 23:45-01:00 LARP (75 min) | N22: L12 Chunking strategies and query transformation | P22: WIN = project 'Done when' met and pushed (or one clean carry-over line in docs/LOG.md) + LARP quiz scored, misses written as flashcards + DSA ticked (office). | R22: ☐
A23: ☐ | B23: 46351 | C23: Wed | D23: 4 | E23: 1: DocuLens | F23: 3 | G23: 22:00-23:45 PROJECT (105 min) | H23: D20 | I23: LangGraph 1: your RAG pipeline as a StateGraph | J23: 1. RAGState TypedDict: question, conversation_id, filters, standalone_question, candidates, context, answer, citations, confidence, steps (Annotated list with operator.add reducer). 2. Nodes: condense -> retrieve -> rerank -> generate. Each node is a small pure-ish function calling your existing services. 3. Compile; expose POST /agent/ask that invokes the graph. 4. Export the Mermaid diagram (graph.get_graph().draw_mermaid()) into README. 5. Unit test the graph with FakeProvider and FakeEmbedder. | K23: /agent/ask returns the same quality answer as /ask (spot check 5 golden questions), and the Mermaid diagram is in the README. | L23: LangGraph docs (docs.langchain.com, LangGraph section): 'Quickstart', 'Graph API' (state, reducers, nodes, edges). | M23: 23:45-01:00 LARP (75 min) | N23: L13 LangGraph core: state, nodes, edges, reducers, checkpointers | P23: WIN = project 'Done when' met and pushed (or one clean carry-over line in docs/LOG.md) + LARP quiz scored, misses written as flashcards + DSA ticked (office). | R23: ☐
A24: ☐ | B24: 46352 | C24: Thu | D24: 4 | E24: 1: DocuLens | F24: 3 | G24: 22:00-23:45 PROJECT (105 min) | H24: D21 | I24: LangGraph 2: conditional routing + self-correction (corrective RAG) | J24: 1. route_question node (structured output): direct (chit-chat/meta), retrieve, or clarify (ambiguous). 2. grade_documents node: cheap model labels each chunk relevant/irrelevant in ONE batched call. 3. If no relevant chunks: rewrite_query -> retrieve again, max 2 loops (loop counter in state). 4. check_grounding node after generate: if the answer is not supported by the cited chunks -> regenerate once, else abstain with unanswerable=true. 5. Tests with FakeProvider scripted responses covering: direct, retrieve-ok, rewrite-loop-hits-cap, abstain. | K24: Four graph tests (direct, normal retrieve, rewrite loop capped at 2, abstain) pass, and the golden unanswerable questions now abstain at least 5 of 6 times. | L24: LangGraph tutorial 'Agentic RAG' / 'Adaptive RAG' pages; Self-RAG and CRAG paper abstracts. | M24: 23:45-01:00 LARP (75 min) | N24: L14 Agentic patterns: ReAct, tool calling, HITL, self-correction, multi-agent | P24: WIN = project 'Done when' met and pushed (or one clean carry-over line in docs/LOG.md) + LARP quiz scored, misses written as flashcards + DSA ticked (office). | R24: ☐
A25: ☐ | B25: 46353 | C25: Fri | D25: 4 | E25: 1: DocuLens | F25: 3 | G25: 22:00-23:45 BUFFER + POLISH | H25: BUF | I25: Carry-over first | J25: If no carry-over: graph tests, zero mypy errors. Plus 30 min applications. | K25: No open carry-over from this week (or exactly one carried line in docs/LOG.md). | M25: 23:45-01:00 WEEKLY MOCK | N25: Weekly mock interview (Friday prompt). Topics: L11 LLM routing, fallback, retries, timeouts, circuit breakers, L12 Chunking strategies and query transformation, L13 LangGraph core: state, nodes, edges, reducers, checkpointers, L14 Agentic patterns: ReAct, tool calling, HITL, self-correction, multi-agent | P25: WIN = carry-over cleared (or the polish task done) + weekly mock scored with your 5 'rewrite' answers listed. | R25: ☐
A26: ☐ | B26: 46354 | C26: Sat | D26: 4 | E26: 1: DocuLens | F26: 5 | G26: 10:30-13:30 PROJECT (3 h) | H26: D22 | I26: LangGraph 3: tools, human-in-the-loop interrupt, Postgres checkpointer | J26: 1. Tools (typed, read-only): search_documents(query, filters), get_page_text(document_id, page), list_documents(doc_type). Bind to the answer model; ToolNode executes them. 2. PostgresSaver checkpointer; every request carries thread_id = conversation_id. 3. interrupt() before returning when confidence < 0.6 OR the question asks for a decision (e.g. 'is my claim covered?'): the state is saved and the API returns status=needs_review with the draft. 4. POST /agent/threads/{id}/resume {decision: approve|edit|reject, edited_answer?} resumes with Command(resume=...). 5. Test: pause, restart the API container, resume - the thread continues from the checkpoint. | K26: A low-confidence question pauses with needs_review, survives an API restart, and completes after POST /resume. | L26: LangGraph docs: 'Tools'/'ToolNode', 'Persistence' (checkpointers, thread_id), 'Human-in-the-loop' (interrupt, Command(resume=...)); langgraph-checkpoint-postgres README. | O26: 14:30-15:30 BACKEND LAB: LAB03 Idempotency keys. Done when: POST /payments with Idempotency-Key: concurrent duplicates execute once; retry returns the stored response. 16:00-17:00 JOB HUNT: 8 applications + 3 referral messages. Log every interview question you get in the Interview Log. 17:00-18:00 OPTIONAL: carry-over, tests, docs (never tomorrow's card) | P26: WIN = project 'Done when' met + lab 'Done when' met + job-hunt task done. | Q26: 8 | R26: ☐
A27: ☐ | B27: 46355 | C27: Sun | D27: 4 | E27: 1: DocuLens | F27: 5 | G27: 10:30-13:00 PROJECT (2.5 h) | H27: D23 | I27: Multi-document comparison: fan-out with Send (map-reduce) | J27: 1. Route compare-type questions to a compare branch. 2. planner node: identify target documents (from metadata) and the aspect to compare. 3. Send one task per document to a per_document subgraph (retrieve within that document -> extract structured findings with citations). 4. aggregate node: builds a comparison table (aspect x document) with citations; abstain per cell if nothing found. 5. Cap fan-out at 5 documents; per-branch timeout; a failed branch shows 'not found' instead of failing the whole answer. Stretch: Deep-research report mode: a planner writes 3-5 sub-questions, Send fans them out, a writer composes a cited report and a checker deletes unsupported sentences. Keep it only if 3 sample reports pass your grounding check. | K27: 'Compare exclusions in policy A vs policy B' returns a table with citations from both documents, and the Langfuse trace shows the parallel branches. | L27: LangGraph docs 'Map-reduce with Send API' and 'Subgraphs'; your backend patterns notes on fan-out/fan-in. | O27: 14:00-15:00 MOCK & STORY: Design-choice defence: answer the DocuLens questions in the Design Choices sheet aloud (record, score yourself). 15:00-16:00 READ / CERT: LangGraph docs: low-level concepts (state, reducers, persistence, interrupts) end to end. 16:00-16:30 WEEKLY REVIEW: tick the week, scorecard (project cards x/6, LARP x/4, mock score, applications x/8), 3 lines in LOG.md, read next week's first card. | P27: WIN = project 'Done when' met + story/mock recorded + weekly review written (scorecard, 3 lines, next week's first card read). | R27: ☐
A28: ☐ | B28: 46356 | C28: Mon | D28: 5 | E28: 1: DocuLens | F28: 3 | G28: 22:00-23:45 PROJECT (105 min) | H28: D24 | I28: Auth, workspaces and RBAC (tenant isolation) | J28: 1. users, workspaces, memberships(role: owner|editor|viewer); signup/login returning access (15 min) + refresh (7 days, stored hashed, rotated) tokens. 2. get_current_principal dependency -> (user_id, workspace_id, role). 3. Every query on documents/chunks/jobs/threads filters by workspace_id - put it in the repository layer so it cannot be forgotten. 4. Viewer cannot upload or delete; editor can; owner manages members. 5. Isolation tests: user B cannot see A's documents via /documents, /search, /ask, /agent tools, or by guessing a document id (404, not 403). | K28: The two-user isolation test suite passes for every endpoint, including the agent's tools. | L28: FastAPI 'Security - OAuth2 with Password, Bearer with JWT'; OWASP 'Authorization Cheat Sheet' (skim); pwdlib/argon2 README. | M28: 23:45-01:00 LARP (75 min) | N28: L15 Authentication, authorization, JWT, OAuth2/OIDC, RBAC, multi-tenancy | P28: WIN = project 'Done when' met and pushed (or one clean carry-over line in docs/LOG.md) + LARP quiz scored, misses written as flashcards + DSA ticked (office). | R28: ☐
A29: ☐ | B29: 46357 | C29: Tue | D29: 5 | E29: 1: DocuLens | F29: 3 | G29: 22:00-23:45 PROJECT (105 min) | H29: D25 | I29: Production Dockerfiles + GitHub Actions CI | J29: 1. Multi-stage Dockerfile: builder installs deps with uv into .venv, runtime copies it; non-root user; HEALTHCHECK; pre-download the embedding/reranker models at build time. 2. Same image runs api (uvicorn) and worker (celery) with different commands. 3. CI workflow: ruff, mypy, pytest with postgres(pgvector)+redis service containers, docker build, and an eval smoke test (5 golden questions with FakeProvider asserting the pipeline wiring). 4. Cache uv and Docker layers in CI. 5. README badge. | K29: CI is green on a pull request, the runtime image runs as non-root, and an intentionally broken test makes CI fail. | L29: Docker docs 'Multi-stage builds'; uv docs 'Using uv in Docker'; GitHub Actions 'Creating PostgreSQL service containers'. | M29: 23:45-01:00 LARP (75 min) | N29: L16 Docker in depth + CI/CD with GitHub Actions | P29: WIN = project 'Done when' met and pushed (or one clean carry-over line in docs/LOG.md) + LARP quiz scored, misses written as flashcards + DSA ticked (office). | R29: ☐
A30: ☐ | B30: 46358 | C30: Wed | D30: 5 | E30: 1: DocuLens | F30: 3 | G30: 22:00-23:45 PROJECT (105 min) | H30: D26 | I30: Azure foundation (budget first) | J30: 1. Budget + alert at a small monthly cap before creating anything. One region (e.g. Central India). Tag every resource project=doculens. 2. infra/azure/setup.sh using az CLI: resource group, Azure Container Registry, Log Analytics workspace + Container Apps environment, PostgreSQL Flexible Server (Burstable B1ms) with azure.extensions=VECTOR, Storage account + private container, Key Vault. 3. Enable vector extension and run Alembic migrations against Azure PG from your laptop (firewall rule for your IP only). 4. BlobStorage implementation of your Storage interface (SAS URLs for download). 5. docs/cloud-cost.md: every billable resource, its expected monthly cost, and how to stop it. Stretch: teardown.sh that deletes the resource group. | K30: setup.sh recreates the environment from scratch, migrations run on Azure PG with pgvector, and a budget alert exists. | L30: Microsoft Learn: 'Azure Container Apps overview', 'Azure Database for PostgreSQL flexible server - enable pgvector', 'Key Vault basics', 'Cost Management budgets'. Check whether your employer gives a Visual Studio subscription with monthly Azure credit. | M30: 23:45-01:00 LARP (75 min) | N30: L17 Cloud fundamentals: Azure services and their AWS equivalents | P30: WIN = project 'Done when' met and pushed (or one clean carry-over line in docs/LOG.md) + LARP quiz scored, misses written as flashcards + DSA ticked (office). | R30: ☐
A31: ☐ | B31: 46359 | C31: Thu | D31: 5 | E31: 1: DocuLens | F31: 3 | G31: 22:00-23:45 PROJECT (105 min) | H31: D27 | I31: Deploy API + worker to Azure Container Apps | J31: 1. Push image to ACR (az acr build or from CI). 2. Container App 'api' (external ingress, min replicas 0-1) and 'worker' (no ingress); Redis as an internal Container App (redis:7) for v1 - write down why not Azure Cache yet (cost). 3. User-assigned managed identity: pull from ACR, read Key Vault secrets, read/write Blob. No secrets in env files or images. 4. Container Apps job for alembic upgrade head. 5. Smoke test script: health, signup, upload, poll job, ask. | K31: A public HTTPS URL passes the smoke test end to end (upload -> ready -> cited answer) and no secret value appears in the Container App configuration. | L31: Microsoft Learn: 'Deploy to Container Apps from ACR', 'Managed identities in Container Apps', 'Container Apps jobs' (for migrations). | M31: 23:45-01:00 LARP (75 min) | N31: L18 Observability: logs, metrics, traces, OpenTelemetry, LLM tracing | P31: WIN = project 'Done when' met and pushed (or one clean carry-over line in docs/LOG.md) + LARP quiz scored, misses written as flashcards + DSA ticked (office). | R31: ☐
A32: ☐ | B32: 46360 | C32: Fri | D32: 5 | E32: 1: DocuLens | F32: 3 | G32: 22:00-23:45 BUFFER + POLISH | H32: BUF | I32: Carry-over first | J32: If no carry-over: clean infra scripts, check cloud costs. Plus 30 min applications. | K32: No open carry-over from this week (or exactly one carried line in docs/LOG.md). | M32: 23:45-01:00 WEEKLY MOCK | N32: Weekly mock interview (Friday prompt). Topics: L15 Authentication, authorization, JWT, OAuth2/OIDC, RBAC, multi-tenancy, L16 Docker in depth + CI/CD with GitHub Actions, L17 Cloud fundamentals: Azure services and their AWS equivalents, L18 Observability: logs, metrics, traces, OpenTelemetry, LLM tracing | P32: WIN = carry-over cleared (or the polish task done) + weekly mock scored with your 5 'rewrite' answers listed. | R32: ☐
A33: ☐ | B33: 46361 | C33: Sat | D33: 5 | E33: 1: DocuLens | F33: 5 | G33: 10:30-13:30 PROJECT (3 h) | H33: D28 | I33: Observability, rate limiting and a load test | J33: 1. Structured JSON logs with request_id, user/workspace id, route, status, duration; propagate request_id into Celery tasks. 2. OpenTelemetry traces + metrics to Application Insights (HTTP + DB + Redis + Celery); Langfuse stays for LLM traces. 3. Per-workspace rate limit on /ask (Redis token bucket, Lua for atomicity) returning 429 + Retry-After. 4. Load test /search with 20 virtual users for 3 minutes; record p50/p95/error rate; find one bottleneck (e.g. reranker on CPU, pool size) and fix or document it. 5. docs/perf.md with before/after numbers. | K33: docs/perf.md shows p50/p95 for /search under load, one bottleneck you found, and a 429 appears when you exceed the rate limit. | L33: OpenTelemetry Python 'Getting started' + Azure Monitor OpenTelemetry distro; k6 or Locust quickstart; Redis 'rate limiting' patterns (token bucket with Lua). | O33: 14:30-15:30 BACKEND LAB: LAB04 Offset vs cursor pagination. Done when: 1M-row table; EXPLAIN ANALYZE shows page 5,000 offset vs keyset timings; numbers saved. 16:00-17:00 JOB HUNT: 10 applications + 5 referral asks. Resume v2 with the deployed link and eval numbers (GATE 1). 17:00-18:00 OPTIONAL: carry-over, tests, docs (never tomorrow's card) | P33: WIN = project 'Done when' met + lab 'Done when' met + job-hunt task done. | Q33: 10 | R33: ☐
A34: ☐ | B34: 46362 | C34: Sun | D34: 5 | E34: 1: DocuLens | F34: 5 | G34: 10:30-13:00 PROJECT (2.5 h) | H34: D29 | I34: Release v1: README, design doc, demo, resume bullets | J34: 1. README: one-paragraph pitch, architecture diagram (API, worker, Postgres+pgvector, Redis, Blob, LLM router, Langfuse), features, eval tables, 'Design decisions' links, how to run, known limits. 2. docs/design.md: 1-2 pages: problem, architecture, data flow of ingest and ask, trade-offs, what you would do at 100x scale. 3. Record a 3-minute demo video (upload -> job progress -> cited answer with page -> compare question -> needs_review pause -> resume). 4. Tag v1.0. Write 3 resume bullets using only numbers you measured (recall@5, faithfulness, p95, docs ingested). 5. Fill the 'Design Choices' sheet answers for DocuLens. | K34: v1.0 is tagged, README + design.md + demo video are linked, and the resume has 3 DocuLens bullets with real numbers. | L34: Look at 2-3 well-known open-source RAG repos' READMEs for structure; Excalidraw for the diagram. | O34: 14:00-15:00 MOCK & STORY: Full mock with Claude: 30-minute DocuLens deep dive as a senior interviewer (use the Friday mock prompt, longer). 15:00-16:00 READ / CERT: Microsoft Learn: Azure Container Apps + managed identity modules (before D26/D27 if possible). 16:00-16:30 WEEKLY REVIEW: tick the week, scorecard (project cards x/6, LARP x/4, mock score, applications x/10), 3 lines in LOG.md, read next week's first card. | P34: WIN = project 'Done when' met + story/mock recorded + weekly review written (scorecard, 3 lines, next week's first card read). | R34: ☐ | S34: Gate 1: DocuLens v1 deployed on Azure with eval report and demo. Resume v2. 10-15 applications/week + 5 referral asks.
A35: ☐ | B35: 46363 | C35: Mon | D35: 6 | E35: 1: DocuLens | F35: 3 | G35: 22:00-23:45 PROJECT (105 min) | H35: D31 | I35: Intake: document classification + per-type extraction with field confidence | J35: 1. Domain (recommended): insurance claims. Document types claim_form, hospital_bill, discharge_summary, other. One Pydantic schema per type (claimant, policy_number, incident_date, diagnosis, line_items[{description, amount}], total, hospital, ...). 2. scripts/make_claims.py: generate 30 synthetic claim packets (one PDF per document, via PyMuPDF insert_textbox or reportlab) with Faker data and a ground-truth JSON next to each. Render 5 of them as images (scanned) to exercise OCR. Plant errors on purpose: total != sum of line items, missing policy number, incident date before policy start. These are your eval labels, for free. 3. classify(document) -> doc_type + confidence: cheap model, structured output, first 2 pages only. 4. extract(document, doc_type) -> each field with value, confidence and source (page, bbox) taken from your D04 blocks. A value that does not appear on the page is marked unverified. 5. validate: Pydantic types + business rules (line items sum to total, dates in range, policy number format). Rule failures are recorded, not raised. 6. Table extractions(document_id, doc_type, schema_version, fields jsonb, field_confidence jsonb, rule_failures jsonb, model, prompt_version) + POST /documents/{id}/extract. Test on 10 packets: print classification accuracy and field exact-match accuracy. Stretch: Azure Document Intelligence prebuilt-invoice adapter for hospital bills behind the same interface; compare accuracy and cost with the LLM extractor. | K35: On 10 synthetic claim packets a script prints classification accuracy and field accuracy, and every planted error (bad total, missing policy number, bad date) is caught as a rule failure. | L35: Pydantic 'JSON Schema' page (model_json_schema); structured outputs docs of OpenAI and Anthropic; Azure AI Document Intelligence 'prebuilt invoice' overview (concept only, it is AI-102 material); Faker README. | M35: 23:45-01:00 LARP (75 min) | N35: L71 Intelligent document processing: classify, extract, validate, route | P35: WIN = project 'Done when' met and pushed (or one clean carry-over line in docs/LOG.md) + LARP quiz scored, misses written as flashcards + DSA ticked (office). | R35: ☐
A36: ☐ | B36: 46364 | C36: Tue | D36: 6 | E36: 1: DocuLens | F36: 3 | G36: 22:00-23:45 PROJECT (105 min) | H36: D32 | I36: Workflow engine: definitions, runs and durable steps | J36: 1. workflows(name, version, definition): YAML with a trigger and steps[] (type, config, on_failure, timeout). Seed claim_intake v1: classify -> extract -> validate -> policy_check -> route -> act. 2. workflow_runs(id, workflow, version, document_ids, status pending|running|waiting_review|succeeded|failed|cancelled, current_step, idempotency_key UNIQUE, started_at, ended_at) and step_runs(run_id, step, attempt, status, output jsonb, error, duration_ms). 3. Executor: build a LangGraph StateGraph from the definition (one node per step) with the Postgres checkpointer (thread_id = run_id). It runs inside a Celery task and every node writes its step_runs row. 4. Triggers: (a) upload with ?workflow=claim_intake, (b) POST /triggers/email with a simulated inbound email (JSON + attachments), (c) a Celery beat 'daily_digest' workflow. Each trigger computes an idempotency key (email message-id, or sha256 + workflow). 5. Retry policy per step: transient errors (timeout, 429, 5xx) retry with backoff + jitter; permanent errors (validation, 4xx) fail the run with the error stored. 6. Crash test: kill the worker mid-run; the restarted worker resumes from the last checkpoint and no completed step runs again. Stretch: GET /runs/{id}/timeline returning step durations - you will show it in the demo. | K36: A packet uploaded with workflow=claim_intake produces a run with one step_runs row per step, the same email trigger sent twice creates exactly one run, and a run killed mid-way resumes and finishes. | L36: LangGraph docs 'Durable execution' and 'Persistence'; Temporal 'What is durable execution?' (to compare, not to use); Celery 'Periodic tasks' (beat). | M36: 23:45-01:00 LARP (75 min) | N36: L72 Durable workflows and orchestration engines (LangGraph, Celery, Temporal, Step Functions) | P36: WIN = project 'Done when' met and pushed (or one clean carry-over line in docs/LOG.md) + LARP quiz scored, misses written as flashcards + DSA ticked (office). | R36: ☐
A37: ☐ | B37: 46365 | C37: Wed | D37: 6 | E37: 1: DocuLens | F37: 3 | G37: 22:00-23:45 PROJECT (105 min) | H37: D33 | I37: Decision step: policy-grounded coverage check + human review queue with SLAs | J37: 1. policy_check node: retrieve from the claimant's policy wording (metadata filter policy_number -> document) with your hybrid + rerank retriever; structured output {decision: covered|not_covered|unclear, clause_ids, reasons, confidence}; reuse the D10 citation validator. 2. route node is pure code, not an LLM: auto_approve only if every field is verified, there are no rule failures, decision=covered with valid citations and the amount is under a threshold; otherwise needs_review with reason codes. not_covered becomes reject_draft, which still needs a human. 3. Review queue: interrupt() -> run status waiting_review. GET /reviews (filter by reason and age); POST /reviews/{run_id} {approve | edit fields | reject, note}. Edits are stored as corrections - future eval data. 4. SLA: a Celery beat job finds reviews older than N hours, escalates them to the owner role and sends a notification; reviewer and decision go to audit_log. 5. Tests: one packet per route (auto-approve, review for low confidence, review for rule failure, reject draft) and an escalation test with a frozen clock. | K37: Four synthetic packets end in the four expected routes with reason codes, a reviewer's edit resumes the run to completion, and an overdue review is escalated by the scheduler. | L37: Your D21/D22 code (grounding check, interrupt/resume); LangGraph 'Human-in-the-loop' patterns (approve / edit / reject); a short read on straight-through processing (STP) in insurance claims. | M37: 23:45-01:00 LARP (75 min) | N37: L74 Integrations and side effects: webhooks, outbox, retries, audit | P37: WIN = project 'Done when' met and pushed (or one clean carry-over line in docs/LOG.md) + LARP quiz scored, misses written as flashcards + DSA ticked (office). | R37: ☐
A38: ☐ | B38: 46366 | C38: Thu | D38: 6 | E38: 1: DocuLens | F38: 3 | G38: 22:00-23:45 PROJECT (105 min) | H38: D34 | I38: Analytics agent: text-to-SQL over workflow data with guardrails | J38: 1. Read-only role analytics_ro with SELECT on 3-4 curated views only (v_claims, v_runs, v_reviews) and row-level security on workspace_id (SET app.workspace_id per session). 2. Schema context: YAML with view/column descriptions + 3 example question -> SQL pairs. Schema linking: embed the descriptions and give the model only the views/columns relevant to the question. 3. LangGraph: generate_sql (structured output) -> validate with sqlglot (exactly one SELECT, allow-listed views only, no dangerous functions such as pg_sleep, LIMIT 200 added) -> execute with statement_timeout 3 s -> on error feed the error back, max 2 retries -> answer in words with the SQL shown. 4. POST /analytics/ask, plus a tool query_workflow_data for the DocuLens agent: the agent now chooses between searching documents and querying data. 5. Eval: 25 questions with expected result sets (e.g. 'claims waiting for review more than 24 h, by reason'); metric = execution accuracy. Plus 5 malicious prompts ('drop table claims', 'show workspace B') that must be blocked. | K38: docs/eval/text_to_sql_v1.md records execution accuracy on 25 questions, and all 5 malicious prompts are blocked by validation or database permissions - not by the prompt. | L38: sqlglot README (parse, validate); PostgreSQL docs 'Row Security Policies' and 'GRANT'; the idea of execution accuracy from the Spider / BIRD text-to-SQL benchmarks (abstracts only). | M38: 23:45-01:00 LARP (75 min) | N38: L73 Text-to-SQL agents and safe data access | P38: WIN = project 'Done when' met and pushed (or one clean carry-over line in docs/LOG.md) + LARP quiz scored, misses written as flashcards + DSA ticked (office). | R38: ☐
A39: ☐ | B39: 46367 | C39: Fri | D39: 6 | E39: 1: DocuLens | F39: 3 | G39: 22:00-23:45 BUFFER + POLISH | H39: BUF | I39: Carry-over first | J39: If no carry-over: run the 30-packet workflow eval once more and fix the worst failure. Plus 30 min applications. | K39: No open carry-over from this week (or exactly one carried line in docs/LOG.md). | M39: 23:45-01:00 WEEKLY MOCK | N39: Weekly mock interview (Friday prompt). Topics: L71 Intelligent document processing: classify, extract, validate, route, L72 Durable workflows and orchestration engines (LangGraph, Celery, Temporal, Step Functions), L74 Integrations and side effects: webhooks, outbox, retries, audit, L73 Text-to-SQL agents and safe data access | P39: WIN = carry-over cleared (or the polish task done) + weekly mock scored with your 5 'rewrite' answers listed. | R39: ☐
A40: ☐ | B40: 46368 | C40: Sat | D40: 6 | E40: 1: DocuLens | F40: 5 | G40: 10:30-13:30 PROJECT (3 h) | H40: D35 | I40: Actions: outbox, signed webhooks, notifications and audit trail | J40: 1. act node writes outbox rows (event_type, payload, event_id) in the SAME transaction as the run state change: claim.approved, claim.rejected, review.required, run.failed. 2. Relay (Celery beat): SELECT ... FOR UPDATE SKIP LOCKED in batches; deliver to subscribed webhooks with an HMAC-SHA256 signature + timestamp header; retry with exponential backoff + jitter; after N attempts dead-letter with the last error; mark published_at. 3. webhook_subscriptions per workspace (url, secret, events) + a tiny receiver app (second container) that verifies the signature and de-duplicates by event_id. 4. Notifications: email through MailHog in Docker Compose (or a Slack incoming webhook) for review.required and escalations. 5. audit_log: append-only record of every human action and external effect (who, what, when, run_id); GET /runs/{id}/audit. 6. Tests: receiver down for 2 minutes -> every event arrives once after it recovers; a tampered signature is rejected; killing the relay mid-batch loses nothing. | K40: With the receiver stopped and restarted, every event arrives exactly once (the receiver's dedup log proves it), a forged signature gets 401, and the audit endpoint shows the full history of a run. | L40: microservices.io 'Transactional outbox'; Stripe docs 'Verify webhook signatures' (the HMAC pattern); your LAB03 idempotency notes. | O40: 14:30-15:30 BACKEND LAB: LAB05 Resilient HTTP client. Done when: Unreliable server (500/429/slow/disconnect); client with timeout, retry, backoff+jitter, circuit breaker, fallback; success rate measured. 16:00-17:00 JOB HUNT: 15 applications + 5 referral asks; follow up on last week's; update Interview Log. 17:00-18:00 OPTIONAL: carry-over, tests, docs (never tomorrow's card) | P40: WIN = project 'Done when' met + lab 'Done when' met + job-hunt task done. | Q40: 15 | R40: ☐
A41: ☐ | B41: 46369 | C41: Sun | D41: 6 | E41: 1: DocuLens | F41: 5 | G41: 10:30-13:00 PROJECT (2.5 h) | H41: D36 | I41: Workflow eval, ops dashboard and release v1.5 | J41: 1. Run all 30 synthetic packets through claim_intake and compare with ground truth: classification accuracy, field accuracy per field, route accuracy, STP rate, false auto-approvals (target 0), mean run time, cost per packet from the usage ledger. 2. docs/eval/workflow_v1.md: the table + 3 failure analyses; fix one cause, rerun, record before/after. 3. Ops page (FastAPI + HTMX or Streamlit): runs by status, review-queue age, STP rate, failures by step. 4. Redeploy to Azure: worker and beat as separate Container Apps; notifications to a real sandbox (Slack or an SMTP test inbox). 5. README: workflow diagram, 'why LangGraph + Celery instead of Temporal or Power Automate', demo video part 2 (packet arrives -> extracted -> policy check with cited clause -> human review -> webhook fires -> analytics question). 6. Tag v1.5 and add 2 resume bullets with measured numbers (e.g. 'X% straight-through, 0 false auto-approvals on 30 labelled packets'). | K41: v1.5 is deployed and tagged, workflow_v1.md shows STP rate, field accuracy and false auto-approvals, and the demo video covers the whole workflow. | L41: Your D16/D17 eval harness; Langfuse datasets; Azure Container Apps 'Revisions' (for the redeploy). | O41: 14:00-15:00 MOCK & STORY: Record a 3-minute DocuLens workflow walkthrough (packet -> extraction -> cited policy check -> review -> webhook -> analytics question); then answer aloud: 'why not Power Automate or Temporal?' and 'how do you stop wrong auto-approvals?' 15:00-16:00 READ / CERT: AI-102 prep 1: Microsoft Learn path - plan and manage an Azure AI solution. Then 15 min: LangGraph 'Durable execution' page. 16:00-16:30 WEEKLY REVIEW: tick the week, scorecard (project cards x/6, LARP x/4, mock score, applications x/15), 3 lines in LOG.md, read next week's first card. | P41: WIN = project 'Done when' met + story/mock recorded + weekly review written (scorecard, 3 lines, next week's first card read). | R41: ☐ | S41: DocuLens v1.5: Workflow automation released: claim intake, review queue, webhooks, text-to-SQL, workflow eval. Resume bullets updated. | Stage 1 exit: v1.0 (W5): public URL passes the smoke test, retrieval + generation eval tables, demo. v1.5 (W6): workflow eval with STP rate, field accuracy and 0 false auto-approvals; text-to-SQL eval; demo part 2; resume bullets with real numbers.
A42: ☐ | B42: 46370 | C42: Mon | D42: 7 | E42: 2: AI SRE Copilot v1 | F42: 3 | G42: 22:00-23:45 PROJECT (105 min) | H42: D30 | I42: MCP server for DocuLens | J42: 1. FastMCP server with tools search_documents(query, filters, k), get_page_text(document_id, page), start_workflow(document_id, workflow), get_run_status(run_id) and ask_data(question) calling your API with a workspace API key (scoped: read + start runs, never approve). 2. Typed inputs/outputs with descriptions written for a model (tool descriptions are prompts). 3. Run over stdio locally and streamable HTTP in Docker. 4. Test with MCP Inspector, then connect it to Claude Code / Claude Desktop and ask a question about your corpus. 5. Log every tool call with the workspace and a request id (audit). | K42: Claude Code (or Claude Desktop) lists your tools, answers a corpus question, starts a claim workflow and reports its status; every tool call appears in your audit log. | L42: modelcontextprotocol.io 'Introduction' + 'Build a server' (Python); FastMCP docs (gofastmcp.com); MCP Inspector. | M42: 23:45-01:00 LARP (75 min) | N42: L19 Model Context Protocol (MCP) | P42: WIN = project 'Done when' met and pushed (or one clean carry-over line in docs/LOG.md) + LARP quiz scored, misses written as flashcards + DSA ticked (office). | R42: ☐
A43: ☐ | B43: 46371 | C43: Tue | D43: 7 | E43: 2: AI SRE Copilot v1 | F43: 3 | G43: 22:00-23:45 PROJECT (105 min) | H43: S01 | I43: SRE repo + local Kubernetes (kind) + kubectl drills | J43: 1. Monorepo: services/, victim-app/, faults/, deploy/, eval/, docs/ (reuse D01 tooling). 2. kind cluster with namespaces victim, platform, observability. 3. Deploy nginx; practise describe, logs, exec, port-forward, rollout restart, scale. 4. Note idle RAM of Docker Desktop with the cluster in docs/decisions/0001-resource-budget.md. | K43: `kubectl get nodes` is Ready, port-forward to nginx works, and the resource-budget note is committed. | L43: kind quickstart (kind.sigs.k8s.io); Kubernetes docs 'Concepts > Workloads' (Pods, Deployments, Services). | M43: 23:45-01:00 LARP (75 min) | N43: L20 Kubernetes core objects | P43: WIN = project 'Done when' met and pushed (or one clean carry-over line in docs/LOG.md) + LARP quiz scored, misses written as flashcards + DSA ticked (office). | R43: ☐
A44: ☐ | B44: 46372 | C44: Wed | D44: 7 | E44: 2: AI SRE Copilot v1 | F44: 3 | G44: 22:00-23:45 PROJECT (105 min) | H44: S02 | I44: Victim app: gateway -> api -> Postgres on the cluster | J44: 1. FastAPI api (/health/live, /health/ready, /items backed by Postgres) and gateway proxying to it. 2. Manifests: Deployments with probes, requests/limits, annotation sre-copilot/baseline-replicas; Services; Postgres StatefulSet + PVC + Secret. 3. Load images into kind (kind load docker-image). | K44: A request through the gateway returns data from Postgres inside the cluster and all pods are Ready. | L44: Kubernetes docs 'Configure Liveness, Readiness and Startup Probes', 'Resource Management for Pods and Containers'. | M44: 23:45-01:00 LARP (75 min) | N44: L21 Debugging containers and Kubernetes in practice | P44: WIN = project 'Done when' met and pushed (or one clean carry-over line in docs/LOG.md) + LARP quiz scored, misses written as flashcards + DSA ticked (office). | R44: ☐
A45: ☐ | B45: 46373 | C45: Thu | D45: 7 | E45: 2: AI SRE Copilot v1 | F45: 3 | G45: 22:00-23:45 PROJECT (105 min) | H45: S03 | I45: Fault knobs + one-command fault scripts with undo | J45: 1. Env-guarded toggles on api: crash, memory leak, CPU spin, latency, readiness fail. 2. faults/*.sh with undo: kill-pod, oom, cpu-spin, bad-image, db-down (scale Postgres to 0), bad-config, readiness-fail, latency. 3. Each script prints what to watch (kubectl get pods -w, events). | K45: Every fault triggers and undoes with one command, and you can explain how limits change the OOM and CPU behaviour. | L45: Kubernetes docs 'Debug Running Pods'; your old master plan Phase 0 (S005-S006). | M45: 23:45-01:00 LARP (75 min) | N45: L22 Prometheus, PromQL and alerting | P45: WIN = project 'Done when' met and pushed (or one clean carry-over line in docs/LOG.md) + LARP quiz scored, misses written as flashcards + DSA ticked (office). | R45: ☐
A46: ☐ | B46: 46374 | C46: Fri | D46: 7 | E46: 2: AI SRE Copilot v1 | F46: 3 | G46: 22:00-23:45 BUFFER + POLISH | H46: BUF | I46: Carry-over first | J46: Carry-over first. If nothing is left: write the ADR for this week's main decision, then 30 min applications/follow-ups. | K46: No open carry-over from this week (or exactly one carried line in docs/LOG.md). | M46: 23:45-01:00 WEEKLY MOCK | N46: Weekly mock interview (Friday prompt). Topics: L19 Model Context Protocol (MCP), L20 Kubernetes core objects, L21 Debugging containers and Kubernetes in practice, L22 Prometheus, PromQL and alerting | P46: WIN = carry-over cleared (or the polish task done) + weekly mock scored with your 5 'rewrite' answers listed. | R46: ☐
A47: ☐ | B47: 46375 | C47: Sat | D47: 7 | E47: 2: AI SRE Copilot v1 | F47: 5 | G47: 10:30-13:30 PROJECT (3 h) | H47: S04 | I47: Prometheus + Alertmanager -> webhook, alert fixtures | J47: 1. Helm install kube-prometheus-stack with laptop-sized values (disable what you do not need). 2. PrometheusRules: PodCrashLooping, PodNotReady, ContainerOOMKilled, ImagePullBackOff. 3. Route alerts to a webhook URL; capture real payloads into fixtures/alertmanager_*.json. | K47: Each rule fires for its fault in 3 of 3 runs and real webhook payloads are saved as fixtures. | L47: kube-prometheus-stack chart README; Prometheus 'Alerting rules'; Alertmanager 'Configuration > webhook_config'. | O47: 14:30-15:30 BACKEND LAB: LAB06 asyncio worker pool + backpressure. Done when: Bounded asyncio.Queue with N workers; producer slows when full; memory stays flat under overload. 16:00-17:00 JOB HUNT: 15 applications + 5 referral asks; follow up on last week's; update Interview Log. 17:00-18:00 OPTIONAL: carry-over, tests, docs (never tomorrow's card) | P47: WIN = project 'Done when' met + lab 'Done when' met + job-hunt task done. | Q47: 15 | R47: ☐
A48: ☐ | B48: 46376 | C48: Sun | D48: 7 | E48: 2: AI SRE Copilot v1 | F48: 5 | G48: 10:30-13:00 PROJECT (2.5 h) | H48: S05 | I48: alert-receiver + incident store (event-style records) | J48: 1. FastAPI POST /webhooks/alertmanager with Pydantic models; raw payload stored. 2. Dedup by fingerprint within 30 min -> one incident; unsupported alertnames stored as unsupported. 3. incidents/incident_events tables with event_id, incident_id, correlation_id, schema_version (seams for Kafka later). 4. Structured logs carrying correlation_id. | K48: 10 identical webhooks create exactly 1 incident and 9 recorded duplicates; an unknown alert is stored as unsupported. | L48: Alertmanager webhook payload format; your D12/D13 idempotency notes. | O48: 14:00-15:00 MOCK & STORY: STAR stories 3-4 (ownership; learning something fast). 15:00-16:00 READ / CERT: AI-102 prep 2: generative AI solutions with Azure OpenAI / AI Foundry. 16:00-16:30 WEEKLY REVIEW: tick the week, scorecard (project cards x/6, LARP x/4, mock score, applications x/15), 3 lines in LOG.md, read next week's first card. | P48: WIN = project 'Done when' met + story/mock recorded + weekly review written (scorecard, 3 lines, next week's first card read). | R48: ☐
A49: ☐ | B49: 46377 | C49: Mon | D49: 8 | E49: 2: AI SRE Copilot v1 | F49: 3 | G49: 22:00-23:45 PROJECT (105 min) | H49: S06 | I49: Read-only Kubernetes tools + tool registry | J49: 1. Typed tools: get_pod_status, get_events, get_logs(tail, since), get_rollout_history, get_resource_usage. 2. get_recent_changes(namespace, since): rollout history plus the diff of image tag, env vars and ConfigMaps between the last revisions - most incidents follow a change (the 'PR review' idea, aimed at deploys). 3. ServiceAccount + ClusterRole with get/list/watch only. 4. Registry: name, JSON schema, risk=read, timeout; evidence items stored immutable with ids. 5. Fake k8s client for tests. | K49: `kubectl auth can-i patch deployments --as=system:serviceaccount:platform:evidence` says no, and tool tests pass with the fake client. | L49: kubernetes Python client docs; Kubernetes 'Using RBAC Authorization'. | M49: 23:45-01:00 LARP (75 min) | N49: L23 Redis in depth | P49: WIN = project 'Done when' met and pushed (or one clean carry-over line in docs/LOG.md) + LARP quiz scored, misses written as flashcards + DSA ticked (office). | R49: ☐
A50: ☐ | B50: 46378 | C50: Tue | D50: 8 | E50: 2: AI SRE Copilot v1 | F50: 3 | G50: 22:00-23:45 PROJECT (105 min) | H50: S07 | I50: Metrics tool, evidence caps and truncation | J50: 1. query_prometheus with allow-listed PromQL templates only (no free-form queries from the model). 2. Evidence caps: 12 tool calls / 60 s per incident; truncated flag; log line caps. 3. Token accounting per incident. | K50: The OOM scenario evidence includes a memory-trend item with an id, and a forced cap ends with truncated=true rather than an error. | L50: Prometheus HTTP API docs; PromQL basics (rate, increase, container_memory_working_set_bytes). | M50: 23:45-01:00 LARP (75 min) | N50: L24 Caching patterns (including LLM caching) | P50: WIN = project 'Done when' met and pushed (or one clean carry-over line in docs/LOG.md) + LARP quiz scored, misses written as flashcards + DSA ticked (office). | R50: ☐
A51: ☐ | B51: 46379 | C51: Wed | D51: 8 | E51: 2: AI SRE Copilot v1 | F51: 3 | G51: 22:00-23:45 PROJECT (105 min) | H51: S08 | I51: SRE MCP server (read-only tools) | J51: 1. Expose the S06/S07 tools via FastMCP with a bearer token. 2. Agent will consume them through langchain-mcp-adapters. 3. Test with MCP Inspector and from Claude Code ('why is the api pod restarting?'). | K51: MCP Inspector calls get_events on the victim namespace, and Claude Code can investigate a live fault through your server. | L51: Your D30 MCP server; MCP docs 'Transports'. | M51: 23:45-01:00 LARP (75 min) | N51: L25 Rate limiting algorithms | P51: WIN = project 'Done when' met and pushed (or one clean carry-over line in docs/LOG.md) + LARP quiz scored, misses written as flashcards + DSA ticked (office). | R51: ☐
A52: ☐ | B52: 46380 | C52: Thu | D52: 8 | E52: 2: AI SRE Copilot v1 | F52: 3 | G52: 22:00-23:45 PROJECT (105 min) | H52: S09 | I52: Diagnosis agent v1 with cited hypotheses | J52: 1. LangGraph agent with the MCP tools -> structured Diagnosis {cause_class enum incl. insufficient_evidence, hypotheses[{text, evidence_ids}], confidence, suggested_action}. 2. Validator rejects unknown evidence ids and re-asks once. 3. Change correlation: the agent calls get_recent_changes first and states whether a change in the last 30 minutes is a suspect, citing its evidence id (bad-image and bad-config faults should be blamed on the change). 4. Prompt version hash stored with each diagnosis. | K52: The kill-pod fixture produces a valid diagnosis citing at least one real evidence id, and a test proves an invented id is rejected. | L52: LangGraph 'prebuilt ReAct agent' docs; your D10 citation validator. | M52: 23:45-01:00 LARP (75 min) | N52: L26 Designing multi-agent systems | P52: WIN = project 'Done when' met and pushed (or one clean carry-over line in docs/LOG.md) + LARP quiz scored, misses written as flashcards + DSA ticked (office). | R52: ☐
A53: ☐ | B53: 46381 | C53: Fri | D53: 8 | E53: 2: AI SRE Copilot v1 | F53: 3 | G53: 22:00-23:45 BUFFER + POLISH | H53: BUF | I53: Carry-over first | J53: Carry-over first. If nothing is left: write the ADR for this week's main decision, then 30 min applications/follow-ups. | K53: No open carry-over from this week (or exactly one carried line in docs/LOG.md). | M53: 23:45-01:00 WEEKLY MOCK | N53: Weekly mock interview (Friday prompt). Topics: L23 Redis in depth, L24 Caching patterns (including LLM caching), L25 Rate limiting algorithms, L26 Designing multi-agent systems | P53: WIN = carry-over cleared (or the polish task done) + weekly mock scored with your 5 'rewrite' answers listed. | R53: ☐
A54: ☐ | B54: 46382 | C54: Sat | D54: 8 | E54: 2: AI SRE Copilot v1 | F54: 5 | G54: 10:30-13:30 PROJECT (3 h) | H54: S10 | I54: Multi-agent supervisor: triage -> evidence -> diagnosis -> policy | J54: 1. Supervisor graph: triage (rules first, LLM fallback) -> evidence agent (tool loop) -> diagnosis agent -> policy node (pure code: cause -> action table, confidence gate 0.6 -> escalate). 2. Postgres checkpointer, thread_id = incident_id. 3. Graph diagram in README. | K54: End to end in the cluster, F1 (pod killed) and F3 (OOM) each produce a diagnosis and a policy decision, with the run stored as checkpoints. | L54: LangGraph 'Multi-agent supervisor' tutorial; LangGraph 'Subgraphs'. | O54: 14:30-15:30 BACKEND LAB: LAB07 Lost update. Done when: Two concurrent updates lose one change; fixed with optimistic locking (version) and with SELECT FOR UPDATE; both tested. 16:00-17:00 JOB HUNT: 15 applications + 5 referral asks; follow up on last week's; update Interview Log. 17:00-18:00 OPTIONAL: carry-over, tests, docs (never tomorrow's card) | P54: WIN = project 'Done when' met + lab 'Done when' met + job-hunt task done. | Q54: 15 | R54: ☐
A55: ☐ | B55: 46383 | C55: Sun | D55: 8 | E55: 2: AI SRE Copilot v1 | F55: 5 | G55: 10:30-13:00 PROJECT (2.5 h) | H55: S11 | I55: Incident UI + 60-second slice | J55: 1. Incident list/detail page: raw alert, evidence items, agent step timeline (from checkpoint history), diagnosis. 2. Deploy receiver + agent in-cluster (platform namespace) with the read-only ServiceAccount. 3. Run kill-pod 5 times. | K55: Kill a pod: within about 60 s the incident page shows evidence and a cited diagnosis, 5 of 5 runs. | L55: HTMX docs (optional) or Jinja templates in FastAPI. | O55: 14:00-15:00 MOCK & STORY: System design mock: 'Design a RAG platform for 10k users' (45 min, L38 skeleton). 15:00-16:00 READ / CERT: AI-102 prep 3: Azure AI Search (vector, hybrid, semantic ranker) - map to what you built. 16:00-16:30 WEEKLY REVIEW: tick the week, scorecard (project cards x/6, LARP x/4, mock score, applications x/15), 3 lines in LOG.md, read next week's first card. | P55: WIN = project 'Done when' met + story/mock recorded + weekly review written (scorecard, 3 lines, next week's first card read). | R55: ☐
A56: ☐ | B56: 46384 | C56: Mon | D56: 9 | E56: 2: AI SRE Copilot v1 | F56: 3 | G56: 22:00-23:45 PROJECT (105 min) | H56: S12 | I56: Scenario corpus F1-F8 + runner | J56: 1. F1-F8 as versioned YAML: trigger, expected symptoms, expected cause_class, expected action. 2. make scenario SCENARIO=F3 triggers, waits for the incident, collects the diagnosis, undoes the fault. 3. Freeze: git tag scenarios-v1. | K56: The runner completes F1 and F3 unattended and the scenarios-v1 tag exists. | L56: Your old master plan, section 3 (fault scenarios F1-F8). | M56: 23:45-01:00 LARP (75 min) | N56: L27 PostgreSQL indexes and query plans | P56: WIN = project 'Done when' met and pushed (or one clean carry-over line in docs/LOG.md) + LARP quiz scored, misses written as flashcards + DSA ticked (office). | R56: ☐
A57: ☐ | B57: 46385 | C57: Tue | D57: 9 | E57: 2: AI SRE Copilot v1 | F57: 3 | G57: 22:00-23:45 PROJECT (105 min) | H57: S13 | I57: Eval harness for the agent | J57: 1. Metrics per run: cause_correct, action_correct, citations_valid, abstained, latency, tokens, cost, tool calls. 2. Results to eval/results/*.json + markdown report generator. 3. Store the trajectory (tool sequence) for later analysis. | K57: One full scenario run writes a results row with all metrics and a trajectory. | L57: Anthropic/LangChain blog posts on agent evals (trajectory vs outcome). | M57: 23:45-01:00 LARP (75 min) | N57: L28 Transactions, isolation levels, MVCC and locking | P57: WIN = project 'Done when' met and pushed (or one clean carry-over line in docs/LOG.md) + LARP quiz scored, misses written as flashcards + DSA ticked (office). | R57: ☐
A58: ☐ | B58: 46386 | C58: Wed | D58: 9 | E58: 2: AI SRE Copilot v1 | F58: 3 | G58: 22:00-23:45 PROJECT (105 min) | H58: S14 | I58: Baseline eval run (8 scenarios x 3) | J58: 1. Start the 24 runs; while it runs, write the report skeleton. 2. docs/eval/baseline.md: per-scenario table + overall accuracy + cost per incident. | K58: docs/eval/baseline.md is committed with per-scenario scores and average cost/latency per incident. | L58: - | M58: 23:45-01:00 LARP (75 min) | N58: L29 Evaluating agents and LLM apps in production | P58: WIN = project 'Done when' met and pushed (or one clean carry-over line in docs/LOG.md) + LARP quiz scored, misses written as flashcards + DSA ticked (office). | R58: ☐
A59: ☐ | B59: 46387 | C59: Thu | D59: 9 | E59: 2: AI SRE Copilot v1 | F59: 3 | G59: 22:00-23:45 PROJECT (105 min) | H59: S15 | I59: Failure analysis + fixes (prompts and tools only) | J59: 1. Classify each miss: evidence missing, wrong tool use, reasoning error, label ambiguity. 2. Fix prompts/tools only - never the labels. Rerun failed scenarios. | K59: A written miss analysis exists and the reruns show an improvement or a documented limit. | L59: - | M59: 23:45-01:00 LARP (75 min) | N59: L30 Cost and latency optimisation for LLM applications | P59: WIN = project 'Done when' met and pushed (or one clean carry-over line in docs/LOG.md) + LARP quiz scored, misses written as flashcards + DSA ticked (office). | R59: ☐
A60: ☐ | B60: 46388 | C60: Fri | D60: 9 | E60: 2: AI SRE Copilot v1 | F60: 3 | G60: 22:00-23:45 BUFFER + POLISH | H60: BUF | I60: Carry-over first | J60: Carry-over first. If nothing is left: write the ADR for this week's main decision, then 30 min applications/follow-ups. | K60: No open carry-over from this week (or exactly one carried line in docs/LOG.md). | M60: 23:45-01:00 WEEKLY MOCK | N60: Weekly mock interview (Friday prompt). Topics: L27 PostgreSQL indexes and query plans, L28 Transactions, isolation levels, MVCC and locking, L29 Evaluating agents and LLM apps in production, L30 Cost and latency optimisation for LLM applications | P60: WIN = carry-over cleared (or the polish task done) + weekly mock scored with your 5 'rewrite' answers listed. | R60: ☐
A61: ☐ | B61: 46389 | C61: Sat | D61: 9 | E61: 2: AI SRE Copilot v1 | F61: 5 | G61: 10:30-13:30 PROJECT (3 h) | H61: S16 | I61: Langfuse traces + LLM-as-judge (calibrated) | J61: 1. Trace every agent run with tool spans. 2. Judge rubric (grounded? actionable? safe?) on 10 runs; compare with your manual labels. | K61: Judge agreement with your labels is at least 8 of 10, or the disagreement is documented with the rubric change you made. | L61: Langfuse 'LLM-as-a-judge' docs; Eugene Yan's write-ups on LLM evaluators. | O61: 14:30-15:30 BACKEND LAB: LAB08 Outbox with Redis Streams. Done when: Order + outbox row in one transaction; relay publishes to a Redis Stream; killing the relay loses nothing. 16:00-17:00 JOB HUNT: 15 applications + 5 referral asks; follow up on last week's; update Interview Log. 17:00-18:00 OPTIONAL: carry-over, tests, docs (never tomorrow's card) | P61: WIN = project 'Done when' met + lab 'Done when' met + job-hunt task done. | Q61: 15 | R61: ☐
A62: ☐ | B62: 46390 | C62: Sun | D62: 9 | E62: 2: AI SRE Copilot v1 | F62: 5 | G62: 10:30-13:00 PROJECT (2.5 h) | H62: S17 | I62: Abstention + budgets | J62: 1. F8 (ambiguous) must abstain (insufficient_evidence). 2. Per-incident token and time caps -> degraded diagnosis -> ESCALATED. 3. Second eval run -> docs/eval/v2.md. | K62: F8 abstains at least 4 of 5 times and a forced timeout produces a degraded, escalated incident. | L62: - | O62: 14:00-15:00 MOCK & STORY: Explain the SRE agent architecture in 3 minutes; record; fix. 15:00-16:00 READ / CERT: AI-102 prep 4: Azure AI Document Intelligence (OCR, layout, prebuilt models) - compare with your D31 extractor. 16:00-16:30 WEEKLY REVIEW: tick the week, scorecard (project cards x/6, LARP x/4, mock score, applications x/15), 3 lines in LOG.md, read next week's first card. | P62: WIN = project 'Done when' met + story/mock recorded + weekly review written (scorecard, 3 lines, next week's first card read). | R62: ☐
A63: ☐ | B63: 46391 | C63: Mon | D63: 10 | E63: 2: AI SRE Copilot v1 | F63: 3 | G63: 22:00-23:45 PROJECT (105 min) | H63: S18 | I63: Remediation executor + write RBAC (allow-list) | J63: 1. Separate executor service; Role in victim namespace allowing patch on deployments and deployments/scale only. 2. Actions: restart_deployment, scale_deployment(1..5); server-side dry-run; capture before-state. 3. Save the `kubectl auth can-i` matrix output as proof. | K63: The can-i matrix proves allowed vs denied actions and dry-run previews work for both actions. | L63: Kubernetes 'RBAC' (Role vs ClusterRole), server-side dry-run docs. | M63: 23:45-01:00 LARP (75 min) | N63: L31 REST API design | P63: WIN = project 'Done when' met and pushed (or one clean carry-over line in docs/LOG.md) + LARP quiz scored, misses written as flashcards + DSA ticked (office). | R63: ☐
A64: ☐ | B64: 46392 | C64: Tue | D64: 10 | E64: 2: AI SRE Copilot v1 | F64: 3 | G64: 22:00-23:45 PROJECT (105 min) | H64: S19 | I64: Remediation as an explicit state machine in Postgres | J64: 1. States PROPOSED -> AWAITING_APPROVAL -> EXECUTING -> VERIFYING -> SUCCEEDED, or COMPENSATING -> COMPENSATED, FAILED, REJECTED, EXPIRED. 2. Transition table + tests for every illegal transition. | K64: Every illegal transition has a test that fails as expected, and legal paths are covered. | L64: Any article on finite state machines for workflows; your old plan's saga states. | M64: 23:45-01:00 LARP (75 min) | N64: L32 State machines, sagas and compensation | P64: WIN = project 'Done when' met and pushed (or one clean carry-over line in docs/LOG.md) + LARP quiz scored, misses written as flashcards + DSA ticked (office). | R64: ☐
A65: ☐ | B65: 46393 | C65: Wed | D65: 10 | E65: 2: AI SRE Copilot v1 | F65: 3 | G65: 22:00-23:45 PROJECT (105 min) | H65: S20 | I65: Human approval via LangGraph interrupt | J65: 1. Proposal with dry-run diff and 15-minute expiry; graph interrupts. 2. Approve/reject API with token; expiry job; rejection -> ESCALATED. | K65: Approving changes the replicas for real, a request without the token gets 401, and an expired proposal escalates. | L65: LangGraph 'Human-in-the-loop' docs (you used them in D22). | M65: 23:45-01:00 LARP (75 min) | N65: L33 Guardrails and security for LLM applications | P65: WIN = project 'Done when' met and pushed (or one clean carry-over line in docs/LOG.md) + LARP quiz scored, misses written as flashcards + DSA ticked (office). | R65: ☐
A66: ☐ | B66: 46394 | C66: Thu | D66: 10 | E66: 2: AI SRE Copilot v1 | F66: 3 | G66: 22:00-23:45 PROJECT (105 min) | H66: S21 | I66: Verify + rollback | J66: 1. Verify: readiness + alert-clear within 120 s. 2. On failure: restore the before-state (exempt from bounds); record COMPENSATED. | K66: A forced verification failure restores the before-state. | L66: - | M66: 23:45-01:00 LARP (75 min) | N66: L34 Kubernetes RBAC, ServiceAccounts and least privilege | P66: WIN = project 'Done when' met and pushed (or one clean carry-over line in docs/LOG.md) + LARP quiz scored, misses written as flashcards + DSA ticked (office). | R66: ☐
A67: ☐ | B67: 46395 | C67: Fri | D67: 10 | E67: 2: AI SRE Copilot v1 | F67: 3 | G67: 22:00-23:45 BUFFER + POLISH | H67: BUF | I67: Carry-over first | J67: Carry-over first. If nothing is left: write the ADR for this week's main decision, then 30 min applications/follow-ups. | K67: No open carry-over from this week (or exactly one carried line in docs/LOG.md). | M67: 23:45-01:00 WEEKLY MOCK | N67: Weekly mock interview (Friday prompt). Topics: L31 REST API design, L32 State machines, sagas and compensation, L33 Guardrails and security for LLM applications, L34 Kubernetes RBAC, ServiceAccounts and least privilege | P67: WIN = carry-over cleared (or the polish task done) + weekly mock scored with your 5 'rewrite' answers listed. | R67: ☐
A68: ☐ | B68: 46396 | C68: Sat | D68: 10 | E68: 2: AI SRE Copilot v1 | F68: 5 | G68: 10:30-13:30 PROJECT (3 h) | H68: S22 | I68: Idempotency + crash safety drill | J68: 1. Idempotency key per command; duplicate -> no-op. 2. Harness kills the orchestrator at each step boundary and resumes from the checkpoint. 3. docs/drills/crash-safety.md. | K68: Zero duplicate executions across 10 forced restarts, written up as a drill note. | L68: Your D13 notes; LangGraph durable execution docs. | O68: 14:30-15:30 BACKEND LAB: LAB09 Fan-out/fan-in aggregator. Done when: Aggregator calls 4 services concurrently with per-call timeouts; partial failure returns partial data, not 500. 16:00-17:00 JOB HUNT: 15 applications + 5 referral asks; follow up on last week's; update Interview Log. 17:00-18:00 OPTIONAL: carry-over, tests, docs (never tomorrow's card) | P68: WIN = project 'Done when' met + lab 'Done when' met + job-hunt task done. | Q68: 15 | R68: ☐
A69: ☐ | B69: 46397 | C69: Sun | D69: 10 | E69: 2: AI SRE Copilot v1 | F69: 5 | G69: 10:30-13:00 PROJECT (2.5 h) | H69: S23 | I69: Safety test suite + compensation x10 | J69: 1. Tests: execute without approval refused; out-of-namespace denied by the API server; unknown action rejected. 2. Forced-failure switch; run compensation 10 times. | K69: All safety tests pass and compensation succeeds 10 of 10, with saved output. | L69: - | O69: 14:00-15:00 MOCK & STORY: STAR stories 5-6 (disagreement; a mistake and what you changed). 15:00-16:00 READ / CERT: AI-102 prep 5: agents in Azure AI Foundry Agent Service. 16:00-16:30 WEEKLY REVIEW: tick the week, scorecard (project cards x/6, LARP x/4, mock score, applications x/15), 3 lines in LOG.md, read next week's first card. | P69: WIN = project 'Done when' met + story/mock recorded + weekly review written (scorecard, 3 lines, next week's first card read). | R69: ☐
A70: ☐ | B70: 46398 | C70: Mon | D70: 11 | E70: 2: AI SRE Copilot v1 | F70: 3 | G70: 22:00-23:45 PROJECT (105 min) | H70: S24 | I70: Postmortem writer with linked claims | J70: 1. Code builds the timeline from incident_events; LLM writes the narrative. 2. Each claim carries event ids; validator flags unlinked claims. 3. Similar-incident memory: embed resolved postmortems in pgvector; give the diagnosis agent a search_past_incidents tool (top 3 with links). 4. Reuse the DocuLens text-to-SQL module as query_incident_stats over a read-only incidents view (MTTR, incidents per service, top causes). | K70: A postmortem for one resolved incident is in docs/postmortems/ with every claim linked or flagged. | L70: Google SRE book chapter 'Postmortem Culture' (blameless format). | M70: 23:45-01:00 LARP (75 min) | N70: L35 Distributed systems fundamentals | P70: WIN = project 'Done when' met and pushed (or one clean carry-over line in docs/LOG.md) + LARP quiz scored, misses written as flashcards + DSA ticked (office). | R70: ☐
A71: ☐ | B71: 46399 | C71: Tue | D71: 11 | E71: 2: AI SRE Copilot v1 | F71: 3 | G71: 22:00-23:45 PROJECT (105 min) | H71: S25 | I71: End-to-end remediation scenarios + action-correctness eval | J71: 1. Run F3, F4, F6, F7 through approve -> verify; F1, F2, F5, F8 must give no_action/escalate. 2. Add action correctness to the eval -> docs/eval/v3.md. | K71: docs/eval/v3.md shows cause and action correctness per scenario. | L71: - | M71: 23:45-01:00 LARP (75 min) | N71: L36 Message queues vs event streams: RabbitMQ, Kafka, SQS | P71: WIN = project 'Done when' met and pushed (or one clean carry-over line in docs/LOG.md) + LARP quiz scored, misses written as flashcards + DSA ticked (office). | R71: ☐
A72: ☐ | B72: 46400 | C72: Wed | D72: 11 | E72: 2: AI SRE Copilot v1 | F72: 3 | G72: 22:00-23:45 PROJECT (105 min) | H72: S26 | I72: CI for the SRE project | J72: 1. GitHub Actions: lint, types, unit, contract tests, kubeconform on manifests, eval subset on recorded fixtures. | K72: CI is green and fails on an intentionally broken manifest. | L72: kubeconform README. | M72: 23:45-01:00 LARP (75 min) | N72: L37 Outbox, inbox, DLQ and poison messages | P72: WIN = project 'Done when' met and pushed (or one clean carry-over line in docs/LOG.md) + LARP quiz scored, misses written as flashcards + DSA ticked (office). | R72: ☐
A73: ☐ | B73: 46401 | C73: Thu | D73: 11 | E73: 2: AI SRE Copilot v1 | F73: 3 | G73: 22:00-23:45 PROJECT (105 min) | H73: S27 | I73: README, architecture, ADRs | J73: 1. Diagram, one-command quickstart, supported failure classes, eval numbers, known limits, at least 5 ADRs. | K73: A fresh clone follows the quickstart successfully. | L73: - | M73: 23:45-01:00 LARP (75 min) | N73: L38 System design: a RAG platform for 10,000 users | P73: WIN = project 'Done when' met and pushed (or one clean carry-over line in docs/LOG.md) + LARP quiz scored, misses written as flashcards + DSA ticked (office). | R73: ☐
A74: ☐ | B74: 46402 | C74: Fri | D74: 11 | E74: 2: AI SRE Copilot v1 | F74: 3 | G74: 22:00-23:45 BUFFER + POLISH | H74: BUF | I74: Carry-over first | J74: Carry-over first. If nothing is left: write the ADR for this week's main decision, then 30 min applications/follow-ups. | K74: No open carry-over from this week (or exactly one carried line in docs/LOG.md). | M74: 23:45-01:00 WEEKLY MOCK | N74: Weekly mock interview (Friday prompt). Topics: L35 Distributed systems fundamentals, L36 Message queues vs event streams: RabbitMQ, Kafka, SQS, L37 Outbox, inbox, DLQ and poison messages, L38 System design: a RAG platform for 10,000 users | P74: WIN = carry-over cleared (or the polish task done) + weekly mock scored with your 5 'rewrite' answers listed. | R74: ☐
A75: ☐ | B75: 46403 | C75: Sat | D75: 11 | E75: 2: AI SRE Copilot v1 | F75: 5 | G75: 10:30-13:30 PROJECT (3 h) | H75: S28 | I75: Demo video + resume v2 | J75: 1. 5-minute demo: break -> diagnose -> approve -> verify -> postmortem. 2. Resume bullets from verified numbers only; LinkedIn post with the demo. | K75: v1.0 is tagged, the demo is linked in the README, and the resume has SRE bullets with measured numbers. | L75: - | O75: 14:30-15:30 BACKEND LAB: LAB10 SSE/WebSocket fan-out. Done when: Two server instances share Redis pub/sub; a message reaches clients on both instances. 16:00-17:00 JOB HUNT: 15 applications + 5 referral asks; follow up on last week's; update Interview Log. 17:00-18:00 OPTIONAL: carry-over, tests, docs (never tomorrow's card) | P75: WIN = project 'Done when' met + lab 'Done when' met + job-hunt task done. | Q75: 15 | R75: ☐
A76: ☐ | B76: 46404 | C76: Sun | D76: 11 | E76: 2: AI SRE Copilot v1 | F76: 5 | G76: 10:30-13:00 PROJECT (2.5 h) | H76: S29 | I76: Stage 2 buffer | J76: 1. Finish any carry-over from Stage 2. If nothing is left: write a blog post 'How I evaluated an SRE agent'. | K76: No open Stage 2 carry-over remains. | L76: - | O76: 14:00-15:00 MOCK & STORY: Full mock: SRE project deep dive + safety and agent-design questions. 15:00-16:00 READ / CERT: AI-102 prep 6: natural language processing solutions (language service, translator). 16:00-16:30 WEEKLY REVIEW: tick the week, scorecard (project cards x/6, LARP x/4, mock score, applications x/15), 3 lines in LOG.md, read next week's first card. | P76: WIN = project 'Done when' met + story/mock recorded + weekly review written (scorecard, 3 lines, next week's first card read). | R76: ☐ | S76: Gate 2: AI SRE Copilot v1 finished. Resume v3 with two projects. Aim at AI-agent / LLM-engineer roles. | Stage 2 exit: Eval v3 with cause and action correctness; safety tests + compensation 10/10; crash drill; v1.0 tag; demo video.
A77: ☐ | B77: 46405 | C77: Mon | D77: 12 | E77: 3: PDF Translator (your PRD) | F77: 3 | G77: 22:00-23:45 PROJECT (105 min) | H77: T01 | I77: Translator app + paragraph regions | J77: 1. Create apps/translator next to DocuLens in one monorepo; move shared code (PDF extraction, OCR, storage, auth, model router, outbox) into packages/ so both apps import it. 2. Reuse D04 blocks; group spans into paragraph regions with bbox, font, alignment; regions table linked to document/page. | K77: A fixture page produces paragraph regions (not per-line fragments) with bboxes you checked visually. | L77: Use the tutor prompt with the card title to get a 10-minute briefing before you build. | M77: 23:45-01:00 LARP (75 min) | N77: L39 PDF internals and document parsing | P77: WIN = project 'Done when' met and pushed (or one clean carry-over line in docs/LOG.md) + LARP quiz scored, misses written as flashcards + DSA ticked (office). | R77: ☐
A78: ☐ | B78: 46406 | C78: Tue | D78: 12 | E78: 3: PDF Translator (your PRD) | F78: 3 | G78: 22:00-23:45 PROJECT (105 min) | H78: T02 | I78: Region translation through the router (structured, batched) | J78: 1. Capability 'translate' in models.yaml. 2. Batch regions per page; schema {region_id, translated_text}; validate every id returns. | K78: A page of regions translates in one call per batch with all ids accounted for. | L78: Use the tutor prompt with the card title to get a 10-minute briefing before you build. | M78: 23:45-01:00 LARP (75 min) | N78: L40 Ingestion pipeline design at scale | P78: WIN = project 'Done when' met and pushed (or one clean carry-over line in docs/LOG.md) + LARP quiz scored, misses written as flashcards + DSA ticked (office). | R78: ☐
A79: ☐ | B79: 46407 | C79: Wed | D79: 12 | E79: 3: PDF Translator (your PRD) | F79: 3 | G79: 22:00-23:45 PROJECT (105 min) | H79: T03 | I79: Overlay renderer v1 (redact + insert) | J79: 1. page.add_redact_annot + apply_redactions to remove source text; insert_htmlbox/insert_textbox for the translation. 2. Same page count, selectable text. | K79: The output PDF opens, keeps page count, and translated text is selectable in roughly the original positions. | L79: Use the tutor prompt with the card title to get a 10-minute briefing before you build. | M79: 23:45-01:00 LARP (75 min) | N79: L41 Vector databases compared | P79: WIN = project 'Done when' met and pushed (or one clean carry-over line in docs/LOG.md) + LARP quiz scored, misses written as flashcards + DSA ticked (office). | R79: ☐
A80: ☐ | B80: 46408 | C80: Thu | D80: 12 | E80: 3: PDF Translator (your PRD) | F80: 3 | G80: 22:00-23:45 PROJECT (105 min) | H80: T04 | I80: Fit engine: wrap, shrink-to-fit, fit_status | J80: 1. Measure text; wrap to bbox; shrink within min/max font size. 2. fit_status fit|shrunk|overflow|review_required per region. | K80: Tests cover fit, shrunk and overflow, and every rendered region has a fit_status. | L80: Use the tutor prompt with the card title to get a 10-minute briefing before you build. | M80: 23:45-01:00 LARP (75 min) | N80: L42 Prompt injection through documents and data governance | P80: WIN = project 'Done when' met and pushed (or one clean carry-over line in docs/LOG.md) + LARP quiz scored, misses written as flashcards + DSA ticked (office). | R80: ☐
A81: ☐ | B81: 46409 | C81: Fri | D81: 12 | E81: 3: PDF Translator (your PRD) | F81: 3 | G81: 22:00-23:45 BUFFER + POLISH | H81: BUF | I81: Carry-over first | J81: Carry-over first. If nothing is left: write the ADR for this week's main decision, then 30 min applications/follow-ups. | K81: No open carry-over from this week (or exactly one carried line in docs/LOG.md). | M81: 23:45-01:00 WEEKLY MOCK | N81: Weekly mock interview (Friday prompt). Topics: L39 PDF internals and document parsing, L40 Ingestion pipeline design at scale, L41 Vector databases compared, L42 Prompt injection through documents and data governance | P81: WIN = carry-over cleared (or the polish task done) + weekly mock scored with your 5 'rewrite' answers listed. | R81: ☐
A82: ☐ | B82: 46410 | C82: Sat | D82: 12 | E82: 3: PDF Translator (your PRD) | F82: 5 | G82: 10:30-13:30 PROJECT (3 h) | H82: T05 | I82: Async translation job with per-page progress | J82: 1. POST /documents/{id}/translations -> 202; Celery chain per page; progress events. 2. Idempotency key on the request. | K82: A 10-page job shows per-page progress and a duplicate request reuses the same job. | L82: Use the tutor prompt with the card title to get a 10-minute briefing before you build. | O82: 14:30-15:30 BACKEND LAB: LAB11 Consistent hashing. Done when: Ring with virtual nodes; adding a node moves about 1/N keys (measured) vs hash % N moving most keys. 16:00-17:00 JOB HUNT: GATE 2: resume v3 with both projects. 15 applications aimed at AI-agent / LLM-engineer roles + 5 referral asks. 17:00-18:00 OPTIONAL: carry-over, tests, docs (never tomorrow's card) | P82: WIN = project 'Done when' met + lab 'Done when' met + job-hunt task done. | Q82: 15 | R82: ☐
A83: ☐ | B83: 46411 | C83: Sun | D83: 12 | E83: 3: PDF Translator (your PRD) | F83: 5 | G83: 10:30-13:00 PROJECT (2.5 h) | H83: T06 | I83: Previews + secure download | J83: 1. Render original/output pages to PNG; side-by-side endpoint. 2. Blob SAS download URL valid for 10 minutes, owner only. | K83: The owner sees side-by-side previews and a stranger's request gets 404. | L83: Use the tutor prompt with the card title to get a 10-minute briefing before you build. | O83: 14:00-15:00 MOCK & STORY: System design drill (45 min) from the Design Drills list in the roadmap; write 5 bullets on what you would change. 15:00-16:00 READ / CERT: AI-102 prep 7: computer vision solutions. 16:00-16:30 WEEKLY REVIEW: tick the week, scorecard (project cards x/6, LARP x/4, mock score, applications x/15), 3 lines in LOG.md, read next week's first card. | P83: WIN = project 'Done when' met + story/mock recorded + weekly review written (scorecard, 3 lines, next week's first card read). | R83: ☐
A84: ☐ | B84: 46412 | C84: Mon | D84: 13 | E84: 3: PDF Translator (your PRD) | F84: 3 | G84: 22:00-23:45 PROJECT (105 min) | H84: T07 | I84: Glossary: table, CRUD, CSV import | J84: 1. glossary_entries per workspace + language pair; CRUD with RBAC; CSV import with row validation. | K84: A 20-row CSV imports with clear errors for bad rows. | L84: Use the tutor prompt with the card title to get a 10-minute briefing before you build. | M84: 23:45-01:00 LARP (75 min) | N84: L43 Framework landscape: LangChain, LangGraph, LlamaIndex, Pydantic AI, OpenAI Agents SDK, CrewAI, Semantic Kernel | P84: WIN = project 'Done when' met and pushed (or one clean carry-over line in docs/LOG.md) + LARP quiz scored, misses written as flashcards + DSA ticked (office). | R84: ☐
A85: ☐ | B85: 46413 | C85: Tue | D85: 13 | E85: 3: PDF Translator (your PRD) | F85: 3 | G85: 22:00-23:45 PROJECT (105 min) | H85: T08 | I85: Translation memory + scoped retrieval (pgvector) | J85: 1. Approved segments -> translation_memory with embeddings. 2. Retrieve by workspace + language pair + approved state. | K85: A two-workspace test proves memory never leaks across workspaces. | L85: Use the tutor prompt with the card title to get a 10-minute briefing before you build. | M85: 23:45-01:00 LARP (75 min) | N85: L44 Async Python deep dive and concurrency control | P85: WIN = project 'Done when' met and pushed (or one clean carry-over line in docs/LOG.md) + LARP quiz scored, misses written as flashcards + DSA ticked (office). | R85: ☐
A86: ☐ | B86: 46414 | C86: Wed | D86: 13 | E86: 3: PDF Translator (your PRD) | F86: 3 | G86: 22:00-23:45 PROJECT (105 min) | H86: T09 | I86: Constraint-aware translation + glossary compliance validator | J86: 1. Inject retrieved terms/memory ids into the prompt; output lists applied ids. 2. Validator flags a required term missing in output. | K86: A deliberately wrong term is flagged and routed to review. | L86: Use the tutor prompt with the card title to get a 10-minute briefing before you build. | M86: 23:45-01:00 LARP (75 min) | N86: L45 Testing backend and LLM systems | P86: WIN = project 'Done when' met and pushed (or one clean carry-over line in docs/LOG.md) + LARP quiz scored, misses written as flashcards + DSA ticked (office). | R86: ☐
A87: ☐ | B87: 46415 | C87: Thu | D87: 13 | E87: 3: PDF Translator (your PRD) | F87: 3 | G87: 22:00-23:45 PROJECT (105 min) | H87: T10 | I87: Translation eval | J87: 1. 20 reference segments; chrF (sacrebleu) + glossary compliance %; LLM judge for fluency on a sample. 2. docs/eval/translation_v1.md. | K87: The translation eval report shows chrF, compliance % and judge scores. | L87: Use the tutor prompt with the card title to get a 10-minute briefing before you build. | M87: 23:45-01:00 LARP (75 min) | N87: L46 GraphRAG and knowledge graphs | P87: WIN = project 'Done when' met and pushed (or one clean carry-over line in docs/LOG.md) + LARP quiz scored, misses written as flashcards + DSA ticked (office). | R87: ☐
A88: ☐ | B88: 46416 | C88: Fri | D88: 13 | E88: 3: PDF Translator (your PRD) | F88: 3 | G88: 22:00-23:45 BUFFER + POLISH | H88: BUF | I88: Carry-over first | J88: Carry-over first. If nothing is left: write the ADR for this week's main decision, then 30 min applications/follow-ups. | K88: No open carry-over from this week (or exactly one carried line in docs/LOG.md). | M88: 23:45-01:00 WEEKLY MOCK | N88: Weekly mock interview (Friday prompt). Topics: L43 Framework landscape: LangChain, LangGraph, LlamaIndex, Pydantic AI, OpenAI Agents SDK, CrewAI, Semantic Kernel, L44 Async Python deep dive and concurrency control, L45 Testing backend and LLM systems, L46 GraphRAG and knowledge graphs | P88: WIN = carry-over cleared (or the polish task done) + weekly mock scored with your 5 'rewrite' answers listed. | R88: ☐
A89: ☐ | B89: 46417 | C89: Sat | D89: 13 | E89: 3: PDF Translator (your PRD) | F89: 5 | G89: 10:30-13:30 PROJECT (3 h) | H89: T11 | I89: LangGraph translation workflow | J89: 1. Nodes: classify page -> extract/OCR -> retrieve context -> translate -> validate -> fit -> (review gate) -> render. 2. Retry fit once with a different strategy. | K89: A native PDF runs through the graph end to end and an overflow region pauses at the review gate. | L89: Use the tutor prompt with the card title to get a 10-minute briefing before you build. | O89: 14:30-15:30 BACKEND LAB: LAB12 Load balancer. Done when: Round robin + least connections + health checks; an unhealthy backend is removed and re-added. 16:00-17:00 JOB HUNT: 15 applications + 5 referral asks until you have an offer you accept; then switch to maintenance (see roadmap section 9). 17:00-18:00 OPTIONAL: carry-over, tests, docs (never tomorrow's card) | P89: WIN = project 'Done when' met + lab 'Done when' met + job-hunt task done. | Q89: 15 | R89: ☐
A90: ☐ | B90: 46418 | C90: Sun | D90: 13 | E90: 3: PDF Translator (your PRD) | F90: 5 | G90: 10:30-13:00 PROJECT (2.5 h) | H90: T12 | I90: Review API: edit, approve, new version, feed memory | J90: 1. PATCH region -> approve; re-render creates version 2 (v1 immutable). 2. Approved edits become translation memory. | K90: Editing a region produces v2, v1 is unchanged, and the edit appears in memory retrieval. | L90: Use the tutor prompt with the card title to get a 10-minute briefing before you build. | O90: 14:00-15:00 MOCK & STORY: Mock from your Interview Log: replay every question you were asked this fortnight; fix weak answers in the Answer Bank. 15:00-16:00 READ / CERT: AI-102: free Microsoft Learn practice assessment #1; error log of weak areas. 16:00-16:30 WEEKLY REVIEW: tick the week, scorecard (project cards x/6, LARP x/4, mock score, applications x/15), 3 lines in LOG.md, read next week's first card. | P90: WIN = project 'Done when' met + story/mock recorded + weekly review written (scorecard, 3 lines, next week's first card read). | R90: ☐
A91: ☐ | B91: 46419 | C91: Mon | D91: 14 | E91: 3: PDF Translator (your PRD) | F91: 3 | G91: 22:00-23:45 PROJECT (105 min) | H91: T13 | I91: OCR route for scanned pages | J91: 1. Tesseract adapter (pytesseract) with confidence + bbox; optional Azure Document Intelligence adapter. 2. Low confidence -> review. | K91: The scanned fixture is processed and a low-confidence page is flagged for review. | L91: Use the tutor prompt with the card title to get a 10-minute briefing before you build. | M91: 23:45-01:00 LARP (75 min) | N91: L47 Fine-tuning vs RAG vs prompting | P91: WIN = project 'Done when' met and pushed (or one clean carry-over line in docs/LOG.md) + LARP quiz scored, misses written as flashcards + DSA ticked (office). | R91: ☐
A92: ☐ | B92: 46420 | C92: Tue | D92: 14 | E92: 3: PDF Translator (your PRD) | F92: 3 | G92: 22:00-23:45 PROJECT (105 min) | H92: T14 | I92: Tables: cell-by-cell translation | J92: 1. page.find_tables(); translate cells; keep cell boundaries. | K92: A simple table keeps its cell structure after translation. | L92: Use the tutor prompt with the card title to get a 10-minute briefing before you build. | M92: 23:45-01:00 LARP (75 min) | N92: L48 Streaming and real-time: SSE, WebSockets, long polling | P92: WIN = project 'Done when' met and pushed (or one clean carry-over line in docs/LOG.md) + LARP quiz scored, misses written as flashcards + DSA ticked (office). | R92: ☐
A93: ☐ | B93: 46421 | C93: Wed | D93: 14 | E93: 3: PDF Translator (your PRD) | F93: 3 | G93: 22:00-23:45 PROJECT (105 min) | H93: T15 | I93: Fonts and one script family (Hindi/Devanagari) | J93: 1. Noto fallback; glyph coverage check; review status when glyphs are missing. | K93: An English -> Hindi fixture renders correctly or is honestly flagged. | L93: Use the tutor prompt with the card title to get a 10-minute briefing before you build. | M93: 23:45-01:00 LARP (75 min) | N93: L49 AI gateway design | P93: WIN = project 'Done when' met and pushed (or one clean carry-over line in docs/LOG.md) + LARP quiz scored, misses written as flashcards + DSA ticked (office). | R93: ☐
A94: ☐ | B94: 46422 | C94: Thu | D94: 14 | E94: 3: PDF Translator (your PRD) | F94: 3 | G94: 22:00-23:45 PROJECT (105 min) | H94: T16 | I94: Visual QA: overlap/overflow detector + page score | J94: 1. bbox overlap checks; page pass/warning/review_required. | K94: Three fixture classes get page scores and a broken page is caught. | L94: Use the tutor prompt with the card title to get a 10-minute briefing before you build. | M94: 23:45-01:00 LARP (75 min) | N94: L50 Semantic caching and prompt caching | P94: WIN = project 'Done when' met and pushed (or one clean carry-over line in docs/LOG.md) + LARP quiz scored, misses written as flashcards + DSA ticked (office). | R94: ☐
A95: ☐ | B95: 46423 | C95: Fri | D95: 14 | E95: 3: PDF Translator (your PRD) | F95: 3 | G95: 22:00-23:45 BUFFER + POLISH | H95: BUF | I95: Carry-over first | J95: Carry-over first. If nothing is left: write the ADR for this week's main decision, then 30 min applications/follow-ups. | K95: No open carry-over from this week (or exactly one carried line in docs/LOG.md). | M95: 23:45-01:00 WEEKLY MOCK | N95: Weekly mock interview (Friday prompt). Topics: L47 Fine-tuning vs RAG vs prompting, L48 Streaming and real-time: SSE, WebSockets, long polling, L49 AI gateway design, L50 Semantic caching and prompt caching | P95: WIN = carry-over cleared (or the polish task done) + weekly mock scored with your 5 'rewrite' answers listed. | R95: ☐
A96: ☐ | B96: 46424 | C96: Sat | D96: 14 | E96: 3: PDF Translator (your PRD) | F96: 5 | G96: 10:30-13:30 PROJECT (3 h) | H96: T17 | I96: Deploy the translator + CI with PDF fixtures | J96: 1. Worker image with Tesseract + fonts; CI runs fixture tests. 2. Redeploy to Container Apps. | K96: The cloud URL translates a fixture PDF and CI runs the PDF fixture tests. | L96: Use the tutor prompt with the card title to get a 10-minute briefing before you build. | O96: 14:30-15:30 BACKEND LAB: LAB13 Distributed lock. Done when: Redis SET NX PX lock with token check on release; write-up on why fencing tokens are needed. 16:00-17:00 JOB HUNT: 15 applications + 5 referral asks until you have an offer you accept; then switch to maintenance (see roadmap section 9). 17:00-18:00 OPTIONAL: carry-over, tests, docs (never tomorrow's card) | P96: WIN = project 'Done when' met + lab 'Done when' met + job-hunt task done. | Q96: 15 | R96: ☐
A97: ☐ | B97: 46425 | C97: Sun | D97: 14 | E97: 3: PDF Translator (your PRD) | F97: 5 | G97: 10:30-13:00 PROJECT (2.5 h) | H97: T18 | I97: PDF Translator README, support matrix, demo, resume bullets | J97: 1. Support matrix (doc types, scripts, tables) stated honestly; 3-minute demo; resume entry as its own project. | K97: PDF Translator v1.0 is tagged with the support matrix and demo linked. | L97: Use the tutor prompt with the card title to get a 10-minute briefing before you build. | O97: 14:00-15:00 MOCK & STORY: System design drill (45 min) from the Design Drills list in the roadmap; write 5 bullets on what you would change. 15:00-16:00 READ / CERT: AI-102: practice assessment #2 + weak-area review. 16:00-16:30 WEEKLY REVIEW: tick the week, scorecard (project cards x/6, LARP x/4, mock score, applications x/15), 3 lines in LOG.md, read next week's first card. | P97: WIN = project 'Done when' met + story/mock recorded + weekly review written (scorecard, 3 lines, next week's first card read). | R97: ☐
A98: ☐ | B98: 46426 | C98: Mon | D98: 15 | E98: 3: PDF Translator (your PRD) | F98: 3 | G98: 22:00-23:45 PROJECT (105 min) | H98: T19 | I98: Extract the AI gateway + per-workspace quotas | J98: 1. Move the router + usage ledger into ai-gateway (FastAPI), used by DocuLens, the translator and the SRE agent; narrow OpenAI-compatible /v1/chat/completions facade backed by real routing. 2. Daily token budget + request rate limit per workspace in Redis; 429 with a reason. | K98: All three projects call the gateway, the ledger shows usage from each, and exceeding a budget returns 429. | L98: Use the tutor prompt with the card title to get a 10-minute briefing before you build. | M98: 23:45-01:00 LARP (75 min) | N98: L51 System design: document translation service | P98: WIN = project 'Done when' met and pushed (or one clean carry-over line in docs/LOG.md) + LARP quiz scored, misses written as flashcards + DSA ticked (office). | R98: ☐
A99: ☐ | B99: 46427 | C99: Tue | D99: 15 | E99: 3: PDF Translator (your PRD) | F99: 3 | G99: 22:00-23:45 PROJECT (105 min) | H99: T20 | I99: Prompt registry with versions | J99: 1. prompts table (name, version, status); only approved versions in prod; version id on every run. | K99: Changing a prompt creates a new version and runs reference it. | L99: Use the tutor prompt with the card title to get a 10-minute briefing before you build. | M99: 23:45-01:00 LARP (75 min) | N99: L52 System design: AI support assistant with human handoff | P99: WIN = project 'Done when' met and pushed (or one clean carry-over line in docs/LOG.md) + LARP quiz scored, misses written as flashcards + DSA ticked (office). | R99: ☐
A100: ☐ | B100: 46428 | C100: Wed | D100: 15 | E100: 3: PDF Translator (your PRD) | F100: 3 | G100: 22:00-23:45 PROJECT (105 min) | H100: T21 | I100: Translation events, webhooks and a failure drill (PRD phase 8) | J100: 1. Reuse the DocuLens outbox + webhook relay for translation.completed, translation.failed and review.required. 2. Replaying an event creates no duplicate version or webhook (idempotency test). 3. Drill: simulate an OCR timeout and a missing font; find the failing stage from logs and traces; write docs/drills/translator.md. | K100: Each event's webhook arrives once per job, and the drill write-up shows how you found the failing stage. | L100: Use the tutor prompt with the card title to get a 10-minute briefing before you build. | M100: 23:45-01:00 LARP (75 min) | N100: L53 Behavioural: your story as an AI/backend engineer | P100: WIN = project 'Done when' met and pushed (or one clean carry-over line in docs/LOG.md) + LARP quiz scored, misses written as flashcards + DSA ticked (office). | R100: ☐
...

Sheet Weekly Plan
A1: Weekly plan
A2: A week is successful when its 'WIN when' line is true. Planned/ticked days come from Daily Plan.
A4: Wk | B4: Mon | C4: Sun | D4: Stage | E4: Week is a WIN when | F4: Project cards | G4: LARP topics | H4: Backend lab | I4: Job hunt | J4: Apps/wk | K4: Days planned | L4: Days ticked | M4: % done
A5: 1 | B5: 46328 | C5: 46334 | D5: 1: DocuLens: RAG platform + document workflow automation | E5: Repo, Docker services, schema, upload with coordinates, three chunkers. You can explain async vs threads and FastAPI DI. | F5: D01 Dev setup + repo + hello FastAPI; D02 Docker Compose: Postgres + pgvector + Redis, settings, readiness; D03 Alembic + data model v1; D04 Upload + PyMuPDF extraction with coordinates; D05 Chunking strategies v1 (layout-aware) | G5: L01 Python async/await and the event loop; L02 FastAPI internals: dependency injection, Pydantic v2, sync vs async | H5: LAB00 HTTP from raw sockets | I5: LinkedIn: headline 'AI Engineer | LLM agents, RAG | Python, FastAPI | Copilot Studio', About (5 lines), skills; open-to-work for recruiters only. | J5: 0 | K5: =COUNTIF('Daily Plan'!$D$2:$D$209,A5) | L5: =COUNTIFS('Daily Plan'!$D$2:$D$209,A5,'Daily Plan'!$A$2:$A$209,"☑") | M5: =IF(K5=0,0,L5/K5)
A6: 2 | B6: 46335 | C6: 46341 | D6: 1: DocuLens: RAG platform + document workflow automation | E6: Dense + lexical + hybrid (RRF) + rerank retrieval and a cited, streamed answer. You can whiteboard the retrieval pipeline. | F6: D06 Embeddings + dense search on pgvector (HNSW); D07 Lexical leg: Postgres full-text search; D08 Hybrid retrieval with Reciprocal Rank Fusion + metadata filters; D09 Reranking with a cross-encoder; D10 LLM layer: providers, structured output, grounded answers with citations; D11 Streaming answers over SSE + conversation memory | G6: L03 Embeddings and vector search (ANN, HNSW vs IVFFlat); L04 BM25 and full-text search; L05 Hybrid search, Reciprocal Rank Fusion and metadata filtering; L06 Rerankers: bi-encoders vs cross-encoders | H6: LAB01 Cache-aside + stampede | I6: Resume v1 draft (1 page): Copilot Studio work in engineering terms + DocuLens 'in progress' section. Build a JD keyword list from the JD Skill Matrix sheet. | J6: 0 | K6: =COUNTIF('Daily Plan'!$D$2:$D$209,A6) | L6: =COUNTIFS('Daily Plan'!$D$2:$D$209,A6,'Daily Plan'!$A$2:$A$209,"☑") | M6: =IF(K6=0,0,L6/K6)
A7: 3 | B7: 46342 | C7: 46348 | D7: 1: DocuLens: RAG platform + document workflow automation | E7: Async ingestion with Celery, dedup, metadata, frozen golden set and the first eval tables. GATE 0: resume out, first applications. | F7: D12 Async ingestion with Celery + Redis (202 + job status); D13 Retries, idempotent tasks and chunk-level de-duplication; D14 Metadata extraction with structured outputs + filtered search; D15 Golden evaluation dataset (frozen); D16 Retrieval evaluation harness: numbers for your design choices; D17 Generation eval (RAGAS or DeepEval) + Langfuse tracing | G7: L07 Task queues: Celery, Redis, delivery guarantees; L08 Idempotency and de-duplication; L09 Structured outputs and prompt engineering; L10 Evaluating RAG systems | H7: LAB02 Rate limiters | I7: Target list: 40 companies (product/SaaS, AI startups, GCCs) + 10 recruiters in the Job Tracker; job alerts on LinkedIn, Naukri, Instahyre, Wellfound. Resume v1 final. GATE 0 on Sunday: send the first 3 applications. | J7: 3 | K7: =COUNTIF('Daily Plan'!$D$2:$D$209,A7) | L7: =COUNTIFS('Daily Plan'!$D$2:$D$209,A7,'Daily Plan'!$A$2:$A$209,"☑") | M7: =IF(K7=0,0,L7/K7)
A8: 4 | B8: 46349 | C8: 46355 | D8: 1: DocuLens: RAG platform + document workflow automation | E8: Model router with fallback, query transformation, LangGraph agent with routing, tools, human review and map-reduce compare. | F8: D18 Model router: capability routing, fallback, usage ledger; D19 Query transformation: rewrite, multi-query, HyDE; D20 LangGraph 1: your RAG pipeline as a StateGraph; D21 LangGraph 2: conditional routing + self-correction (corrective RAG); D22 LangGraph 3: tools, human-in-the-loop interrupt, Postgres checkpointer; D23 Multi-document comparison: fan-out with Send (map-reduce) | G8: L11 LLM routing, fallback, retries, timeouts, circuit breakers; L12 Chunking strategies and query transformation; L13 LangGraph core: state, nodes, edges, reducers, checkpointers; L14 Agentic patterns: ReAct, tool calling, HITL, self-correction, multi-agent | H8: LAB03 Idempotency keys | I8: 8 applications + 3 referral messages. Log every interview question you get in the Interview Log. | J8: 8 | K8: =COUNTIF('Daily Plan'!$D$2:$D$209,A8) | L8: =COUNTIFS('Daily Plan'!$D$2:$D$209,A8,'Daily Plan'!$A$2:$A$209,"☑") | M8: =IF(K8=0,0,L8/K8)
A9: 5 | B9: 46356 | C9: 46362 | D9: 1: DocuLens: RAG platform + document workflow automation | E9: Auth + tenancy, CI, Azure deploy, observability, load test, v1.0 release. GATE 1: deployed project, full applying. | F9: D24 Auth, workspaces and RBAC (tenant isolation); D25 Production Dockerfiles + GitHub Actions CI; D26 Azure foundation (budget first); D27 Deploy API + worker to Azure Container Apps; D28 Observability, rate limiting and a load test; D29 Release v1: README, design doc, demo, resume bullets | G9: L15 Authentication, authorization, JWT, OAuth2/OIDC, RBAC, multi-tenancy; L16 Docker in depth + CI/CD with GitHub Actions; L17 Cloud fundamentals: Azure services and their AWS equivalents; L18 Observability: logs, metrics, traces, OpenTelemetry, LLM tracing | H9: LAB04 Offset vs cursor pagination | I9: 10 applications + 5 referral asks. Resume v2 with the deployed link and eval numbers (GATE 1). | J9: 10 | K9: =COUNTIF('Daily Plan'!$D$2:$D$209,A9) | L9: =COUNTIFS('Daily Plan'!$D$2:$D$209,A9,'Daily Plan'!$A$2:$A$209,"☑") | M9: =IF(K9=0,0,L9/K9)
A10: 6 | B10: 46363 | C10: 46369 | D10: 1: DocuLens: RAG platform + document workflow automation | E10: DocuLens v1.5 workflows: claim intake (classify, extract, validate), durable workflow engine, policy-grounded decision + review queue, text-to-SQL analytics, outbox + signed webhooks, workflow eval and redeploy. | F10: D31 Intake: document classification + per-type extraction with field confidence; D32 Workflow engine: definitions, runs and durable steps; D33 Decision step: policy-grounded coverage check + human review queue with SLAs; D34 Analytics agent: text-to-SQL over workflow data with guardrails; D35 Actions: outbox, signed webhooks, notifications and audit trail; D36 Workflow eval, ops dashboard and release v1.5 | G10: L71 Intelligent document processing: classify, extract, validate, route; L72 Durable workflows and orchestration engines (LangGraph, Celery, Temporal, Step Functions); L74 Integrations and side effects: webhooks, outbox, retries, audit; L73 Text-to-SQL agents and safe data access | H10: LAB05 Resilient HTTP client | I10: 15 applications + 5 referral asks; follow up on last week's; update Interview Log. | J10: 15 | K10: =COUNTIF('Daily Plan'!$D$2:$D$209,A10) | L10: =COUNTIFS('Daily Plan'!$D$2:$D$209,A10,'Daily Plan'!$A$2:$A$209,"☑") | M10: =IF(K10=0,0,L10/K10)
A11: 7 | B11: 46370 | C11: 46376 | D11: 2: AI SRE Copilot v1: multi-agent incident diagnosis with human-approved remediation | E11: DocuLens MCP server (search + workflow tools); SRE lab: kind cluster, victim app, fault scripts, alerts, incident store. | F11: D30 MCP server for DocuLens; S01 SRE repo + local Kubernetes (kind) + kubectl drills; S02 Victim app: gateway -> api -> Postgres on the cluster; S03 Fault knobs + one-command fault scripts with undo; S04 Prometheus + Alertmanager -> webhook, alert fixtures; S05 alert-receiver + incident store (event-style records) | G11: L19 Model Context Protocol (MCP); L20 Kubernetes core objects; L21 Debugging containers and Kubernetes in practice; L22 Prometheus, PromQL and alerting | H11: LAB06 asyncio worker pool + backpressure | I11: 15 applications + 5 referral asks; follow up on last week's; update Interview Log. | J11: 15 | K11: =COUNTIF('Daily Plan'!$D$2:$D$209,A11) | L11: =COUNTIFS('Daily Plan'!$D$2:$D$209,A11,'Daily Plan'!$A$2:$A$209,"☑") | M11: =IF(K11=0,0,L11/K11)
A12: 8 | B12: 46377 | C12: 46383 | D12: 2: AI SRE Copilot v1: multi-agent incident diagnosis with human-approved remediation | E12: Read-only tools incl. change correlation, SRE MCP server, diagnosis agent with citations, multi-agent supervisor, 60-second slice. | F12: S06 Read-only Kubernetes tools + tool registry; S07 Metrics tool, evidence caps and truncation; S08 SRE MCP server (read-only tools); S09 Diagnosis agent v1 with cited hypotheses; S10 Multi-agent supervisor: triage -> evidence -> diagnosis -> policy; S11 Incident UI + 60-second slice | G12: L23 Redis in depth; L24 Caching patterns (including LLM caching); L25 Rate limiting algorithms; L26 Designing multi-agent systems | H12: LAB07 Lost update | I12: 15 applications + 5 referral asks; follow up on last week's; update Interview Log. | J12: 15 | K12: =COUNTIF('Daily Plan'!$D$2:$D$209,A12) | L12: =COUNTIFS('Daily Plan'!$D$2:$D$209,A12,'Daily Plan'!$A$2:$A$209,"☑") | M12: =IF(K12=0,0,L12/K12)
A13: 9 | B13: 46384 | C13: 46390 | D13: 2: AI SRE Copilot v1: multi-agent incident diagnosis with human-approved remediation | E13: Frozen scenarios, eval harness, baseline + fixes, calibrated judge, abstention and budgets. | F13: S12 Scenario corpus F1-F8 + runner; S13 Eval harness for the agent; S14 Baseline eval run (8 scenarios x 3); S15 Failure analysis + fixes (prompts and tools only); S16 Langfuse traces + LLM-as-judge (calibrated); S17 Abstention + budgets | G13: L27 PostgreSQL indexes and query plans; L28 Transactions, isolation levels, MVCC and locking; L29 Evaluating agents and LLM apps in production; L30 Cost and latency optimisation for LLM applications | H13: LAB08 Outbox with Redis Streams | I13: 15 applications + 5 referral asks; follow up on last week's; update Interview Log. | J13: 15 | K13: =COUNTIF('Daily Plan'!$D$2:$D$209,A13) | L13: =COUNTIFS('Daily Plan'!$D$2:$D$209,A13,'Daily Plan'!$A$2:$A$209,"☑") | M13: =IF(K13=0,0,L13/K13)
A14: 10 | B14: 46391 | C14: 46397 | D14: 2: AI SRE Copilot v1: multi-agent incident diagnosis with human-approved remediation | E14: Executor with RBAC, remediation state machine, human approval, verify + rollback, crash and safety drills. | F14: S18 Remediation executor + write RBAC (allow-list); S19 Remediation as an explicit state machine in Postgres; S20 Human approval via LangGraph interrupt; S21 Verify + rollback; S22 Idempotency + crash safety drill; S23 Safety test suite + compensation x10 | G14: L31 REST API design; L32 State machines, sagas and compensation; L33 Guardrails and security for LLM applications; L34 Kubernetes RBAC, ServiceAccounts and least privilege | H14: LAB09 Fan-out/fan-in aggregator | I14: 15 applications + 5 referral asks; follow up on last week's; update Interview Log. | J14: 15 | K14: =COUNTIF('Daily Plan'!$D$2:$D$209,A14) | L14: =COUNTIFS('Daily Plan'!$D$2:$D$209,A14,'Daily Plan'!$A$2:$A$209,"☑") | M14: =IF(K14=0,0,L14/K14)
A15: 11 | B15: 46398 | C15: 46404 | D15: 2: AI SRE Copilot v1: multi-agent incident diagnosis with human-approved remediation | E15: Postmortem writer + similar-incident memory + incident stats (text-to-SQL), end-to-end scenarios, CI, docs, demo. GATE 2: two finished projects. | F15: S24 Postmortem writer with linked claims; S25 End-to-end remediation scenarios + action-correctness eval; S26 CI for the SRE project; S27 README, architecture, ADRs; S28 Demo video + resume v2; S29 Stage 2 buffer | G15: L35 Distributed systems fundamentals; L36 Message queues vs event streams: RabbitMQ, Kafka, SQS; L37 Outbox, inbox, DLQ and poison messages; L38 System design: a RAG platform for 10,000 users | H15: LAB10 SSE/WebSocket fan-out | I15: 15 applications + 5 referral asks; follow up on last week's; update Interview Log. | J15: 15 | K15: =COUNTIF('Daily Plan'!$D$2:$D$209,A15) | L15: =COUNTIFS('Daily Plan'!$D$2:$D$209,A15,'Daily Plan'!$A$2:$A$209,"☑") | M15: =IF(K15=0,0,L15/K15)
A16: 12 | B16: 46405 | C16: 46411 | D16: 3: PDF Translator (your PRD): layout-preserving translation + shared AI gateway | E16: PDF Translator core: app in the monorepo, regions, batched translation, overlay renderer, fit engine, async jobs, previews. | F16: T01 Translator app + paragraph regions; T02 Region translation through the router (structured, batched); T03 Overlay renderer v1 (redact + insert); T04 Fit engine: wrap, shrink-to-fit, fit_status; T05 Async translation job with per-page progress; T06 Previews + secure download | G16: L39 PDF internals and document parsing; L40 Ingestion pipeline design at scale; L41 Vector databases compared; L42 Prompt injection through documents and data governance | H16: LAB11 Consistent hashing | I16: GATE 2: resume v3 with both projects. 15 applications aimed at AI-agent / LLM-engineer roles + 5 referral asks. | J16: 15 | K16: =COUNTIF('Daily Plan'!$D$2:$D$209,A16) | L16: =COUNTIFS('Daily Plan'!$D$2:$D$209,A16,'Daily Plan'!$A$2:$A$209,"☑") | M16: =IF(K16=0,0,L16/K16)
... A34: 30 | B34: 46531 | C34: 46537 | D34: 6: Advanced and nice-to-haves (keep flexible) | E34: Portfolio frozen and retrospective committed. | F34: Portfolio freeze and retrospective: Final README passes for both repos; Security pass (dependency + secrets scan) and refreshed architecture diagrams for all three projects; Two blog posts published (eval story, agent safety story); Resume and LinkedIn final; Retrospective: what worked, what to learn next (Go? distributed systems? deeper ML?); Plan the next quarter | G34: L69 SQL interview patterns + revisit / interview-log / design drills | H34: LAB29 Explain three labs | I34: 15 applications + 5 referral asks until you have an offer you accept; then switch to maintenance (see roadmap section 9). | J34: 15 | K34: =COUNTIF('Daily Plan'!$D$2:$D$209,A34) | L34: =COUNTIFS('Daily Plan'!$D$2:$D$209,A34,'Daily Plan'!$A$2:$A$209,"☑") | M34: =IF(K34=0,0,L34/K34)

Sheet Stages & Gates
A1: Stages, exit checks and gates
A4: Stage | B4: Name | C4: Start | D4: End | E4: Weeks | F4: Goal | G4: Exit check (stage is done when)
A5: 1 | B5: DocuLens: RAG platform + document workflow automation | C5: 46330 | D5: 46369 | E5: W1-W6 | F5: Weeks 1-5: a deployed, evaluated RAG platform (ingestion with OCR/metadata/dedup, hybrid search + rerank, LangGraph agent with tools and human review, eval, Azure). Week 6: claim-intake workflows on top (classify -> extract -> validate -> policy check with citations -> human review -> webhooks), text-to-SQL analytics, workflow eval. | G5: v1.0 (W5): public URL passes the smoke test, retrieval + generation eval tables, demo. v1.5 (W6): workflow eval with STP rate, field accuracy and 0 false auto-approvals; text-to-SQL eval; demo part 2; resume bullets with real numbers.
A6: 2 | B6: AI SRE Copilot v1: multi-agent incident diagnosis with human-approved remediation | C6: 46370 | D6: 46404 | E6: W7-W11 | F6: Kill a pod -> cited diagnosis in about 60 s (with change correlation); human approves; executor fixes, verifies, rolls back on failure; frozen 8-scenario eval; MCP tools; similar-incident memory. | G6: Eval v3 with cause and action correctness; safety tests + compensation 10/10; crash drill; v1.0 tag; demo video.
A7: 3 | B7: PDF Translator (your PRD): layout-preserving translation + shared AI gateway | C7: 46405 | D7: 46432 | E7: W12-W15 | F7: Your PRD phases 1-8: translate a PDF keeping layout, glossary/translation-memory RAG, LangGraph review workflow, OCR, tables, one Indic script, visual QA, events/webhooks, traces and dashboard. Built as its own app reusing DocuLens's packages; the AI gateway is extracted for all three projects. | G7: PDF Translator v1.0 tag with support matrix, translation eval and demo; all three projects call the gateway.
A8: 4 | B8: Backend depth: event-driven SRE (Kafka, outbox, DLQ, event sourcing, CQRS, OTel) | C8: 46433 | D8: 46467 | E8: W16-W20 | F8: Same SRE flow through Kafka with idempotent consumers, outbox and DLQ, event-sourced incident state, circuit breaker, end-to-end traces. | G8: Drills documented: kill-consumer, replay, relay crash, poison message, rebuild projections; one trace alert -> verified remediation.
A9: 5 | B9: AWS: Terraform, EKS, Bedrock, serverless | C9: 46468 | D9: 46502 | E9: W21-W25 | F9: SRE platform on EKS via Terraform + Helm; Bedrock route in the gateway; one Lambda + SQS path; GitHub OIDC deploys. | G9: F1-F8 eval rerun on EKS, environment destroyed, cost report written.
A10: 6 | B10: Advanced and nice-to-haves (keep flexible) | C10: 46503 | D10: 46537 | E10: W26-W30 | F10: GraphRAG, fine-tuning a small model with MLflow, framework comparison + A2A agent, portfolio freeze. | G10: Each experiment has an eval-backed keep/drop decision; portfolio frozen with a retrospective.
A13: Gate | B13: Date | C13: What changes
A14: Gate 0 | B14: 46348 | C14: Resume v1, LinkedIn, GitHub ready (DocuLens with hybrid search and first eval table). First 3 applications; 8/week next week. Interviews are practice and market information.
A15: Gate 1 | B15: 46362 | C15: DocuLens v1 deployed on Azure with eval report and demo. Resume v2. 10-15 applications/week + 5 referral asks.
A16: DocuLens v1.5 | B16: 46369 | C16: Workflow automation released: claim intake, review queue, webhooks, text-to-SQL, workflow eval. Resume bullets updated.
A17: Gate 2 | B17: 46404 | C17: AI SRE Copilot v1 finished. Resume v3 with two projects. Aim at AI-agent / LLM-engineer roles.
A18: PDF Translator v1.0 | B18: 46432 | C18: Your PRD built (phases 1-8) + shared AI gateway. Resume v4 with three projects.
A19: AI-102 exam | B19: 46438 | C19: Azure AI Engineer Associate (company-paid). Check the current exam code on Microsoft Learn before booking.
A20: Offer rule | C20: Take the first offer that clears your pay bar AND has real engineering substance. Then drop to maintenance mode (roadmap section 9).

Sheet Project Cards
A1: Project cards (tutor-style lessons)
A2: Weeks 16-30 are weekly task lists on the Weekly Plan sheet.
A4: Card | B4: Planned | C4: Project | D4: Title | E4: Why it matters (interview angle) | F4: Learn first | G4: Steps | H4: Done when | I4: Stretch | J4: Done
A5: D01 | B5: 46330 | C5: DocuLens | D5: Dev setup + repo + hello FastAPI | E5: Every interview starts with 'how is your project structured and tooled?'. uv, ruff, pytest and a clean layout are what a 3-YOE Python dev is expected to use without thinking. | F5: uv docs (docs.astral.sh/uv) 'Projects' page; FastAPI tutorial 'First Steps' and 'Testing' (fastapi.tiangolo.com); WSL2 + Docker Desktop install guide (learn.microsoft.com/windows/wsl). | G5: 1. Install WSL2 (Ubuntu), Docker Desktop with WSL integration, VS Code + WSL extension, git, uv. Work inside WSL from now on (Celery, Tesseract and k8s tooling behave better there). 2. uv init doculens; add fastapi, uvicorn[standard], pydantic-settings; dev deps: pytest, pytest-asyncio, httpx, ruff, mypy, pre-commit. 3. Layout: app/main.py (app factory), app/api/routes/health.py, app/core/config.py, tests/, docs/decisions/, docs/LOG.md. 4. GET /health returns {"status":"ok","version":...}. Write one test with httpx.AsyncClient + ASGITransport. 5. Makefile (run from WSL): make dev, make test, make lint. Add pre-commit with ruff + ruff-format. 6. Create GitHub repo, push, write a 5-line README (what it will be). | H5: `make test` is green, `make lint` is clean, repo is on GitHub, and `docker run hello-world` works inside WSL. | I5: Add a GitHub Actions workflow that runs `make lint test` (you will formalise CI in D25). | J5: ☐
A6: D02 | B6: 46331 | C6: DocuLens | D6: Docker Compose: Postgres + pgvector + Redis, settings, readiness | E6: Interviewers ask how you run dependencies locally and how your service knows it is ready. This is the backbone every later card plugs into. | F6: pgvector README (github.com/pgvector/pgvector) 'Docker' + 'Getting started'; SQLAlchemy 2.0 'Asynchronous I/O' page; pydantic-settings docs. | G6: 1. docker-compose.yml: pgvector/pgvector:pg16 (volume, healthcheck pg_isready) and redis:7 (healthcheck redis-cli ping). 2. app/core/config.py: Settings(BaseSettings) with DATABASE_URL, REDIS_URL, ENV; .env.example committed, .env ignored. 3. app/db/session.py: async engine (asyncpg) + async_sessionmaker; FastAPI dependency get_session(). 4. GET /health/ready: runs SELECT 1 and Redis PING concurrently with asyncio.gather and a 1 s timeout each; returns per-dependency status and 503 if any fails. 5. Test: ready endpoint returns 200 with compose up; unit test with a failing fake returns 503. | H6: `docker compose up -d` then `curl /health/ready` returns {"db":"ok","redis":"ok"}; stopping Redis makes it return 503. | I6: Write docs/decisions/0001-one-database.md: why Postgres+pgvector instead of a separate vector DB for v1. | J6: ☐
A7: D03 | B7: 46332 | C7: DocuLens | D7: Alembic + data model v1 | E7: Schema design and migrations come up in every backend round ('how do you change a schema without downtime?'). | F7: Alembic tutorial (alembic.sqlalchemy.org) 'Auto Generating Migrations'; pgvector 'Storing' section. | G7: 1. alembic init -t async migrations; point env.py at your Base metadata and settings. 2. Models: documents(id uuid pk, workspace_id uuid null, filename, sha256 unique-per-workspace, status, page_count, metadata jsonb, created_at). 3. chunks(id uuid, document_id fk, page int, bbox jsonb, section text, text text, token_count int, content_hash text, embedding vector(384), metadata jsonb). 4. First migration runs CREATE EXTENSION IF NOT EXISTS vector; autogenerate the rest and READ the generated file before applying. 5. Test: upgrade head on an empty DB, insert one document + chunk, downgrade base. | H7: `alembic upgrade head` and `alembic downgrade base` both succeed on a clean database and the round-trip test passes. | J7: ☐
A8: D04 | B8: 46333 | C8: DocuLens | D8: Upload + PyMuPDF extraction with coordinates | E8: This is the root of both the RAG pipeline and the translator. Coordinates (bbox) are what make your project different from 'chat with PDF' tutorials: later, citations can highlight the exact region on the page. | F8: PyMuPDF docs 'Text extraction' + 'Appendix 1: Details on Text Extraction' (page.get_text('dict')); FastAPI 'Request Files'. | G8: 1. POST /documents (multipart): check magic bytes %PDF-, size cap (e.g. 25 MB), page cap; compute sha256 while reading. 2. If the same sha256 already exists in the workspace, return the existing document (200) instead of creating a duplicate (idempotent upload). Document the 200 vs 409 choice. 3. Save the file under ./storage/{document_id}.pdf behind a Storage interface (LocalStorage now, Blob later). 4. extract_blocks(path) -> list[Block(page, bbox, text, font_size, is_bold)] using page.get_text('dict'); skip empty/whitespace spans. 5. Pick a corpus: 5-8 public insurance policy wordings (recommended: in week 6 your claim workflow checks claims against these same policies) or pharma drug labels, + 1 scanned PDF. Put 2 small ones in tests/fixtures/. 6. Tests: block count > 0 for the fixture; every bbox has 4 floats inside the page rect; second upload returns the same id. | H8: Uploading the same PDF twice returns the same document_id, and the extraction test proves every block has a page number and a valid bbox. | I8: Print the 10 largest-font blocks of a document: those are your heading candidates for D05. | J8: ☐
A9: D05 | B9: 46334 | C9: DocuLens | D9: Chunking strategies v1 (layout-aware) | E9: 'How did you chunk and why?' is the single most common RAG interview question. You will answer it with numbers in W3; today you build the candidates. | F9: Pinecone 'Chunking Strategies for LLM Applications' article; LangChain RecursiveCharacterTextSplitter docs (concept only); tiktoken README. | G9: 1. Chunker A, fixed: 400 tokens, 60 overlap (tiktoken cl100k as the counter). 2. Chunker B, recursive: split on paragraph -> sentence -> word to stay under 400 tokens. 3. Chunker C, layout-aware: walk blocks in reading order; a block whose font size is above the page median (or bold + short) starts a new section; never merge across sections; keep the heading path ('3 Exclusions > 3.2 Pre-existing') in chunk.section. 4. Every chunk keeps page, union bbox of its blocks, token_count and content_hash (sha256 of normalised text). 5. scripts/chunk_stats.py prints count / mean / p95 tokens per strategy for the corpus. | H9: Unit tests pass for all three chunkers, chunk_stats prints a table for your corpus, and docs/decisions/0002-chunking.md states your provisional pick (to be confirmed by eval in D16). | J9: ☐
A10: D06 | B10: 46335 | C10: DocuLens | D10: Embeddings + dense search on pgvector (HNSW) | E10: Vector search fundamentals: embedding model choice, dimensions, distance metric and ANN index. Expect 'HNSW vs IVFFlat' and 'why cosine'. | F10: pgvector README sections 'Querying', 'HNSW', 'Filtering'; fastembed README (qdrant/fastembed); MTEB leaderboard (concept: how models are compared). | G10: 1. EmbeddingProvider protocol: embed_documents(list[str]) / embed_query(str). Implement FastEmbedProvider (BAAI/bge-small-en-v1.5, 384-d, runs on CPU, free) and FakeEmbedder for tests. 2. Pipeline step: embed chunks in batches of 64; store vectors. 3. Migration: HNSW index USING hnsw (embedding vector_cosine_ops). 4. POST /search {query, k, mode:'dense'} -> chunks with score, page, section, document filename. 5. Run EXPLAIN on the search query and confirm the index is used (set enable_seqscan=off only to test). | H10: A natural question ('what is not covered?') returns sensible top-5 chunks with page numbers, and EXPLAIN shows the HNSW index scan. | I10: Try ef_search 40 vs 200 on 10 queries and note latency vs result changes. | J10: ☐
A11: D07 | B11: 46336 | C11: DocuLens | D11: Lexical leg: Postgres full-text search | E11: Dense search misses exact identifiers (clause numbers, drug names, error codes). Knowing why is what separates RAG builders from tutorial followers. | F11: PostgreSQL docs chapter 12 'Full Text Search' (12.1-12.3, websearch_to_tsquery, ts_rank_cd); 'BM25' explanation (Elastic blog 'Practical BM25'). | G11: 1. Migration: generated column tsv tsvector GENERATED ALWAYS AS (to_tsvector('english', coalesce(section,'') || ' ' || text)) STORED + GIN index. 2. mode='lexical': websearch_to_tsquery + ts_rank_cd ordering, same response shape as dense. 3. Find 3 queries where lexical beats dense (exact clause id, rare term, acronym) and 3 where dense beats lexical (paraphrase). Write them in docs/notes/retrieval-examples.md - these are interview examples. 4. Note honestly: ts_rank_cd is not true BM25 (no IDF saturation tuning); record that as a known limit. | H11: docs/notes/retrieval-examples.md lists at least 3 queries where lexical finds the right chunk and dense does not, and 3 the other way round. | I11: Add bm25s (pip) over the same chunks and compare top-5 for your 6 example queries. | J11: ☐
A12: D08 | B12: 46337 | C12: DocuLens | D12: Hybrid retrieval with Reciprocal Rank Fusion + metadata filters | E12: Hybrid search (dense + BM25) is named in most RAG job posts. RRF is the simplest robust fusion; you must be able to explain why rank fusion beats adding raw scores. | F12: Paper/summary: 'Reciprocal Rank Fusion outperforms Condorcet...' (Cormack et al. 2009) - read the abstract and formula only; pgvector 'Hybrid search' section. | G12: 1. Run dense and lexical legs concurrently (asyncio.gather), each returning top 30. 2. rrf(lists, k=60): score = sum(1/(k + rank)). Pure function + unit test with hand-made rankings. 3. Metadata filters applied INSIDE both legs (document_ids, doc_type, page range) - pre-filtering, not post-filtering. 4. mode='hybrid' is the default; debug=true returns each chunk's dense rank, lexical rank and fused score. | H12: RRF unit test passes, and /search?debug=true shows per-leg ranks and the fused order for any query. | I12: Add a weight per leg (weighted RRF) behind a setting; you'll tune it with eval data in W3. | J12: ☐
A13: D09 | B13: 46338 | C13: DocuLens | D13: Reranking with a cross-encoder | E13: Retrieve wide, rerank narrow. Interviewers probe the latency/quality trade-off of rerankers and why a cross-encoder is more accurate than the bi-encoder used for retrieval. | F13: sbert.net 'Cross-Encoders' + 'Retrieve & Re-Rank' pages; BAAI/bge-reranker-base model card. | G13: 1. Reranker protocol + CrossEncoderReranker (sentence-transformers, BAAI/bge-reranker-base) + NoopReranker. 2. Rerank the fused top-30 down to top-5. Model call is CPU-bound: run it with run_in_threadpool / anyio.to_thread so the event loop is not blocked. 3. Load the model once at startup (lifespan), not per request. 4. Log rerank latency; scripts/bench_rerank.py prints p50/p95 for 20 queries. 5. Setting RERANK_ENABLED to switch it off (you will compare in eval). | H13: debug output shows the order before and after reranking, and bench_rerank prints p50/p95 latency for 20 queries. | I13: Try top-20 vs top-50 candidates and note the latency change. | J13: ☐
A14: D10 | B14: 46340 | C14: DocuLens | D14: LLM layer: providers, structured output, grounded answers with citations | E14: Structured outputs, provider abstraction and citation validation are explicitly listed in AI-engineer job posts. This is the core of 'LLM integration done properly'. | F14: OpenAI docs 'Structured Outputs'; Anthropic docs 'Tool use' (for JSON via tools) and 'Increase output consistency'; Gemini 'OpenAI compatibility' page. | G14: 1. LLMProvider protocol: complete(messages, model, max_tokens, temperature, response_schema=None) -> LLMResult(text|parsed, usage, latency_ms, model, provider). 2. Adapters: OpenAICompatibleProvider (works for OpenAI and Gemini via base_url) and AnthropicProvider. FakeProvider for tests. Use the cheapest current model of each. 3. generate_structured(schema): ask for JSON matching the Pydantic schema; on ValidationError re-ask once with the error message; then fail with a typed error. 4. Answer schema: {answer: str, citations: list[chunk_id], confidence: float 0-1, unanswerable: bool}. 5. POST /ask: hybrid retrieve -> rerank -> prompt with numbered chunks -> structured answer -> reject citations that are not in the retrieved set. 6. Prompt says: answer only from the context, cite chunk ids, set unanswerable=true if the context does not contain the answer. | H14: /ask answers a corpus question with valid citation ids (each maps to a page), an out-of-corpus question returns unanswerable=true, and a test proves invented citation ids are rejected. | I14: Return the bbox of each cited chunk so a UI could highlight it on the page. | J14: ☐
A15: D11 | B15: 46341 | C15: DocuLens | D15: Streaming answers over SSE + conversation memory | E15: Streaming (SSE) is a listed 'good to have'. Interviewers ask SSE vs WebSockets and how you stream while still returning structured citations. | F15: MDN 'Using server-sent events'; FastAPI 'StreamingResponse' (or sse-starlette README); OpenAI/Anthropic streaming docs. | G15: 1. POST /ask/stream returns text/event-stream: event 'token' for answer tokens, then one final event 'citations' with JSON, then 'done'. 2. Implement stream() on both providers (async generator). 3. Conversation: conversations + messages tables; /ask accepts conversation_id; last 6 turns are condensed into a standalone question before retrieval (LLM 'condense' step). 4. Handle client disconnect (request.is_disconnected) so you stop paying for tokens nobody reads. 5. Test the stream with httpx streaming client; manual test with curl -N. | H15: curl -N shows tokens arriving incrementally and a final citations event; a follow-up question ('and what about dental?') is rewritten into a standalone query that retrieves the right chunks. | J15: ☐
A16: D12 | B16: 46342 | C16: DocuLens | D16: Async ingestion with Celery + Redis (202 + job status) | E16: 'Async task processing' appears in almost every backend+AI post. Heavy work (OCR, embeddings) must not run inside the HTTP request. | F16: Celery 'First steps with Celery' + 'Tasks' (acks_late, retries); FastAPI 'Background Tasks' page (to explain why you did NOT use it). | G16: 1. celery_app.py with Redis broker/result backend; worker service in docker-compose using the same image. 2. jobs table: id, document_id, stage (queued|extracting|chunking|embedding|ready|failed), progress, error, attempts, timestamps. 3. POST /documents now stores the file, creates job, enqueues ingest_document(document_id) and returns 202 {job_id}. 4. Celery chain: extract -> chunk -> embed, each updating the job stage. 5. GET /jobs/{id} returns stage/progress/error. 6. docs/decisions/0003-celery.md: Celery vs FastAPI BackgroundTasks vs arq (why a real broker). | H16: Uploading a 50-page PDF returns 202 in under 300 ms and GET /jobs/{id} moves queued -> extracting -> chunking -> embedding -> ready. | J16: ☐
A17: D13 | B17: 46343 | C17: DocuLens | D17: Retries, idempotent tasks and chunk-level de-duplication | E17: Ingestion pipelines in job posts mention 'deduplication'. At-least-once delivery means every task can run twice: you must make that harmless. | F17: Celery 'Retrying' + 'acks_late' notes; datasketch MinHash/LSH README; article on SimHash (optional). | G17: 1. Retries: autoretry_for transient errors (timeouts, 429, connection) with retry_backoff + jitter, max 5; permanent errors (corrupt PDF) fail fast with a clear job error. 2. Idempotency: each stage checks whether its output already exists; UNIQUE(document_id, content_hash, page) prevents duplicate chunks. 3. Exact dedup: normalised text hash. Near-dup: MinHash (datasketch) with Jaccard >= 0.9 marks repeated headers/footers/boilerplate as is_boilerplate=true and excludes them from search. 4. Kill the worker mid-embedding (docker kill), restart, verify the job completes without duplicates. | H17: Re-running ingest for the same document does not change the chunk count, the kill-worker test completes the job with no duplicates, and the job report shows how many boilerplate chunks were removed. | J17: ☐
A18: D14 | B18: 46344 | C18: DocuLens | D18: Metadata extraction with structured outputs + filtered search | E18: 'OCR, metadata extraction and deduplication' is a literal line in the RAG job post you pasted. Metadata turns 'search everything' into precise filtered retrieval. | F18: Instructor library README (concept of retries on validation) - you already built the equivalent; Pydantic 'Field' + 'Literal' docs. | G18: 1. DocMetadata schema: title, doc_type (Literal of 4-5 values), issuer, product_names list, effective_date (date|None), language. 2. Celery stage 'extract_metadata': first 3 pages -> cheap model -> DocMetadata; regex fallback for dates if the model fails. 3. Store in documents.metadata and copy doc_type/issuer into chunk metadata for filtering. 4. /search and /ask accept filters {doc_type, issuer}. 5. Add a 'route by metadata' rule: if the question names an issuer/product, filter automatically (simple keyword match against known products). | H18: Every corpus document has extracted metadata you have checked by eye, and a filtered query only returns chunks from matching documents. | J18: ☐
A19: D15 | B19: 46345 | C19: DocuLens | D19: Golden evaluation dataset (frozen) | E19: 'Understanding of how to measure LLM output quality, not just build it' - this card is where that starts. Without a golden set, every claim about quality is an anecdote. | F19: RAGAS docs 'Testset' concepts; Hamel Husain's blog posts on evals ('Your AI product needs evals'). | G19: 1. Write 30 questions over your corpus: 10 single-fact lookups, 6 exact-term/clause questions, 8 multi-hop or compare-two-documents, 6 unanswerable (not in corpus). 2. For each: reference answer (1-2 lines), expected document + page(s), type tag. 3. Store as eval/golden_v1.jsonl and a loader with Pydantic validation. 4. Freeze it: git tag eval-v1. Rule from your old plan stays: never edit labels to make a run pass. 5. Optional: generate 20 extra synthetic questions with an LLM, but keep them in a separate file and label them synthetic. | H19: eval/golden_v1.jsonl has 30 validated rows with expected pages and types, and the tag eval-v1 exists. | J19: ☐
A20: D16 | B20: 46347 | C20: DocuLens | D20: Retrieval evaluation harness: numbers for your design choices | E20: This produces the table you will show in every interview: 'hybrid + rerank improved recall@5 from X to Y'. | F20: Recall@k, MRR, nDCG definitions (any IR textbook or Pinecone 'Evaluation Measures in IR'). | G20: 1. eval/retrieval.py: for each golden question run a retrieval config, mark a hit when an expected page/chunk is in top-k. 2. Metrics: recall@5, recall@10, MRR, and context precision (fraction of retrieved chunks that are relevant, using page match). 3. Configs: dense / lexical / hybrid / hybrid+rerank x chunkers A/B/C (at least 6 runs). 4. Write docs/eval/retrieval_v1.md: table + 3-sentence conclusion + chosen default. Update decision 0002-chunking.md with the evidence. 5. Exclude unanswerable questions from recall, but report them separately. | H20: docs/eval/retrieval_v1.md has a table of at least 6 configs x 3 metrics and you can state, from memory, which config won and by how much. | J20: ☐
A21: D17 | B21: 46348 | C21: DocuLens | D21: Generation eval (RAGAS or DeepEval) + Langfuse tracing | E21: Evaluation frameworks and LLM tracing are named in the job posts (DeepEval, RAGAs, Langfuse). After today you have used all three concepts for real. | F21: Langfuse docs 'Get started' (self-host with docker compose or free cloud) + Python decorator @observe; RAGAS metrics page (faithfulness, answer_relevancy, context_precision, context_recall) or DeepEval 'Getting started'. | G21: 1. Instrument /ask with Langfuse: one trace per request, spans for condense, retrieve, rerank, generate; record model, tokens, cost, prompt version. 2. eval/generation.py: run the golden set through /ask, score faithfulness, answer relevancy, context precision/recall with RAGAS (or DeepEval); also exact checks: unanswerable questions must return unanswerable=true. 3. Push scores to Langfuse as scores on each trace. 4. docs/eval/generation_v1.md: table + 3 worst answers with a one-line diagnosis each (retrieval miss vs generation error). | H21: One full eval run is visible in Langfuse with per-trace scores, and generation_v1.md lists metrics plus the 3 worst failures with a diagnosis. | I21: Use a different (cheaper) judge model than the answer model and note why. | J21: ☐
A22: D18 | B22: 46349 | C22: DocuLens | D22: Model router: capability routing, fallback, usage ledger | E22: 'Model routing and fallback across providers (Claude, OpenAI, Gemini)' is a literal job requirement. Routing should be based on task needs, not random model names. | F22: Your own LLM layer from D10; AWS Builders Library 'Timeouts, retries and backoff with jitter' (read it - it is also a backend interview classic). | G22: 1. models.yaml: capabilities (extract_metadata, condense, answer, judge) -> ordered list of provider/model with max_tokens and timeout. 2. Router.complete(capability, ...): try primary; on timeout/429/5xx retry once with jittered backoff, then fall back to the next provider. Never fall back on a schema-validation failure that survived the re-ask (that is a prompt bug, not an outage). 3. usage_ledger table: request_id, capability, provider, model, input/output tokens, cost estimate, latency, status (ok|retried|fallback|failed). 4. GET /usage?from&to aggregates cost and calls per capability/model. 5. Test: FakeProvider that returns 429 forces a fallback; ledger shows both attempts. | H22: The forced-429 test shows primary -> fallback in the ledger, and GET /usage returns cost per capability for your eval run. | I22: Add a simple circuit breaker per provider (open after 5 failures in 60 s). | J22: ☐
A23: D19 | B23: 46350 | C23: DocuLens | D23: Query transformation: rewrite, multi-query, HyDE | E23: 'Query transformation' is listed next to hybrid retrieval and reranking in the RAG post. Only keep a technique if the eval says it helps. | F23: LangChain 'MultiQueryRetriever' concept page; HyDE paper abstract (Gao et al. 2022); 'step-back prompting' summary. | G23: 1. Multi-query: LLM writes 3 paraphrases; retrieve for each; fuse with RRF. 2. HyDE: LLM writes a hypothetical answer; embed it for the dense leg only. 3. Decomposition for compare questions: split 'A vs B' into two sub-queries. 4. Feature flags per technique; run the retrieval eval on golden_v1 for each. 5. Add rows to retrieval_v1.md and record keep/drop decisions with the cost (extra LLM calls, latency). | H23: The retrieval table has rows for multi-query and HyDE with recall@5 and added latency, and each has a written keep/drop decision. | J23: ☐
A24: D20 | B24: 46351 | C24: DocuLens | D24: LangGraph 1: your RAG pipeline as a StateGraph | E24: LangGraph is named in nearly every agentic job post. Start by expressing what you already have as a graph so the new concepts (state, nodes, edges) map onto known code. | F24: LangGraph docs (docs.langchain.com, LangGraph section): 'Quickstart', 'Graph API' (state, reducers, nodes, edges). | G24: 1. RAGState TypedDict: question, conversation_id, filters, standalone_question, candidates, context, answer, citations, confidence, steps (Annotated list with operator.add reducer). 2. Nodes: condense -> retrieve -> rerank -> generate. Each node is a small pure-ish function calling your existing services. 3. Compile; expose POST /agent/ask that invokes the graph. 4. Export the Mermaid diagram (graph.get_graph().draw_mermaid()) into README. 5. Unit test the graph with FakeProvider and FakeEmbedder. | H24: /agent/ask returns the same quality answer as /ask (spot check 5 golden questions), and the Mermaid diagram is in the README. | J24: ☐
A25: D21 | B25: 46352 | C25: DocuLens | D25: LangGraph 2: conditional routing + self-correction (corrective RAG) | E25: 'Conditional routing' is the core of stateful agent workflows. Corrective RAG (grade -> rewrite -> retry) is the classic interview whiteboard. | F25: LangGraph tutorial 'Agentic RAG' / 'Adaptive RAG' pages; Self-RAG and CRAG paper abstracts. | G25: 1. route_question node (structured output): direct (chit-chat/meta), retrieve, or clarify (ambiguous). 2. grade_documents node: cheap model labels each chunk relevant/irrelevant in ONE batched call. 3. If no relevant chunks: rewrite_query -> retrieve again, max 2 loops (loop counter in state). 4. check_grounding node after generate: if the answer is not supported by the cited chunks -> regenerate once, else abstain with unanswerable=true. 5. Tests with FakeProvider scripted responses covering: direct, retrieve-ok, rewrite-loop-hits-cap, abstain. | H25: Four graph tests (direct, normal retrieve, rewrite loop capped at 2, abstain) pass, and the golden unanswerable questions now abstain at least 5 of 6 times. | J25: ☐
A26: D22 | B26: 46354 | C26: DocuLens | D26: LangGraph 3: tools, human-in-the-loop interrupt, Postgres checkpointer | E26: Tool calling + human-in-the-loop + persistent state are three named requirements in one card. This is the session that makes 'stateful agent' true. | F26: LangGraph docs: 'Tools'/'ToolNode', 'Persistence' (checkpointers, thread_id), 'Human-in-the-loop' (interrupt, Command(resume=...)); langgraph-checkpoint-postgres README. | G26: 1. Tools (typed, read-only): search_documents(query, filters), get_page_text(document_id, page), list_documents(doc_type). Bind to the answer model; ToolNode executes them. 2. PostgresSaver checkpointer; every request carries thread_id = conversation_id. 3. interrupt() before returning when confidence < 0.6 OR the question asks for a decision (e.g. 'is my claim covered?'): the state is saved and the API returns status=needs_review with the draft. 4. POST /agent/threads/{id}/resume {decision: approve|edit|reject, edited_answer?} resumes with Command(resume=...). 5. Test: pause, restart the API container, resume - the thread continues from the checkpoint. | H26: A low-confidence question pauses with needs_review, survives an API restart, and completes after POST /resume. | J26: ☐
A27: D23 | B27: 46355 | C27: DocuLens | D27: Multi-document comparison: fan-out with Send (map-reduce) | E27: Multi-agent / parallel workflows: fan-out/fan-in is also a backend pattern from your patterns file. Here it solves a real need: comparing documents. | F27: LangGraph docs 'Map-reduce with Send API' and 'Subgraphs'; your backend patterns notes on fan-out/fan-in. | G27: 1. Route compare-type questions to a compare branch. 2. planner node: identify target documents (from metadata) and the aspect to compare. 3. Send one task per document to a per_document subgraph (retrieve within that document -> extract structured findings with citations). 4. aggregate node: builds a comparison table (aspect x document) with citations; abstain per cell if nothing found. 5. Cap fan-out at 5 documents; per-branch timeout; a failed branch shows 'not found' instead of failing the whole answer. | H27: 'Compare exclusions in policy A vs policy B' returns a table with citations from both documents, and the Langfuse trace shows the parallel branches. | I27: Deep-research report mode: a planner writes 3-5 sub-questions, Send fans them out, a writer composes a cited report and a checker deletes unsupported sentences. Keep it only if 3 sample reports pass your grounding check. | J27: ☐
A28: D24 | B28: 46356 | C28: DocuLens | D28: Auth, workspaces and RBAC (tenant isolation) | E28: JWT, RBAC and tenant isolation appear in the full-stack and finance job posts. A RAG system that leaks one customer's chunks to another is the worst-case bug - you must test for it. | F28: FastAPI 'Security - OAuth2 with Password, Bearer with JWT'; OWASP 'Authorization Cheat Sheet' (skim); pwdlib/argon2 README. | G28: 1. users, workspaces, memberships(role: owner|editor|viewer); signup/login returning access (15 min) + refresh (7 days, stored hashed, rotated) tokens. 2. get_current_principal dependency -> (user_id, workspace_id, role). 3. Every query on documents/chunks/jobs/threads filters by workspace_id - put it in the repository layer so it cannot be forgotten. 4. Viewer cannot upload or delete; editor can; owner manages members. 5. Isolation tests: user B cannot see A's documents via /documents, /search, /ask, /agent tools, or by guessing a document id (404, not 403). | H28: The two-user isolation test suite passes for every endpoint, including the agent's tools. | J28: ☐
A29: D25 | B29: 46357 | C29: DocuLens | D29: Production Dockerfiles + GitHub Actions CI | E29: 'Docker, GitHub Actions, CI/CD' are in every post. A green CI with lint, types, tests and an eval smoke test is proof you ship like a professional. | F29: Docker docs 'Multi-stage builds'; uv docs 'Using uv in Docker'; GitHub Actions 'Creating PostgreSQL service containers'. | G29: 1. Multi-stage Dockerfile: builder installs deps with uv into .venv, runtime copies it; non-root user; HEALTHCHECK; pre-download the embedding/reranker models at build time. 2. Same image runs api (uvicorn) and worker (celery) with different commands. 3. CI workflow: ruff, mypy, pytest with postgres(pgvector)+redis service containers, docker build, and an eval smoke test (5 golden questions with FakeProvider asserting the pipeline wiring). 4. Cache uv and Docker layers in CI. 5. README badge. | H29: CI is green on a pull request, the runtime image runs as non-root, and an intentionally broken test makes CI fail. | J29: ☐
A30: D26 | B30: 46358 | C30: DocuLens | D30: Azure foundation (budget first) | E30: 'Familiarity with at least one cloud platform' - and Azure matches your Microsoft background, the Copilot Studio/Fabric posts and the AI-102 cert you will take. | F30: Microsoft Learn: 'Azure Container Apps overview', 'Azure Database for PostgreSQL flexible server - enable pgvector', 'Key Vault basics', 'Cost Management budgets'. Check whether your employer gives a Visual Studio subscription with monthly Azure credit. | G30: 1. Budget + alert at a small monthly cap before creating anything. One region (e.g. Central India). Tag every resource project=doculens. 2. infra/azure/setup.sh using az CLI: resource group, Azure Container Registry, Log Analytics workspace + Container Apps environment, PostgreSQL Flexible Server (Burstable B1ms) with azure.extensions=VECTOR, Storage account + private container, Key Vault. 3. Enable vector extension and run Alembic migrations against Azure PG from your laptop (firewall rule for your IP only). 4. BlobStorage implementation of your Storage interface (SAS URLs for download). 5. docs/cloud-cost.md: every billable resource, its expected monthly cost, and how to stop it. | H30: setup.sh recreates the environment from scratch, migrations run on Azure PG with pgvector, and a budget alert exists. | I30: teardown.sh that deletes the resource group. | J30: ☐
A31: D27 | B31: 46359 | C31: DocuLens | D31: Deploy API + worker to Azure Container Apps | E31: 'Deploy and monitor systems using Docker and cloud platforms' - after this card that sentence on your resume is true. | F31: Microsoft Learn: 'Deploy to Container Apps from ACR', 'Managed identities in Container Apps', 'Container Apps jobs' (for migrations). | G31: 1. Push image to ACR (az acr build or from CI). 2. Container App 'api' (external ingress, min replicas 0-1) and 'worker' (no ingress); Redis as an internal Container App (redis:7) for v1 - write down why not Azure Cache yet (cost). 3. User-assigned managed identity: pull from ACR, read Key Vault secrets, read/write Blob. No secrets in env files or images. 4. Container Apps job for alembic upgrade head. 5. Smoke test script: health, signup, upload, poll job, ask. | H31: A public HTTPS URL passes the smoke test end to end (upload -> ready -> cited answer) and no secret value appears in the Container App configuration. | J31: ☐
A32: D28 | B32: 46361 | C32: DocuLens | D32: Observability, rate limiting and a load test | E32: Logging/observability and p95 latency are what 'production' means in interviews. You will quote these numbers. | F32: OpenTelemetry Python 'Getting started' + Azure Monitor OpenTelemetry distro; k6 or Locust quickstart; Redis 'rate limiting' patterns (token bucket with Lua). | G32: 1. Structured JSON logs with request_id, user/workspace id, route, status, duration; propagate request_id into Celery tasks. 2. OpenTelemetry traces + metrics to Application Insights (HTTP + DB + Redis + Celery); Langfuse stays for LLM traces. 3. Per-workspace rate limit on /ask (Redis token bucket, Lua for atomicity) returning 429 + Retry-After. 4. Load test /search with 20 virtual users for 3 minutes; record p50/p95/error rate; find one bottleneck (e.g. reranker on CPU, pool size) and fix or document it. 5. docs/perf.md with before/after numbers. | H32: docs/perf.md shows p50/p95 for /search under load, one bottleneck you found, and a 429 appears when you exceed the rate limit. | J32: ☐
A33: D29 | B33: 46362 | C33: DocuLens | D33: Release v1: README, design doc, demo, resume bullets | E33: A stranger (the interviewer) must understand the project in 2 minutes. This card turns your work into interview material. | F33: Look at 2-3 well-known open-source RAG repos' READMEs for structure; Excalidraw for the diagram. | G33: 1. README: one-paragraph pitch, architecture diagram (API, worker, Postgres+pgvector, Redis, Blob, LLM router, Langfuse), features, eval tables, 'Design decisions' links, how to run, known limits. 2. docs/design.md: 1-2 pages: problem, architecture, data flow of ingest and ask, trade-offs, what you would do at 100x scale. 3. Record a 3-minute demo video (upload -> job progress -> cited answer with page -> compare question -> needs_review pause -> resume). 4. Tag v1.0. Write 3 resume bullets using only numbers you measured (recall@5, faithfulness, p95, docs ingested). 5. Fill the 'Design Choices' sheet answers for DocuLens. | H33: v1.0 is tagged, README + design.md + demo video are linked, and the resume has 3 DocuLens bullets with real numbers. | J33: ☐
A34: D31 | B34: 46363 | C34: DocuLens | D34: Intake: document classification + per-type extraction with field confidence | E34: Classify -> extract -> validate -> route is the most common enterprise GenAI workflow (intelligent document processing), and 'ingestion with OCR and metadata extraction' is in your top job post. This turns DocuLens from a chatbot into a system that does work. | F34: Pydantic 'JSON Schema' page (model_json_schema); structured outputs docs of OpenAI and Anthropic; Azure AI Document Intelligence 'prebuilt invoice' overview (concept only, it is AI-102 material); Faker README. | G34: 1. Domain (recommended): insurance claims. Document types claim_form, hospital_bill, discharge_summary, other. One Pydantic schema per type (claimant, policy_number, incident_date, diagnosis, line_items[{description, amount}], total, hospital, ...). 2. scripts/make_claims.py: generate 30 synthetic claim packets (one PDF per document, via PyMuPDF insert_textbox or reportlab) with Faker data and a ground-truth JSON next to each. Render 5 of them as images (scanned) to exercise OCR. Plant errors on purpose: total != sum of line items, missing policy number, incident date before policy start. These are your eval labels, for free. 3. classify(document) -> doc_type + confidence: cheap model, structured output, first 2 pages only. 4. extract(document, doc_type) -> each field with value, confidence and source (page, bbox) taken from your D04 blocks. A value that does not appear on the page is marked unverified. 5. validate: Pydantic types + business rules (line items sum to total, dates in range, policy number format). Rule failures are recorded, not raised. 6. Table extractions(document_id, doc_type, schema_version, fields jsonb, field_confidence jsonb, rule_failures jsonb, model, prompt_version) + POST /documents/{id}/extract. Test on 10 packets: print classification accuracy and field exact-match accuracy. | H34: On 10 synthetic claim packets a script prints classification accuracy and field accuracy, and every planted error (bad total, missing policy number, bad date) is caught as a rule failure. | I34: Azure Document Intelligence prebuilt-invoice adapter for hospital bills behind the same interface; compare accuracy and cost with the LLM extractor. | J34: ☐
A35: D32 | B35: 46364 | C35: DocuLens | D35: Workflow engine: definitions, runs and durable steps | E35: Workflow-automation interviews test whether your system survives crashes, retries safely and can be audited. It is also your Copilot Studio / Power Automate experience, rebuilt from the inside - a strong story. | F35: LangGraph docs 'Durable execution' and 'Persistence'; Temporal 'What is durable execution?' (to compare, not to use); Celery 'Periodic tasks' (beat). | G35: 1. workflows(name, version, definition): YAML with a trigger and steps[] (type, config, on_failure, timeout). Seed claim_intake v1: classify -> extract -> validate -> policy_check -> route -> act. 2. workflow_runs(id, workflow, version, document_ids, status pending|running|waiting_review|succeeded|failed|cancelled, current_step, idempotency_key UNIQUE, started_at, ended_at) and step_runs(run_id, step, attempt, status, output jsonb, error, duration_ms). 3. Executor: build a LangGraph StateGraph from the definition (one node per step) with the Postgres checkpointer (thread_id = run_id). It runs inside a Celery task and every node writes its step_runs row. 4. Triggers: (a) upload with ?workflow=claim_intake, (b) POST /triggers/email with a simulated inbound email (JSON + attachments), (c) a Celery beat 'daily_digest' workflow. Each trigger computes an idempotency key (email message-id, or sha256 + workflow). 5. Retry policy per step: transient errors (timeout, 429, 5xx) retry with backoff + jitter; permanent errors (validation, 4xx) fail the run with the error stored. 6. Crash test: kill the worker mid-run; the restarted worker resumes from the last checkpoint and no completed step runs again. | H35: A packet uploaded with workflow=claim_intake produces a run with one step_runs row per step, the same email trigger sent twice creates exactly one run, and a run killed mid-way resumes and finishes. | I35: GET /runs/{id}/timeline returning step durations - you will show it in the demo. | J35: ☐
A36: D33 | B36: 46365 | C36: DocuLens | D36: Decision step: policy-grounded coverage check + human review queue with SLAs | E36: Here RAG and workflow meet: the decision cites the policy clause, and anything uncertain goes to a person. Grounded decisions + human in the loop is exactly what insurance, pharma and finance companies hire for. | F36: Your D21/D22 code (grounding check, interrupt/resume); LangGraph 'Human-in-the-loop' patterns (approve / edit / reject); a short read on straight-through processing (STP) in insurance claims. | G36: 1. policy_check node: retrieve from the claimant's policy wording (metadata filter policy_number -> document) with your hybrid + rerank retriever; structured output {decision: covered|not_covered|unclear, clause_ids, reasons, confidence}; reuse the D10 citation validator. 2. route node is pure code, not an LLM: auto_approve only if every field is verified, there are no rule failures, decision=covered with valid citations and the amount is under a threshold; otherwise needs_review with reason codes. not_covered becomes reject_draft, which still needs a human. 3. Review queue: interrupt() -> run status waiting_review. GET /reviews (filter by reason and age); POST /reviews/{run_id} {approve | edit fields | reject, note}. Edits are stored as corrections - future eval data. 4. SLA: a Celery beat job finds reviews older than N hours, escalates them to the owner role and sends a notification; reviewer and decision go to audit_log. 5. Tests: one packet per route (auto-approve, review for low confidence, review for rule failure, reject draft) and an escalation test with a frozen clock. | H36: Four synthetic packets end in the four expected routes with reason codes, a reviewer's edit resumes the run to completion, and an overdue review is escalated by the scheduler. | J36: ☐
A37: D34 | B37: 46366 | C37: DocuLens | D37: Analytics agent: text-to-SQL over workflow data with guardrails | E37: 'Ask our data in plain English' is one of the most requested enterprise agent features, and the best safety discussion you can have: an LLM writing SQL against production is dangerous unless you constrain it. | F37: sqlglot README (parse, validate); PostgreSQL docs 'Row Security Policies' and 'GRANT'; the idea of execution accuracy from the Spider / BIRD text-to-SQL benchmarks (abstracts only). | G37: 1. Read-only role analytics_ro with SELECT on 3-4 curated views only (v_claims, v_runs, v_reviews) and row-level security on workspace_id (SET app.workspace_id per session). 2. Schema context: YAML with view/column descriptions + 3 example question -> SQL pairs. Schema linking: embed the descriptions and give the model only the views/columns relevant to the question. 3. LangGraph: generate_sql (structured output) -> validate with sqlglot (exactly one SELECT, allow-listed views only, no dangerous functions such as pg_sleep, LIMIT 200 added) -> execute with statement_timeout 3 s -> on error feed the error back, max 2 retries -> answer in words with the SQL shown. 4. POST /analytics/ask, plus a tool query_workflow_data for the DocuLens agent: the agent now chooses between searching documents and querying data. 5. Eval: 25 questions with expected result sets (e.g. 'claims waiting for review more than 24 h, by reason'); metric = execution accuracy. Plus 5 malicious prompts ('drop table claims', 'show workspace B') that must be blocked. | H37: docs/eval/text_to_sql_v1.md records execution accuracy on 25 questions, and all 5 malicious prompts are blocked by validation or database permissions - not by the prompt. | J37: ☐
A38: D35 | B38: 46368 | C38: DocuLens | D38: Actions: outbox, signed webhooks, notifications and audit trail | E38: Automation is only real when it changes something outside your system, and the moment you call other systems you meet duplicates, retries and partial failure. Outbox + signed webhooks is a top backend-pattern interview topic. | F38: microservices.io 'Transactional outbox'; Stripe docs 'Verify webhook signatures' (the HMAC pattern); your LAB03 idempotency notes. | G38: 1. act node writes outbox rows (event_type, payload, event_id) in the SAME transaction as the run state change: claim.approved, claim.rejected, review.required, run.failed. 2. Relay (Celery beat): SELECT ... FOR UPDATE SKIP LOCKED in batches; deliver to subscribed webhooks with an HMAC-SHA256 signature + timestamp header; retry with exponential backoff + jitter; after N attempts dead-letter with the last error; mark published_at. 3. webhook_subscriptions per workspace (url, secret, events) + a tiny receiver app (second container) that verifies the signature and de-duplicates by event_id. 4. Notifications: email through MailHog in Docker Compose (or a Slack incoming webhook) for review.required and escalations. 5. audit_log: append-only record of every human action and external effect (who, what, when, run_id); GET /runs/{id}/audit. 6. Tests: receiver down for 2 minutes -> every event arrives once after it recovers; a tampered signature is rejected; killing the relay mid-batch loses nothing. | H38: With the receiver stopped and restarted, every event arrives exactly once (the receiver's dedup log proves it), a forged signature gets 401, and the audit endpoint shows the full history of a run. | J38: ☐
A39: D36 | B39: 46369 | C39: DocuLens | D39: Workflow eval, ops dashboard and release v1.5 | E39: 'How well does it work?' For automation the numbers are different from RAG: straight-through-processing rate, field accuracy, wrong auto-approvals (must be about 0) and time per packet. These become resume bullets. | F39: Your D16/D17 eval harness; Langfuse datasets; Azure Container Apps 'Revisions' (for the redeploy). | G39: 1. Run all 30 synthetic packets through claim_intake and compare with ground truth: classification accuracy, field accuracy per field, route accuracy, STP rate, false auto-approvals (target 0), mean run time, cost per packet from the usage ledger. 2. docs/eval/workflow_v1.md: the table + 3 failure analyses; fix one cause, rerun, record before/after. 3. Ops page (FastAPI + HTMX or Streamlit): runs by status, review-queue age, STP rate, failures by step. 4. Redeploy to Azure: worker and beat as separate Container Apps; notifications to a real sandbox (Slack or an SMTP test inbox). 5. README: workflow diagram, 'why LangGraph + Celery instead of Temporal or Power Automate', demo video part 2 (packet arrives -> extracted -> policy check with cited clause -> human review -> webhook fires -> analytics question). 6. Tag v1.5 and add 2 resume bullets with measured numbers (e.g. 'X% straight-through, 0 false auto-approvals on 30 labelled packets'). | H39: v1.5 is deployed and tagged, workflow_v1.md shows STP rate, field accuracy and false auto-approvals, and the demo video covers the whole workflow. | J39: ☐
A40: D30 | B40: 46370 | C40: DocuLens | D40: MCP server for DocuLens | E40: 'Developing and hosting MCP servers' is in the AI-engineer posts and is the fastest-growing agent-tool standard. It also lets Claude Code use your project. | F40: modelcontextprotocol.io 'Introduction' + 'Build a server' (Python); FastMCP docs (gofastmcp.com); MCP Inspector. | G40: 1. FastMCP server with tools search_documents(query, filters, k), get_page_text(document_id, page), start_workflow(document_id, workflow), get_run_status(run_id) and ask_data(question) calling your API with a workspace API key (scoped: read + start runs, never approve). 2. Typed inputs/outputs with descriptions written for a model (tool descriptions are prompts). 3. Run over stdio locally and streamable HTTP in Docker. 4. Test with MCP Inspector, then connect it to Claude Code / Claude Desktop and ask a question about your corpus. 5. Log every tool call with the workspace and a request id (audit). | H40: Claude Code (or Claude Desktop) lists your tools, answers a corpus question, starts a claim workflow and reports its status; every tool call appears in your audit log. | J40: ☐
A41: S01 | B41: 46371 | C41: AI SRE Copilot | D41: SRE repo + local Kubernetes (kind) + kubectl drills | E41: Kubernetes basics come up even in AI roles ('how is it deployed?'). kind runs on Docker Desktop, which you already have. | F41: kind quickstart (kind.sigs.k8s.io); Kubernetes docs 'Concepts > Workloads' (Pods, Deployments, Services). | G41: 1. Monorepo: services/, victim-app/, faults/, deploy/, eval/, docs/ (reuse D01 tooling). 2. kind cluster with namespaces victim, platform, observability. 3. Deploy nginx; practise describe, logs, exec, port-forward, rollout restart, scale. 4. Note idle RAM of Docker Desktop with the cluster in docs/decisions/0001-resource-budget.md. | H41: `kubectl get nodes` is Ready, port-forward to nginx works, and the resource-budget note is committed. | J41: ☐
A42: S02 | B42: 46372 | C42: AI SRE Copilot | D42: Victim app: gateway -> api -> Postgres on the cluster | E42: You need something real to break. A 3-service app gives realistic failure chains (dependency down, readiness). | F42: Kubernetes docs 'Configure Liveness, Readiness and Startup Probes', 'Resource Management for Pods and Containers'. | G42: 1. FastAPI api (/health/live, /health/ready, /items backed by Postgres) and gateway proxying to it. 2. Manifests: Deployments with probes, requests/limits, annotation sre-copilot/baseline-replicas; Services; Postgres StatefulSet + PVC + Secret. 3. Load images into kind (kind load docker-image). | H42: A request through the gateway returns data from Postgres inside the cluster and all pods are Ready. | J42: ☐
A43: S03 | B43: 46373 | C43: AI SRE Copilot | D43: Fault knobs + one-command fault scripts with undo | E43: Your eval scenarios (F1-F8) depend on reliable, reversible faults. Interviewers love 'how did you test failure?'. | F43: Kubernetes docs 'Debug Running Pods'; your old master plan Phase 0 (S005-S006). | G43: 1. Env-guarded toggles on api: crash, memory leak, CPU spin, latency, readiness fail. 2. faults/*.sh with undo: kill-pod, oom, cpu-spin, bad-image, db-down (scale Postgres to 0), bad-config, readiness-fail, latency. 3. Each script prints what to watch (kubectl get pods -w, events). | H43: Every fault triggers and undoes with one command, and you can explain how limits change the OOM and CPU behaviour. | J43: ☐
A44: S04 | B44: 46375 | C44: AI SRE Copilot | D44: Prometheus + Alertmanager -> webhook, alert fixtures | E44: Alerts are the trigger of the whole agent. PromQL and alert routing are standard SRE/backend interview topics. | F44: kube-prometheus-stack chart README; Prometheus 'Alerting rules'; Alertmanager 'Configuration > webhook_config'. | G44: 1. Helm install kube-prometheus-stack with laptop-sized values (disable what you do not need). 2. PrometheusRules: PodCrashLooping, PodNotReady, ContainerOOMKilled, ImagePullBackOff. 3. Route alerts to a webhook URL; capture real payloads into fixtures/alertmanager_*.json. | H44: Each rule fires for its fault in 3 of 3 runs and real webhook payloads are saved as fixtures. | J44: ☐
A45: S05 | B45: 46376 | C45: AI SRE Copilot | D45: alert-receiver + incident store (event-style records) | E45: Webhook receivers, validation and de-duplication are backend patterns you can explain with this code. | F45: Alertmanager webhook payload format; your D12/D13 idempotency notes. | G45: 1. FastAPI POST /webhooks/alertmanager with Pydantic models; raw payload stored. 2. Dedup by fingerprint within 30 min -> one incident; unsupported alertnames stored as unsupported. 3. incidents/incident_events tables with event_id, incident_id, correlation_id, schema_version (seams for Kafka later). 4. Structured logs carrying correlation_id. | H45: 10 identical webhooks create exactly 1 incident and 9 recorded duplicates; an unknown alert is stored as unsupported. | J45: ☐
A46: S06 | B46: 46377 | C46: AI SRE Copilot | D46: Read-only Kubernetes tools + tool registry | E46: Tool calling with permissions: an agent must only be able to read. Least privilege is a security interview favourite. | F46: kubernetes Python client docs; Kubernetes 'Using RBAC Authorization'. | G46: 1. Typed tools: get_pod_status, get_events, get_logs(tail, since), get_rollout_history, get_resource_usage. 2. get_recent_changes(namespace, since): rollout history plus the diff of image tag, env vars and ConfigMaps between the last revisions - most incidents follow a change (the 'PR review' idea, aimed at deploys). 3. ServiceAccount + ClusterRole with get/list/watch only. 4. Registry: name, JSON schema, risk=read, timeout; evidence items stored immutable with ids. 5. Fake k8s client for tests. | H46: `kubectl auth can-i patch deployments --as=system:serviceaccount:platform:evidence` says no, and tool tests pass with the fake client. | J46: ☐
A47: S07 | B47: 46378 | C47: AI SRE Copilot | D47: Metrics tool, evidence caps and truncation | E47: Bounding agent cost and context is a real production concern (token budgets, tool-call caps). | F47: Prometheus HTTP API docs; PromQL basics (rate, increase, container_memory_working_set_bytes). | G47: 1. query_prometheus with allow-listed PromQL templates only (no free-form queries from the model). 2. Evidence caps: 12 tool calls / 60 s per incident; truncated flag; log line caps. 3. Token accounting per incident. | H47: The OOM scenario evidence includes a memory-trend item with an id, and a forced cap ends with truncated=true rather than an error. | J47: ☐
... A69: S29 | B69: 46404 | C69: AI SRE Copilot | D69: Stage 2 buffer | E69: Every plan slips. This session absorbs it. | F69: - | G69: 1. Finish any carry-over from Stage 2. If nothing is left: write a blog post 'How I evaluated an SRE agent'. | H69: No open Stage 2 carry-over remains. | J69: ☐
A70: T01 | B70: 46405 | C70: PDF Translator | D70: Translator app + paragraph regions | F70: Use the tutor prompt with the card title to get a 10-minute briefing before you build. | G70: 1. Create apps/translator next to DocuLens in one monorepo; move shared code (PDF extraction, OCR, storage, auth, model router, outbox) into packages/ so both apps import it. 2. Reuse D04 blocks; group spans into paragraph regions with bbox, font, alignment; regions table linked to document/page. | H70: A fixture page produces paragraph regions (not per-line fragments) with bboxes you checked visually. | J70: ☐
A71: T02 | B71: 46406 | C71: PDF Translator | D71: Region translation through the router (structured, batched) | F71: Use the tutor prompt with the card title to get a 10-minute briefing before you build. | G71: 1. Capability 'translate' in models.yaml. 2. Batch regions per page; schema {region_id, translated_text}; validate every id returns. | H71: A page of regions translates in one call per batch with all ids accounted for. | J71: ☐
A72: T03 | B72: 46407 | C72: PDF Translator | D72: Overlay renderer v1 (redact + insert) | F72: Use the tutor prompt with the card title to get a 10-minute briefing before you build. | G72: 1. page.add_redact_annot + apply_redactions to remove source text; insert_htmlbox/insert_textbox for the translation. 2. Same page count, selectable text. | H72: The output PDF opens, keeps page count, and translated text is selectable in roughly the original positions. | J72: ☐
A73: T04 | B73: 46408 | C73: PDF Translator | D73: Fit engine: wrap, shrink-to-fit, fit_status | F73: Use the tutor prompt with the card title to get a 10-minute briefing before you build. | G73: 1. Measure text; wrap to bbox; shrink within min/max font size. 2. fit_status fit|shrunk|overflow|review_required per region. | H73: Tests cover fit, shrunk and overflow, and every rendered region has a fit_status. | J73: ☐
A74: T05 | B74: 46410 | C74: PDF Translator | D74: Async translation job with per-page progress | F74: Use the tutor prompt with the card title to get a 10-minute briefing before you build. | G74: 1. POST /documents/{id}/translations -> 202; Celery chain per page; progress events. 2. Idempotency key on the request. | H74: A 10-page job shows per-page progress and a duplicate request reuses the same job. | J74: ☐
A75: T06 | B75: 46411 | C75: PDF Translator | D75: Previews + secure download | F75: Use the tutor prompt with the card title to get a 10-minute briefing before you build. | G75: 1. Render original/output pages to PNG; side-by-side endpoint. 2. Blob SAS download URL valid for 10 minutes, owner only. | H75: The owner sees side-by-side previews and a stranger's request gets 404. | J75: ☐
A76: T07 | B76: 46412 | C76: PDF Translator | D76: Glossary: table, CRUD, CSV import | F76: Use the tutor prompt with the card title to get a 10-minute briefing before you build. | G76: 1. glossary_entries per workspace + language pair; CRUD with RBAC; CSV import with row validation. | H76: A 20-row CSV imports with clear errors for bad rows. | J76: ☐
A77: T08 | B77: 46413 | C77: PDF Translator | D77: Translation memory + scoped retrieval (pgvector) | F77: Use the tutor prompt with the card title to get a 10-minute briefing before you build. | G77: 1. Approved segments -> translation_memory with embeddings. 2. Retrieve by workspace + language pair + approved state. | H77: A two-workspace test proves memory never leaks across workspaces. | J77: ☐
A78: T09 | B78: 46414 | C78: PDF Translator | D78: Constraint-aware translation + glossary compliance validator | F78: Use the tutor prompt with the card title to get a 10-minute briefing before you build. | G78: 1. Inject retrieved terms/memory ids into the prompt; output lists applied ids. 2. Validator flags a required term missing in output. | H78: A deliberately wrong term is flagged and routed to review. | J78: ☐
A79: T10 | B79: 46415 | C79: PDF Translator | D79: Translation eval | F79: Use the tutor prompt with the card title to get a 10-minute briefing before you build. | G79: 1. 20 reference segments; chrF (sacrebleu) + glossary compliance %; LLM judge for fluency on a sample. 2. docs/eval/translation_v1.md. | H79: The translation eval report shows chrF, compliance % and judge scores. | J79: ☐
A80: T11 | B80: 46417 | C80: PDF Translator | D80: LangGraph translation workflow | F80: Use the tutor prompt with the card title to get a 10-minute briefing before you build. | G80: 1. Nodes: classify page -> extract/OCR -> retrieve context -> translate -> validate -> fit -> (review gate) -> render. 2. Retry fit once with a different strategy. | H80: A native PDF runs through the graph end to end and an overflow region pauses at the review gate. | J80: ☐
A81: T12 | B81: 46418 | C81: PDF Translator | D81: Review API: edit, approve, new version, feed memory | F81: Use the tutor prompt with the card title to get a 10-minute briefing before you build. | G81: 1. PATCH region -> approve; re-render creates version 2 (v1 immutable). 2. Approved edits become translation memory. | H81: Editing a region produces v2, v1 is unchanged, and the edit appears in memory retrieval. | J81: ☐
... A93: T24 | B93: 46432 | C93: PDF Translator | D93: Stage 3 buffer | F93: Use the tutor prompt with the card title to get a 10-minute briefing before you build. | G93: 1. Finish carry-over; otherwise write a blog post 'Evaluating a RAG system with numbers'. | H93: No open Stage 3 carry-over remains. | J93: ☐

Sheet LARP Bank
A1: LARP bank: teach -> quiz -> interview -> scenario
A2: Answer aloud BEFORE reading the key. Score 0 (blank) / 1 (partial) / 2 (interview-ready). Topics L55-L70 are question-only: run the tutor prompt. Sorted by planned date.
A4: ID | B4: Planned | C4: Topic | D4: # | E4: Type | F4: Question / item | G4: Answer key (say it in your own words) | H4: My score 0-2 | I4: Revisit
A5: L01 | B5: 46330 | C5: Python async/await and the event loop | E5: TEACH | F5: Learn these first: - Concurrency vs parallelism; I/O-bound vs CPU-bound work. - Coroutines, the event loop, await as a yield point; asyncio.gather / TaskGroup. - Blocking calls inside async code and how to offload them (to_thread / run_in_executor). - The GIL: what it blocks and what it does not. | G5: Say it like a senior: "Most of our latency was I/O - DB, embeddings, LLM calls - so async gave us concurrency cheaply; the one CPU-heavy step, reranking, I moved to a thread so it couldn't block the loop."
A6: L01 | C6: Python async/await and the event loop | D6: 1 | E6: Concept | F6: What is the difference between concurrency and parallelism? | G6: Concurrency = several tasks make progress in overlapping time (interleaving, e.g. while one waits on I/O). Parallelism = tasks literally run at the same instant on different cores. asyncio gives concurrency on one thread; multiprocessing gives parallelism. | I6: ☐
A7: L01 | C7: Python async/await and the event loop | D7: 2 | E7: Concept | F7: What actually happens when a coroutine hits `await`? | G7: It suspends and hands control back to the event loop, which runs other ready tasks; when the awaited I/O completes, the loop resumes the coroutine. Nothing runs 'in the background' unless something awaits. | I7: ☐
A8: L01 | C8: Python async/await and the event loop | D8: 3 | E8: Concept | F8: What does the GIL prevent, and why does async still help for web servers? | G8: The GIL lets only one thread execute Python bytecode at a time, so CPU-bound threads do not run in parallel. Web servers are mostly I/O-bound (DB, HTTP, LLM calls); while waiting, the GIL is released / the loop switches tasks, so throughput rises. | I8: ☐
A9: L01 | C9: Python async/await and the event loop | D9: 4 | E9: Concept | F9: gather vs TaskGroup? | G9: asyncio.gather runs awaitables concurrently and returns results (return_exceptions option). TaskGroup (3.11+) gives structured concurrency: if one task fails, the others are cancelled and the error is raised as an ExceptionGroup - safer default. | I9: ☐
A10: L01 | C10: Python async/await and the event loop | D10: 5 | E10: Interview | F10: You call a slow synchronous library inside an async FastAPI endpoint. What happens? | G10: It blocks the event loop: every other request on that worker stalls. Fix: make the endpoint `def` (FastAPI runs it in a threadpool), or wrap the call with anyio.to_thread / run_in_executor, or use an async client. In DocuLens the cross-encoder reranker runs in a thread for exactly this reason. | I10: ☐
A11: L01 | C11: Python async/await and the event loop | D11: 6 | E11: Interview | F11: How would you limit concurrency of outbound LLM calls? | G11: asyncio.Semaphore around the call (e.g. 5 in flight), plus timeouts (asyncio.timeout) and retries with backoff; across processes use a Redis-based limiter. | I11: ☐
A12: L01 | C12: Python async/await and the event loop | D12: 7 | E12: Interview | F12: When would you use multiprocessing instead of asyncio? | G12: CPU-bound work (PDF rendering, OCR, embeddings on CPU) - separate processes bypass the GIL. In practice push that work to a Celery worker pool rather than doing it in the API process. | I12: ☐
A13: L01 | C13: Python async/await and the event loop | D13: 8 | E13: Scenario | F13: Your FastAPI service's latency spikes for ALL endpoints whenever one user uploads a big PDF. Diagnose. | G13: Suspect blocking work on the event loop (PDF parsing in an async def). Confirm with py-spy / loop lag metrics; move parsing to a Celery worker (202 + job id), or at least to a thread; add a request size cap. | I13: ☐
A14: L01 | C14: Python async/await and the event loop | D14: 9 | E14: Scenario | F14: A batch job makes 2,000 HTTP calls sequentially and takes 30 minutes. Speed it up safely. | G14: Use an async client with gather/TaskGroup + a semaphore (e.g. 20 concurrent) to respect rate limits; per-call timeout; retry 429/5xx with jittered backoff; idempotent writes so retries are safe; progress checkpointing. | I14: ☐
A15: L02 | B15: 46331 | C15: FastAPI internals: dependency injection, Pydantic v2, sync vs async | E15: TEACH | F15: Learn these first: - Request lifecycle: ASGI (Uvicorn) -> Starlette routing -> dependencies -> endpoint -> response model. - Depends(): scoped resources (DB session), auth, yield dependencies for cleanup. - Pydantic v2 validation and serialisation; response_model filtering. - def vs async def endpoints; lifespan for startup resources. | G15: Say it like a senior: "I keep endpoints thin: dependencies give me the principal and a session, a service layer does the work, and response models guarantee we never leak internal fields."
A16: L02 | C16: FastAPI internals: dependency injection, Pydantic v2, sync vs async | D16: 1 | E16: Concept | F16: What is ASGI and where does Uvicorn fit? | G16: ASGI is the async interface between web servers and Python apps (successor to WSGI, supports websockets/streaming). Uvicorn is the ASGI server that speaks HTTP and calls the FastAPI (Starlette) app. | I16: ☐
A17: L02 | C17: FastAPI internals: dependency injection, Pydantic v2, sync vs async | D17: 2 | E17: Concept | F17: How does FastAPI's dependency injection work? | G17: Endpoint parameters declared with Depends(fn) are resolved per request; dependencies can depend on others (a graph), are cached within a request, and `yield` dependencies run cleanup after the response (e.g. close DB session). | I17: ☐
A18: L02 | C18: FastAPI internals: dependency injection, Pydantic v2, sync vs async | D18: 3 | E18: Concept | F18: def vs async def endpoints in FastAPI? | G18: async def runs on the event loop - must not block. Plain def runs in a threadpool, so blocking code is OK there. Choose based on whether your libraries are async. | I18: ☐
A19: L02 | C19: FastAPI internals: dependency injection, Pydantic v2, sync vs async | D19: 4 | E19: Concept | F19: What does response_model give you? | G19: Output validation and filtering (e.g. never leaking password_hash), OpenAPI docs, and serialisation consistency. | I19: ☐
A20: L02 | C20: FastAPI internals: dependency injection, Pydantic v2, sync vs async | D20: 5 | E20: Interview | F20: How do you manage a DB session per request? | G20: A yield dependency creates an AsyncSession from a sessionmaker, yields it, commits/rolls back and closes in finally. Engine + pool are created once in lifespan. | I20: ☐
A21: L02 | C21: FastAPI internals: dependency injection, Pydantic v2, sync vs async | D21: 6 | E21: Interview | F21: How do you load an ML model once rather than per request? | G21: Lifespan context manager on app startup stores it on app.state (or a module singleton); dependencies read it. Avoid loading in the endpoint. | I21: ☐
A22: L02 | C22: FastAPI internals: dependency injection, Pydantic v2, sync vs async | D22: 7 | E22: Interview | F22: How do you version and document an API in FastAPI? | G22: APIRouter prefixes (/v1), OpenAPI generated from type hints and Pydantic models, tags, examples; breaking changes go to /v2 while v1 is maintained. | I22: ☐
A23: L02 | C23: FastAPI internals: dependency injection, Pydantic v2, sync vs async | D23: 8 | E23: Scenario | F23: Users report 500s that only happen under load; logs show 'QueuePool limit reached'. What is wrong? | G23: DB connection pool exhaustion: sessions held too long (e.g. across an LLM call), pool too small, or leaked sessions. Fix: don't hold a session across slow I/O, size pool vs workers, set pool_timeout, check that yield dependency closes sessions. | I23: ☐
